Workbook

Sheet Summary
B1: Sharpe and Sortino
B2: Master Error Check Cell | D2: =+'Error Checking'!B2 -> 0
B4: Actual / Forecast | D4: Actual | E4: Actual | F4: Actual | G4: Actual | H4: Actual | I4: Actual | J4: Forecast | K4: Forecast | L4: Forecast | M4: Forecast | N4: Forecast | O4: Forecast | P4: Forecast | Q4: Forecast | R4: Forecast | S4: Forecast | T4: Forecast | U4: Forecast | V4: Forecast
B5: Week Number | D5: 1 | E5: 2 | F5: 3 | G5: 4 | H5: 5 | I5: 6 | J5: 7 | K5: 8 | L5: 9 | M5: 10 | N5: 11 | O5: 12 | P5: 13 | Q5: 14 | R5: 15 | S5: 16 | T5: 17 | U5: 18 | V5: 19
B6: Week Beginning | D6: =+D7-6 -> 45221 | E6: =+E7-6 -> 45228 | F6: =+F7-6 -> 45235 | G6: =+G7-6 -> 45242 | H6: =+H7-6 -> 45249 | I6: =+I7-6 -> 45256 | J6: =+J7-6 -> 45263 | K6: =+K7-6 -> 45270 | ... V6: =+V7-6 -> 45347
B7: Week Ending | D7: =+E6-1 -> 45227 | E7: =+F6-1 -> 45234 | F7: =+G6-1 -> 45241 | G7: =+H6-1 -> 45248 | H7: =+I6-1 -> 45255 | I7: =+J6-1 -> 45262 | J7: =+K6-1 -> 45269 | K7: =+L6-1 -> 45276 | ... U7: =+V6-1 -> 45346 | V7: =MAX('Forecast 1'!7:7) -> 45353
B9: Cash Balance
B10: Beginning Cash | D10: =IF($B10='Forecast 1'!$B10,INDEX('Forecast 1'!$1:$1048576,MATCH('Forecast 1'!$B10,'Forecast 1'!$B:$B,0),MATCH('Forecast 1'!D$7,'Forecast 1'!$7:$7,0)),"Mismatch") -> 345580 | E10: =+D12 -> 210210 | F10: =+E12 -> 174090 | G10: =+F12 -> 239110 | H10: =+G12 -> 43360 | I10: =+H12 -> 325260 | J10: =+I12 -> 215160 | K10: =+J12 -> 112041.67 | L10: =+K12 -> 156995.28 | ... V10: =+U12 -> 580273.04
B11: Change in Cash | D11: =+D60 -> -135370 | E11: =+E60 -> -36120 | F11: =+F60 -> 65020 | G11: =+G60 -> -195750 | H11: =+H60 -> 281900 | I11: =+I60 -> -110100 | J11: =+J60 -> -103118.33 | K11: =+K60 -> 44953.611 | ... V11: =+V60 -> -289083.47
B12: Ending Cash | D12: =SUM(D10:D11) -> 210210 | E12: =SUM(E10:E11) -> 174090 | F12: =SUM(F10:F11) -> 239110 | G12: =SUM(G10:G11) -> 43360 | H12: =SUM(H10:H11) -> 325260 | I12: =SUM(I10:I11) -> 215160 | J12: =SUM(J10:J11) -> 112041.67 | K12: =SUM(K10:K11) -> 156995.28 | ... V12: =SUM(V10:V11) -> 291189.57
B13: Per Bank Statement | D13: =IF($B13='Forecast 1'!$B13,INDEX('Forecast 1'!$1:$1048576,MATCH('Forecast 1'!$B13,'Forecast 1'!$B:$B,0),MATCH('Forecast 1'!D$7,'Forecast 1'!$7:$7,0)),"Mismatch") -> 210210 | E13: =IF($B13='Forecast 1'!$B13,INDEX('Forecast 1'!$1:$1048576,MATCH('Forecast 1'!$B13,'Forecast 1'!$B:$B,0),MATCH('Forecast 1'!E$7,'Forecast 1'!$7:$7,0)),"Mismatch") -> 174090 | F13: =IF($B13='Forecast 1'!$B13,INDEX('Forecast 1'!$1:$1048576,MATCH('Forecast 1'!$B13,'Forecast 1'!$B:$B,0),MATCH('Forecast 1'!F$7,'Forecast 1'!$7:$7,0)),"Mismatch") -> 239110 | G13: =IF($B13='Forecast 1'!$B13,INDEX('Forecast 1'!$1:$1048576,MATCH('Forecast 1'!$B13,'Forecast 1'!$B:$B,0),MATCH('Forecast 1'!G$7,'Forecast 1'!$7:$7,0)),"Mismatch") -> 43360 | H13: =IF($B13='Forecast 1'!$B13,INDEX('Forecast 1'!$1:$1048576,MATCH('Forecast 1'!$B13,'Forecast 1'!$B:$B,0),MATCH('Forecast 1'!H$7,'Forecast 1'!$7:$7,0)),"Mismatch") -> 325260 | I13: =IF($B13='Forecast 1'!$B13,INDEX('Forecast 1'!$1:$1048576,MATCH('Forecast 1'!$B13,'Forecast 1'!$B:$B,0),MATCH('Forecast 1'!I$7,'Forecast 1'!$7:$7,0)),"Mismatch") -> 215160 | J13: =IF($B13='Forecast 1'!$B13,INDEX('Forecast 1'!$1:$1048576,MATCH('Forecast 1'!$B13,'Forecast 1'!$B:$B,0),MATCH('Forecast 1'!J$7,'Forecast 1'!$7:$7,0)),"Mismatch") -> 0 | K13: =IF($B13='Forecast 1'!$B13,INDEX('Forecast 1'!$1:$1048576,MATCH('Forecast 1'!$B13,'Forecast 1'!$B:$B,0),MATCH('Forecast 1'!K$7,'Forecast 1'!$7:$7,0)),"Mismatch") -> 0 | ... V13: =IF($B13='Forecast 1'!$B13,INDEX('Forecast 1'!$1:$1048576,MATCH('Forecast 1'!$B13,'Forecast 1'!$B:$B,0),MATCH('Forecast 1'!V$7,'Forecast 1'!$7:$7,0)),"Mismatch") -> 0
B14: Double-Check | D14: =IF(D4="Forecast",0,D13-D12) -> 0 | E14: =IF(E4="Forecast",0,E13-E12) -> 0 | F14: =IF(F4="Forecast",0,F13-F12) -> 0 | G14: =IF(G4="Forecast",0,G13-G12) -> 0 | H14: =IF(H4="Forecast",0,H13-H12) -> 0 | I14: =IF(I4="Forecast",0,I13-I12) -> 0 | J14: =IF(J4="Forecast",0,J13-J12) -> 0 | K14: =IF(K4="Forecast",0,K13-K12) -> 0 | ... V14: =IF(V4="Forecast",0,V13-V12) -> 0
B15: Last Week's Forecast | D15: =IF($B15='Forecast 1'!$B15,INDEX('Forecast 1'!$1:$1048576,MATCH('Forecast 1'!$B15,'Forecast 1'!$B:$B,0),MATCH('Forecast 1'!D$7,'Forecast 1'!$7:$7,0)),"Mismatch") -> 0 | E15: =IF($B15='Forecast 1'!$B15,INDEX('Forecast 1'!$1:$1048576,MATCH('Forecast 1'!$B15,'Forecast 1'!$B:$B,0),MATCH('Forecast 1'!E$7,'Forecast 1'!$7:$7,0)),"Mismatch") -> 0 | F15: =IF($B15='Forecast 1'!$B15,INDEX('Forecast 1'!$1:$1048576,MATCH('Forecast 1'!$B15,'Forecast 1'!$B:$B,0),MATCH('Forecast 1'!F$7,'Forecast 1'!$7:$7,0)),"Mismatch") -> 0 | G15: =IF($B15='Forecast 1'!$B15,INDEX('Forecast 1'!$1:$1048576,MATCH('Forecast 1'!$B15,'Forecast 1'!$B:$B,0),MATCH('Forecast 1'!G$7,'Forecast 1'!$7:$7,0)),"Mismatch") -> 0 | H15: =IF($B15='Forecast 1'!$B15,INDEX('Forecast 1'!$1:$1048576,MATCH('Forecast 1'!$B15,'Forecast 1'!$B:$B,0),MATCH('Forecast 1'!H$7,'Forecast 1'!$7:$7,0)),"Mismatch") -> 0 | I15: =IF($B15='Forecast 1'!$B15,INDEX('Forecast 1'!$1:$1048576,MATCH('Forecast 1'!$B15,'Forecast 1'!$B:$B,0),MATCH('Forecast 1'!I$7,'Forecast 1'!$7:$7,0)),"Mismatch") -> 0 | J15: =IF($B15='Forecast 1'!$B15,INDEX('Forecast 1'!$1:$1048576,MATCH('Forecast 1'!$B15,'Forecast 1'!$B:$B,0),MATCH('Forecast 1'!J$7,'Forecast 1'!$7:$7,0)),"Mismatch") -> 0 | K15: =IF($B15='Forecast 1'!$B15,INDEX('Forecast 1'!$1:$1048576,MATCH('Forecast 1'!$B15,'Forecast 1'!$B:$B,0),MATCH('Forecast 1'!K$7,'Forecast 1'!$7:$7,0)),"Mismatch") -> 0 | ... V15: =IF($B15='Forecast 1'!$B15,INDEX('Forecast 1'!$1:$1048576,MATCH('Forecast 1'!$B15,'Forecast 1'!$B:$B,0),MATCH('Forecast 1'!V$7,'Forecast 1'!$7:$7,0)),"Mismatch") -> 0
B17: Cash Inflows
B18: Invoice Revenue Receipts | D18: =IF($B18='Forecast 1'!$B18,INDEX('Forecast 1'!$1:$1048576,MATCH('Forecast 1'!$B18,'Forecast 1'!$B:$B,0),MATCH('Forecast 1'!D$7,'Forecast 1'!$7:$7,0)),"Mismatch") -> 0 | E18: =IF($B18='Forecast 1'!$B18,INDEX('Forecast 1'!$1:$1048576,MATCH('Forecast 1'!$B18,'Forecast 1'!$B:$B,0),MATCH('Forecast 1'!E$7,'Forecast 1'!$7:$7,0)),"Mismatch") -> 372100 | F18: =IF($B18='Forecast 1'!$B18,INDEX('Forecast 1'!$1:$1048576,MATCH('Forecast 1'!$B18,'Forecast 1'!$B:$B,0),MATCH('Forecast 1'!F$7,'Forecast 1'!$7:$7,0)),"Mismatch") -> 210150 | G18: =IF($B18='Forecast 1'!$B18,INDEX('Forecast 1'!$1:$1048576,MATCH('Forecast 1'!$B18,'Forecast 1'!$B:$B,0),MATCH('Forecast 1'!G$7,'Forecast 1'!$7:$7,0)),"Mismatch") -> 0 | H18: =IF($B18='Forecast 1'!$B18,INDEX('Forecast 1'!$1:$1048576,MATCH('Forecast 1'!$B18,'Forecast 1'!$B:$B,0),MATCH('Forecast 1'!H$7,'Forecast 1'!$7:$7,0)),"Mismatch") -> 361430 | I18: =IF($B18='Forecast 1'!$B18,INDEX('Forecast 1'!$1:$1048576,MATCH('Forecast 1'!$B18,'Forecast 1'!$B:$B,0),MATCH('Forecast 1'!I$7,'Forecast 1'!$7:$7,0)),"Mismatch") -> 68440 | J18: =IF($B18='Forecast 1'!$B18,INDEX('Forecast 1'!$1:$1048576,MATCH('Forecast 1'!$B18,'Forecast 1'!$B:$B,0),MATCH('Forecast 1'!J$7,'Forecast 1'!$7:$7,0)),"Mismatch") -> 330000 | K18: =IF($B18='Forecast 1'!$B18,INDEX('Forecast 1'!$1:$1048576,MATCH('Forecast 1'!$B18,'Forecast 1'!$B:$B,0),MATCH('Forecast 1'!K$7,'Forecast 1'!$7:$7,0)),"Mismatch") -> 120000 | ... V18: =IF($B18='Forecast 1'!$B18,INDEX('Forecast 1'!$1:$1048576,MATCH('Forecast 1'!$B18,'Forecast 1'!$B:$B,0),MATCH('Forecast 1'!V$7,'Forecast 1'!$7:$7,0)),"Mismatch") -> 0
B19: Other Receipts | D19: =IF($B19='Forecast 1'!$B19,INDEX('Forecast 1'!$1:$1048576,MATCH('Forecast 1'!$B19,'Forecast 1'!$B:$B,0),MATCH('Forecast 1'!D$7,'Forecast 1'!$7:$7,0)),"Mismatch") -> 0 | E19: =IF($B19='Forecast 1'!$B19,INDEX('Forecast 1'!$1:$1048576,MATCH('Forecast 1'!$B19,'Forecast 1'!$B:$B,0),MATCH('Forecast 1'!E$7,'Forecast 1'!$7:$7,0)),"Mismatch") -> 0 | F19: =IF($B19='Forecast 1'!$B19,INDEX('Forecast 1'!$1:$1048576,MATCH('Forecast 1'!$B19,'Forecast 1'!$B:$B,0),MATCH('Forecast 1'!F$7,'Forecast 1'!$7:$7,0)),"Mismatch") -> 0 | G19: =IF($B19='Forecast 1'!$B19,INDEX('Forecast 1'!$1:$1048576,MATCH('Forecast 1'!$B19,'Forecast 1'!$B:$B,0),MATCH('Forecast 1'!G$7,'Forecast 1'!$7:$7,0)),"Mismatch") -> 0 | H19: =IF($B19='Forecast 1'!$B19,INDEX('Forecast 1'!$1:$1048576,MATCH('Forecast 1'!$B19,'Forecast 1'!$B:$B,0),MATCH('Forecast 1'!H$7,'Forecast 1'!$7:$7,0)),"Mismatch") -> 0 | I19: =IF($B19='Forecast 1'!$B19,INDEX('Forecast 1'!$1:$1048576,MATCH('Forecast 1'!$B19,'Forecast 1'!$B:$B,0),MATCH('Forecast 1'!I$7,'Forecast 1'!$7:$7,0)),"Mismatch") -> 0 | J19: =IF($B19='Forecast 1'!$B19,INDEX('Forecast 1'!$1:$1048576,MATCH('Forecast 1'!$B19,'Forecast 1'!$B:$B,0),MATCH('Forecast 1'!J$7,'Forecast 1'!$7:$7,0)),"Mismatch") -> 0 | K19: =IF($B19='Forecast 1'!$B19,INDEX('Forecast 1'!$1:$1048576,MATCH('Forecast 1'!$B19,'Forecast 1'!$B:$B,0),MATCH('Forecast 1'!K$7,'Forecast 1'!$7:$7,0)),"Mismatch") -> 0 | ... V19: =IF($B19='Forecast 1'!$B19,INDEX('Forecast 1'!$1:$1048576,MATCH('Forecast 1'!$B19,'Forecast 1'!$B:$B,0),MATCH('Forecast 1'!V$7,'Forecast 1'!$7:$7,0)),"Mismatch") -> 0
B21: Total Cash Inflows | D21: =SUM(D18:D20) -> 0 | E21: =SUM(E18:E20) -> 372100 | F21: =SUM(F18:F20) -> 210150 | G21: =SUM(G18:G20) -> 0 | H21: =SUM(H18:H20) -> 361430 | I21: =SUM(I18:I20) -> 68440 | J21: =SUM(J18:J20) -> 330000 | K21: =SUM(K18:K20) -> 120000 | ... V21: =SUM(V18:V20) -> 0
B23: Operating Cash Outflows
B24: Accounts Payable | D24: =IF($B24='Forecast 1'!$B24,INDEX('Forecast 1'!$1:$1048576,MATCH('Forecast 1'!$B24,'Forecast 1'!$B:$B,0),MATCH('Forecast 1'!D$7,'Forecast 1'!$7:$7,0)),"Mismatch") -> -33620 | E24: =IF($B24='Forecast 1'!$B24,INDEX('Forecast 1'!$1:$1048576,MATCH('Forecast 1'!$B24,'Forecast 1'!$B:$B,0),MATCH('Forecast 1'!E$7,'Forecast 1'!$7:$7,0)),"Mismatch") -> -83210 | F24: =IF($B24='Forecast 1'!$B24,INDEX('Forecast 1'!$1:$1048576,MATCH('Forecast 1'!$B24,'Forecast 1'!$B:$B,0),MATCH('Forecast 1'!F$7,'Forecast 1'!$7:$7,0)),"Mismatch") -> -69810 | G24: =IF($B24='Forecast 1'!$B24,INDEX('Forecast 1'!$1:$1048576,MATCH('Forecast 1'!$B24,'Forecast 1'!$B:$B,0),MATCH('Forecast 1'!G$7,'Forecast 1'!$7:$7,0)),"Mismatch") -> -40140 | H24: =IF($B24='Forecast 1'!$B24,INDEX('Forecast 1'!$1:$1048576,MATCH('Forecast 1'!$B24,'Forecast 1'!$B:$B,0),MATCH('Forecast 1'!H$7,'Forecast 1'!$7:$7,0)),"Mismatch") -> -18680 | I24: =IF($B24='Forecast 1'!$B24,INDEX('Forecast 1'!$1:$1048576,MATCH('Forecast 1'!$B24,'Forecast 1'!$B:$B,0),MATCH('Forecast 1'!I$7,'Forecast 1'!$7:$7,0)),"Mismatch") -> -88580 | J24: =IF($B24='Forecast 1'!$B24,INDEX('Forecast 1'!$1:$1048576,MATCH('Forecast 1'!$B24,'Forecast 1'!$B:$B,0),MATCH('Forecast 1'!J$7,'Forecast 1'!$7:$7,0)),"Mismatch") -> -800 | K24: =IF($B24='Forecast 1'!$B24,INDEX('Forecast 1'!$1:$1048576,MATCH('Forecast 1'!$B24,'Forecast 1'!$B:$B,0),MATCH('Forecast 1'!K$7,'Forecast 1'!$7:$7,0)),"Mismatch") -> -1800 | ... V24: =IF($B24='Forecast 1'!$B24,INDEX('Forecast 1'!$1:$1048576,MATCH('Forecast 1'!$B24,'Forecast 1'!$B:$B,0),MATCH('Forecast 1'!V$7,'Forecast 1'!$7:$7,0)),"Mismatch") -> 0
B25: Credit Cards | D25: =IF($B25='Forecast 1'!$B25,INDEX('Forecast 1'!$1:$1048576,MATCH('Forecast 1'!$B25,'Forecast 1'!$B:$B,0),MATCH('Forecast 1'!D$7,'Forecast 1'!$7:$7,0)),"Mismatch") -> 0 | E25: =IF($B25='Forecast 1'!$B25,INDEX('Forecast 1'!$1:$1048576,MATCH('Forecast 1'!$B25,'Forecast 1'!$B:$B,0),MATCH('Forecast 1'!E$7,'Forecast 1'!$7:$7,0)),"Mismatch") -> -194090 | F25: =IF($B25='Forecast 1'!$B25,INDEX('Forecast 1'!$1:$1048576,MATCH('Forecast 1'!$B25,'Forecast 1'!$B:$B,0),MATCH('Forecast 1'!F$7,'Forecast 1'!$7:$7,0)),"Mismatch") -> 0 | G25: =IF($B25='Forecast 1'!$B25,INDEX('Forecast 1'!$1:$1048576,MATCH('Forecast 1'!$B25,'Forecast 1'!$B:$B,0),MATCH('Forecast 1'!G$7,'Forecast 1'!$7:$7,0)),"Mismatch") -> -100000 | H25: =IF($B25='Forecast 1'!$B25,INDEX('Forecast 1'!$1:$1048576,MATCH('Forecast 1'!$B25,'Forecast 1'!$B:$B,0),MATCH('Forecast 1'!H$7,'Forecast 1'!$7:$7,0)),"Mismatch") -> 0 | I25: =IF($B25='Forecast 1'!$B25,INDEX('Forecast 1'!$1:$1048576,MATCH('Forecast 1'!$B25,'Forecast 1'!$B:$B,0),MATCH('Forecast 1'!I$7,'Forecast 1'!$7:$7,0)),"Mismatch") -> -32000 | J25: =IF($B25='Forecast 1'!$B25,INDEX('Forecast 1'!$1:$1048576,MATCH('Forecast 1'!$B25,'Forecast 1'!$B:$B,0),MATCH('Forecast 1'!J$7,'Forecast 1'!$7:$7,0)),"Mismatch") -> -350000 | K25: =IF($B25='Forecast 1'!$B25,INDEX('Forecast 1'!$1:$1048576,MATCH('Forecast 1'!$B25,'Forecast 1'!$B:$B,0),MATCH('Forecast 1'!K$7,'Forecast 1'!$7:$7,0)),"Mismatch") -> 0 | ... V25: =IF($B25='Forecast 1'!$B25,INDEX('Forecast 1'!$1:$1048576,MATCH('Forecast 1'!$B25,'Forecast 1'!$B:$B,0),MATCH('Forecast 1'!V$7,'Forecast 1'!$7:$7,0)),"Mismatch") -> -210000
B26: Payroll | C26: Trailing 6 Week Average | D26: =IF($B26='Forecast 1'!$B26,INDEX('Forecast 1'!$1:$1048576,MATCH('Forecast 1'!$B26,'Forecast 1'!$B:$B,0),MATCH('Forecast 1'!D$7,'Forecast 1'!$7:$7,0)),"Mismatch") -> -77830 | E26: =IF($B26='Forecast 1'!$B26,INDEX('Forecast 1'!$1:$1048576,MATCH('Forecast 1'!$B26,'Forecast 1'!$B:$B,0),MATCH('Forecast 1'!E$7,'Forecast 1'!$7:$7,0)),"Mismatch") -> -78050 | F26: =IF($B26='Forecast 1'!$B26,INDEX('Forecast 1'!$1:$1048576,MATCH('Forecast 1'!$B26,'Forecast 1'!$B:$B,0),MATCH('Forecast 1'!F$7,'Forecast 1'!$7:$7,0)),"Mismatch") -> -51670 | G26: =IF($B26='Forecast 1'!$B26,INDEX('Forecast 1'!$1:$1048576,MATCH('Forecast 1'!$B26,'Forecast 1'!$B:$B,0),MATCH('Forecast 1'!G$7,'Forecast 1'!$7:$7,0)),"Mismatch") -> -39960 | H26: =IF($B26='Forecast 1'!$B26,INDEX('Forecast 1'!$1:$1048576,MATCH('Forecast 1'!$B26,'Forecast 1'!$B:$B,0),MATCH('Forecast 1'!H$7,'Forecast 1'!$7:$7,0)),"Mismatch") -> -44380 | I26: =IF($B26='Forecast 1'!$B26,INDEX('Forecast 1'!$1:$1048576,MATCH('Forecast 1'!$B26,'Forecast 1'!$B:$B,0),MATCH('Forecast 1'!I$7,'Forecast 1'!$7:$7,0)),"Mismatch") -> -35340 | J26: =IF($B26='Forecast 1'!$B26,INDEX('Forecast 1'!$1:$1048576,MATCH('Forecast 1'!$B26,'Forecast 1'!$B:$B,0),MATCH('Forecast 1'!J$7,'Forecast 1'!$7:$7,0)),"Mismatch") -> -54538.333 | K26: =IF($B26='Forecast 1'!$B26,INDEX('Forecast 1'!$1:$1048576,MATCH('Forecast 1'!$B26,'Forecast 1'!$B:$B,0),MATCH('Forecast 1'!K$7,'Forecast 1'!$7:$7,0)),"Mismatch") -> -50656.389 | ... V26: =IF($B26='Forecast 1'!$B26,INDEX('Forecast 1'!$1:$1048576,MATCH('Forecast 1'!$B26,'Forecast 1'!$B:$B,0),MATCH('Forecast 1'!V$7,'Forecast 1'!$7:$7,0)),"Mismatch") -> -46966.597
B27: Contractors | C27: Enter Manually | D27: =IF($B27='Forecast 1'!$B27,INDEX('Forecast 1'!$1:$1048576,MATCH('Forecast 1'!$B27,'Forecast 1'!$B:$B,0),MATCH('Forecast 1'!D$7,'Forecast 1'!$7:$7,0)),"Mismatch") -> 0 | E27: =IF($B27='Forecast 1'!$B27,INDEX('Forecast 1'!$1:$1048576,MATCH('Forecast 1'!$B27,'Forecast 1'!$B:$B,0),MATCH('Forecast 1'!E$7,'Forecast 1'!$7:$7,0)),"Mismatch") -> 0 | F27: =IF($B27='Forecast 1'!$B27,INDEX('Forecast 1'!$1:$1048576,MATCH('Forecast 1'!$B27,'Forecast 1'!$B:$B,0),MATCH('Forecast 1'!F$7,'Forecast 1'!$7:$7,0)),"Mismatch") -> 0 | G27: =IF($B27='Forecast 1'!$B27,INDEX('Forecast 1'!$1:$1048576,MATCH('Forecast 1'!$B27,'Forecast 1'!$B:$B,0),MATCH('Forecast 1'!G$7,'Forecast 1'!$7:$7,0)),"Mismatch") -> 0 | H27: =IF($B27='Forecast 1'!$B27,INDEX('Forecast 1'!$1:$1048576,MATCH('Forecast 1'!$B27,'Forecast 1'!$B:$B,0),MATCH('Forecast 1'!H$7,'Forecast 1'!$7:$7,0)),"Mismatch") -> 0 | I27: =IF($B27='Forecast 1'!$B27,INDEX('Forecast 1'!$1:$1048576,MATCH('Forecast 1'!$B27,'Forecast 1'!$B:$B,0),MATCH('Forecast 1'!I$7,'Forecast 1'!$7:$7,0)),"Mismatch") -> 0 | J27: =IF($B27='Forecast 1'!$B27,INDEX('Forecast 1'!$1:$1048576,MATCH('Forecast 1'!$B27,'Forecast 1'!$B:$B,0),MATCH('Forecast 1'!J$7,'Forecast 1'!$7:$7,0)),"Mismatch") -> 0 | K27: =IF($B27='Forecast 1'!$B27,INDEX('Forecast 1'!$1:$1048576,MATCH('Forecast 1'!$B27,'Forecast 1'!$B:$B,0),MATCH('Forecast 1'!K$7,'Forecast 1'!$7:$7,0)),"Mismatch") -> 0 | ... V27: =IF($B27='Forecast 1'!$B27,INDEX('Forecast 1'!$1:$1048576,MATCH('Forecast 1'!$B27,'Forecast 1'!$B:$B,0),MATCH('Forecast 1'!V$7,'Forecast 1'!$7:$7,0)),"Mismatch") -> 0
B28: Dues & Subscriptions | C28: Trailing 6 Week Average | D28: =IF($B28='Forecast 1'!$B28,INDEX('Forecast 1'!$1:$1048576,MATCH('Forecast 1'!$B28,'Forecast 1'!$B:$B,0),MATCH('Forecast 1'!D$7,'Forecast 1'!$7:$7,0)),"Mismatch") -> -310 | E28: =IF($B28='Forecast 1'!$B28,INDEX('Forecast 1'!$1:$1048576,MATCH('Forecast 1'!$B28,'Forecast 1'!$B:$B,0),MATCH('Forecast 1'!E$7,'Forecast 1'!$7:$7,0)),"Mismatch") -> -310 | F28: =IF($B28='Forecast 1'!$B28,INDEX('Forecast 1'!$1:$1048576,MATCH('Forecast 1'!$B28,'Forecast 1'!$B:$B,0),MATCH('Forecast 1'!F$7,'Forecast 1'!$7:$7,0)),"Mismatch") -> -310 | G28: =IF($B28='Forecast 1'!$B28,INDEX('Forecast 1'!$1:$1048576,MATCH('Forecast 1'!$B28,'Forecast 1'!$B:$B,0),MATCH('Forecast 1'!G$7,'Forecast 1'!$7:$7,0)),"Mismatch") -> -310 | H28: =IF($B28='Forecast 1'!$B28,INDEX('Forecast 1'!$1:$1048576,MATCH('Forecast 1'!$B28,'Forecast 1'!$B:$B,0),MATCH('Forecast 1'!H$7,'Forecast 1'!$7:$7,0)),"Mismatch") -> -310 | I28: =IF($B28='Forecast 1'!$B28,INDEX('Forecast 1'!$1:$1048576,MATCH('Forecast 1'!$B28,'Forecast 1'!$B:$B,0),MATCH('Forecast 1'!I$7,'Forecast 1'!$7:$7,0)),"Mismatch") -> -310 | J28: =IF($B28='Forecast 1'!$B28,INDEX('Forecast 1'!$1:$1048576,MATCH('Forecast 1'!$B28,'Forecast 1'!$B:$B,0),MATCH('Forecast 1'!J$7,'Forecast 1'!$7:$7,0)),"Mismatch") -> -310 | K28: =IF($B28='Forecast 1'!$B28,INDEX('Forecast 1'!$1:$1048576,MATCH('Forecast 1'!$B28,'Forecast 1'!$B:$B,0),MATCH('Forecast 1'!K$7,'Forecast 1'!$7:$7,0)),"Mismatch") -> -310 | ... V28: =IF($B28='Forecast 1'!$B28,INDEX('Forecast 1'!$1:$1048576,MATCH('Forecast 1'!$B28,'Forecast 1'!$B:$B,0),MATCH('Forecast 1'!V$7,'Forecast 1'!$7:$7,0)),"Mismatch") -> -310
B29: Insurance | C29: Enter Manually | D29: =IF($B29='Forecast 1'!$B29,INDEX('Forecast 1'!$1:$1048576,MATCH('Forecast 1'!$B29,'Forecast 1'!$B:$B,0),MATCH('Forecast 1'!D$7,'Forecast 1'!$7:$7,0)),"Mismatch") -> 0 | E29: =IF($B29='Forecast 1'!$B29,INDEX('Forecast 1'!$1:$1048576,MATCH('Forecast 1'!$B29,'Forecast 1'!$B:$B,0),MATCH('Forecast 1'!E$7,'Forecast 1'!$7:$7,0)),"Mismatch") -> 0 | F29: =IF($B29='Forecast 1'!$B29,INDEX('Forecast 1'!$1:$1048576,MATCH('Forecast 1'!$B29,'Forecast 1'!$B:$B,0),MATCH('Forecast 1'!F$7,'Forecast 1'!$7:$7,0)),"Mismatch") -> 0 | G29: =IF($B29='Forecast 1'!$B29,INDEX('Forecast 1'!$1:$1048576,MATCH('Forecast 1'!$B29,'Forecast 1'!$B:$B,0),MATCH('Forecast 1'!G$7,'Forecast 1'!$7:$7,0)),"Mismatch") -> 0 | H29: =IF($B29='Forecast 1'!$B29,INDEX('Forecast 1'!$1:$1048576,MATCH('Forecast 1'!$B29,'Forecast 1'!$B:$B,0),MATCH('Forecast 1'!H$7,'Forecast 1'!$7:$7,0)),"Mismatch") -> 0 | I29: =IF($B29='Forecast 1'!$B29,INDEX('Forecast 1'!$1:$1048576,MATCH('Forecast 1'!$B29,'Forecast 1'!$B:$B,0),MATCH('Forecast 1'!I$7,'Forecast 1'!$7:$7,0)),"Mismatch") -> 0 | J29: =IF($B29='Forecast 1'!$B29,INDEX('Forecast 1'!$1:$1048576,MATCH('Forecast 1'!$B29,'Forecast 1'!$B:$B,0),MATCH('Forecast 1'!J$7,'Forecast 1'!$7:$7,0)),"Mismatch") -> 0 | K29: =IF($B29='Forecast 1'!$B29,INDEX('Forecast 1'!$1:$1048576,MATCH('Forecast 1'!$B29,'Forecast 1'!$B:$B,0),MATCH('Forecast 1'!K$7,'Forecast 1'!$7:$7,0)),"Mismatch") -> 0 | ... V29: =IF($B29='Forecast 1'!$B29,INDEX('Forecast 1'!$1:$1048576,MATCH('Forecast 1'!$B29,'Forecast 1'!$B:$B,0),MATCH('Forecast 1'!V$7,'Forecast 1'!$7:$7,0)),"Mismatch") -> 0
B30: Lease Payments | C30: Trailing 6 Week Average | D30: =IF($B30='Forecast 1'!$B30,INDEX('Forecast 1'!$1:$1048576,MATCH('Forecast 1'!$B30,'Forecast 1'!$B:$B,0),MATCH('Forecast 1'!D$7,'Forecast 1'!$7:$7,0)),"Mismatch") -> 0 | E30: =IF($B30='Forecast 1'!$B30,INDEX('Forecast 1'!$1:$1048576,MATCH('Forecast 1'!$B30,'Forecast 1'!$B:$B,0),MATCH('Forecast 1'!E$7,'Forecast 1'!$7:$7,0)),"Mismatch") -> -1350 | F30: =IF($B30='Forecast 1'!$B30,INDEX('Forecast 1'!$1:$1048576,MATCH('Forecast 1'!$B30,'Forecast 1'!$B:$B,0),MATCH('Forecast 1'!F$7,'Forecast 1'!$7:$7,0)),"Mismatch") -> 0 | G30: =IF($B30='Forecast 1'!$B30,INDEX('Forecast 1'!$1:$1048576,MATCH('Forecast 1'!$B30,'Forecast 1'!$B:$B,0),MATCH('Forecast 1'!G$7,'Forecast 1'!$7:$7,0)),"Mismatch") -> 0 | H30: =IF($B30='Forecast 1'!$B30,INDEX('Forecast 1'!$1:$1048576,MATCH('Forecast 1'!$B30,'Forecast 1'!$B:$B,0),MATCH('Forecast 1'!H$7,'Forecast 1'!$7:$7,0)),"Mismatch") -> -1350 | I30: =IF($B30='Forecast 1'!$B30,INDEX('Forecast 1'!$1:$1048576,MATCH('Forecast 1'!$B30,'Forecast 1'!$B:$B,0),MATCH('Forecast 1'!I$7,'Forecast 1'!$7:$7,0)),"Mismatch") -> -1350 | J30: =IF($B30='Forecast 1'!$B30,INDEX('Forecast 1'!$1:$1048576,MATCH('Forecast 1'!$B30,'Forecast 1'!$B:$B,0),MATCH('Forecast 1'!J$7,'Forecast 1'!$7:$7,0)),"Mismatch") -> -675 | K30: =IF($B30='Forecast 1'!$B30,INDEX('Forecast 1'!$1:$1048576,MATCH('Forecast 1'!$B30,'Forecast 1'!$B:$B,0),MATCH('Forecast 1'!K$7,'Forecast 1'!$7:$7,0)),"Mismatch") -> -787.5 | ... V30: =IF($B30='Forecast 1'!$B30,INDEX('Forecast 1'!$1:$1048576,MATCH('Forecast 1'!$B30,'Forecast 1'!$B:$B,0),MATCH('Forecast 1'!V$7,'Forecast 1'!$7:$7,0)),"Mismatch") -> -828.39988
B31: Marketing | C31: Trailing 6 Week Average | D31: =IF($B31='Forecast 1'!$B31,INDEX('Forecast 1'!$1:$1048576,MATCH('Forecast 1'!$B31,'Forecast 1'!$B:$B,0),MATCH('Forecast 1'!D$7,'Forecast 1'!$7:$7,0)),"Mismatch") -> 0 | E31: =IF($B31='Forecast 1'!$B31,INDEX('Forecast 1'!$1:$1048576,MATCH('Forecast 1'!$B31,'Forecast 1'!$B:$B,0),MATCH('Forecast 1'!E$7,'Forecast 1'!$7:$7,0)),"Mismatch") -> -1510 | F31: =IF($B31='Forecast 1'!$B31,INDEX('Forecast 1'!$1:$1048576,MATCH('Forecast 1'!$B31,'Forecast 1'!$B:$B,0),MATCH('Forecast 1'!F$7,'Forecast 1'!$7:$7,0)),"Mismatch") -> -1020 | G31: =IF($B31='Forecast 1'!$B31,INDEX('Forecast 1'!$1:$1048576,MATCH('Forecast 1'!$B31,'Forecast 1'!$B:$B,0),MATCH('Forecast 1'!G$7,'Forecast 1'!$7:$7,0)),"Mismatch") -> 0 | H31: =IF($B31='Forecast 1'!$B31,INDEX('Forecast 1'!$1:$1048576,MATCH('Forecast 1'!$B31,'Forecast 1'!$B:$B,0),MATCH('Forecast 1'!H$7,'Forecast 1'!$7:$7,0)),"Mismatch") -> 0 | I31: =IF($B31='Forecast 1'!$B31,INDEX('Forecast 1'!$1:$1048576,MATCH('Forecast 1'!$B31,'Forecast 1'!$B:$B,0),MATCH('Forecast 1'!I$7,'Forecast 1'!$7:$7,0)),"Mismatch") -> -1510 | J31: =IF($B31='Forecast 1'!$B31,INDEX('Forecast 1'!$1:$1048576,MATCH('Forecast 1'!$B31,'Forecast 1'!$B:$B,0),MATCH('Forecast 1'!J$7,'Forecast 1'!$7:$7,0)),"Mismatch") -> -673.33333 | K31: =IF($B31='Forecast 1'!$B31,INDEX('Forecast 1'!$1:$1048576,MATCH('Forecast 1'!$B31,'Forecast 1'!$B:$B,0),MATCH('Forecast 1'!K$7,'Forecast 1'!$7:$7,0)),"Mismatch") -> -785.55556 | ... V31: =IF($B31='Forecast 1'!$B31,INDEX('Forecast 1'!$1:$1048576,MATCH('Forecast 1'!$B31,'Forecast 1'!$B:$B,0),MATCH('Forecast 1'!V$7,'Forecast 1'!$7:$7,0)),"Mismatch") -> -717.21397
B32: Phone & Internet | C32: Enter Manually | D32: =IF($B32='Forecast 1'!$B32,INDEX('Forecast 1'!$1:$1048576,MATCH('Forecast 1'!$B32,'Forecast 1'!$B:$B,0),MATCH('Forecast 1'!D$7,'Forecast 1'!$7:$7,0)),"Mismatch") -> 0 | E32: =IF($B32='Forecast 1'!$B32,INDEX('Forecast 1'!$1:$1048576,MATCH('Forecast 1'!$B32,'Forecast 1'!$B:$B,0),MATCH('Forecast 1'!E$7,'Forecast 1'!$7:$7,0)),"Mismatch") -> 0 | F32: =IF($B32='Forecast 1'!$B32,INDEX('Forecast 1'!$1:$1048576,MATCH('Forecast 1'!$B32,'Forecast 1'!$B:$B,0),MATCH('Forecast 1'!F$7,'Forecast 1'!$7:$7,0)),"Mismatch") -> 0 | G32: =IF($B32='Forecast 1'!$B32,INDEX('Forecast 1'!$1:$1048576,MATCH('Forecast 1'!$B32,'Forecast 1'!$B:$B,0),MATCH('Forecast 1'!G$7,'Forecast 1'!$7:$7,0)),"Mismatch") -> 0 | H32: =IF($B32='Forecast 1'!$B32,INDEX('Forecast 1'!$1:$1048576,MATCH('Forecast 1'!$B32,'Forecast 1'!$B:$B,0),MATCH('Forecast 1'!H$7,'Forecast 1'!$7:$7,0)),"Mismatch") -> 0 | I32: =IF($B32='Forecast 1'!$B32,INDEX('Forecast 1'!$1:$1048576,MATCH('Forecast 1'!$B32,'Forecast 1'!$B:$B,0),MATCH('Forecast 1'!I$7,'Forecast 1'!$7:$7,0)),"Mismatch") -> 0 | J32: =IF($B32='Forecast 1'!$B32,INDEX('Forecast 1'!$1:$1048576,MATCH('Forecast 1'!$B32,'Forecast 1'!$B:$B,0),MATCH('Forecast 1'!J$7,'Forecast 1'!$7:$7,0)),"Mismatch") -> 0 | K32: =IF($B32='Forecast 1'!$B32,INDEX('Forecast 1'!$1:$1048576,MATCH('Forecast 1'!$B32,'Forecast 1'!$B:$B,0),MATCH('Forecast 1'!K$7,'Forecast 1'!$7:$7,0)),"Mismatch") -> 0 | ... V32: =IF($B32='Forecast 1'!$B32,INDEX('Forecast 1'!$1:$1048576,MATCH('Forecast 1'!$B32,'Forecast 1'!$B:$B,0),MATCH('Forecast 1'!V$7,'Forecast 1'!$7:$7,0)),"Mismatch") -> 0
B33: Professional Fees | C33: $5k each Month | D33: =IF($B33='Forecast 1'!$B33,INDEX('Forecast 1'!$1:$1048576,MATCH('Forecast 1'!$B33,'Forecast 1'!$B:$B,0),MATCH('Forecast 1'!D$7,'Forecast 1'!$7:$7,0)),"Mismatch") -> 0 | E33: =IF($B33='Forecast 1'!$B33,INDEX('Forecast 1'!$1:$1048576,MATCH('Forecast 1'!$B33,'Forecast 1'!$B:$B,0),MATCH('Forecast 1'!E$7,'Forecast 1'!$7:$7,0)),"Mismatch") -> -5000 | F33: =IF($B33='Forecast 1'!$B33,INDEX('Forecast 1'!$1:$1048576,MATCH('Forecast 1'!$B33,'Forecast 1'!$B:$B,0),MATCH('Forecast 1'!F$7,'Forecast 1'!$7:$7,0)),"Mismatch") -> 0 | G33: =IF($B33='Forecast 1'!$B33,INDEX('Forecast 1'!$1:$1048576,MATCH('Forecast 1'!$B33,'Forecast 1'!$B:$B,0),MATCH('Forecast 1'!G$7,'Forecast 1'!$7:$7,0)),"Mismatch") -> 0 | H33: =IF($B33='Forecast 1'!$B33,INDEX('Forecast 1'!$1:$1048576,MATCH('Forecast 1'!$B33,'Forecast 1'!$B:$B,0),MATCH('Forecast 1'!H$7,'Forecast 1'!$7:$7,0)),"Mismatch") -> 0 | I33: =IF($B33='Forecast 1'!$B33,INDEX('Forecast 1'!$1:$1048576,MATCH('Forecast 1'!$B33,'Forecast 1'!$B:$B,0),MATCH('Forecast 1'!I$7,'Forecast 1'!$7:$7,0)),"Mismatch") -> 0 | J33: =IF($B33='Forecast 1'!$B33,INDEX('Forecast 1'!$1:$1048576,MATCH('Forecast 1'!$B33,'Forecast 1'!$B:$B,0),MATCH('Forecast 1'!J$7,'Forecast 1'!$7:$7,0)),"Mismatch") -> -5000 | K33: =IF($B33='Forecast 1'!$B33,INDEX('Forecast 1'!$1:$1048576,MATCH('Forecast 1'!$B33,'Forecast 1'!$B:$B,0),MATCH('Forecast 1'!K$7,'Forecast 1'!$7:$7,0)),"Mismatch") -> 0 | ... V33: =IF($B33='Forecast 1'!$B33,INDEX('Forecast 1'!$1:$1048576,MATCH('Forecast 1'!$B33,'Forecast 1'!$B:$B,0),MATCH('Forecast 1'!V$7,'Forecast 1'!$7:$7,0)),"Mismatch") -> -5000
B34: Rent | C34: Enter Manually | D34: =IF($B34='Forecast 1'!$B34,INDEX('Forecast 1'!$1:$1048576,MATCH('Forecast 1'!$B34,'Forecast 1'!$B:$B,0),MATCH('Forecast 1'!D$7,'Forecast 1'!$7:$7,0)),"Mismatch") -> 0 | E34: =IF($B34='Forecast 1'!$B34,INDEX('Forecast 1'!$1:$1048576,MATCH('Forecast 1'!$B34,'Forecast 1'!$B:$B,0),MATCH('Forecast 1'!E$7,'Forecast 1'!$7:$7,0)),"Mismatch") -> 0 | F34: =IF($B34='Forecast 1'!$B34,INDEX('Forecast 1'!$1:$1048576,MATCH('Forecast 1'!$B34,'Forecast 1'!$B:$B,0),MATCH('Forecast 1'!F$7,'Forecast 1'!$7:$7,0)),"Mismatch") -> 0 | G34: =IF($B34='Forecast 1'!$B34,INDEX('Forecast 1'!$1:$1048576,MATCH('Forecast 1'!$B34,'Forecast 1'!$B:$B,0),MATCH('Forecast 1'!G$7,'Forecast 1'!$7:$7,0)),"Mismatch") -> 0 | H34: =IF($B34='Forecast 1'!$B34,INDEX('Forecast 1'!$1:$1048576,MATCH('Forecast 1'!$B34,'Forecast 1'!$B:$B,0),MATCH('Forecast 1'!H$7,'Forecast 1'!$7:$7,0)),"Mismatch") -> 0 | I34: =IF($B34='Forecast 1'!$B34,INDEX('Forecast 1'!$1:$1048576,MATCH('Forecast 1'!$B34,'Forecast 1'!$B:$B,0),MATCH('Forecast 1'!I$7,'Forecast 1'!$7:$7,0)),"Mismatch") -> 0 | J34: =IF($B34='Forecast 1'!$B34,INDEX('Forecast 1'!$1:$1048576,MATCH('Forecast 1'!$B34,'Forecast 1'!$B:$B,0),MATCH('Forecast 1'!J$7,'Forecast 1'!$7:$7,0)),"Mismatch") -> 0 | K34: =IF($B34='Forecast 1'!$B34,INDEX('Forecast 1'!$1:$1048576,MATCH('Forecast 1'!$B34,'Forecast 1'!$B:$B,0),MATCH('Forecast 1'!K$7,'Forecast 1'!$7:$7,0)),"Mismatch") -> 0 | ... V34: =IF($B34='Forecast 1'!$B34,INDEX('Forecast 1'!$1:$1048576,MATCH('Forecast 1'!$B34,'Forecast 1'!$B:$B,0),MATCH('Forecast 1'!V$7,'Forecast 1'!$7:$7,0)),"Mismatch") -> 0
B35: Repairs & Maintenance | C35: Enter Manually | D35: =IF($B35='Forecast 1'!$B35,INDEX('Forecast 1'!$1:$1048576,MATCH('Forecast 1'!$B35,'Forecast 1'!$B:$B,0),MATCH('Forecast 1'!D$7,'Forecast 1'!$7:$7,0)),"Mismatch") -> 0 | E35: =IF($B35='Forecast 1'!$B35,INDEX('Forecast 1'!$1:$1048576,MATCH('Forecast 1'!$B35,'Forecast 1'!$B:$B,0),MATCH('Forecast 1'!E$7,'Forecast 1'!$7:$7,0)),"Mismatch") -> 0 | F35: =IF($B35='Forecast 1'!$B35,INDEX('Forecast 1'!$1:$1048576,MATCH('Forecast 1'!$B35,'Forecast 1'!$B:$B,0),MATCH('Forecast 1'!F$7,'Forecast 1'!$7:$7,0)),"Mismatch") -> 0 | G35: =IF($B35='Forecast 1'!$B35,INDEX('Forecast 1'!$1:$1048576,MATCH('Forecast 1'!$B35,'Forecast 1'!$B:$B,0),MATCH('Forecast 1'!G$7,'Forecast 1'!$7:$7,0)),"Mismatch") -> 0 | H35: =IF($B35='Forecast 1'!$B35,INDEX('Forecast 1'!$1:$1048576,MATCH('Forecast 1'!$B35,'Forecast 1'!$B:$B,0),MATCH('Forecast 1'!H$7,'Forecast 1'!$7:$7,0)),"Mismatch") -> 0 | I35: =IF($B35='Forecast 1'!$B35,INDEX('Forecast 1'!$1:$1048576,MATCH('Forecast 1'!$B35,'Forecast 1'!$B:$B,0),MATCH('Forecast 1'!I$7,'Forecast 1'!$7:$7,0)),"Mismatch") -> 0 | J35: =IF($B35='Forecast 1'!$B35,INDEX('Forecast 1'!$1:$1048576,MATCH('Forecast 1'!$B35,'Forecast 1'!$B:$B,0),MATCH('Forecast 1'!J$7,'Forecast 1'!$7:$7,0)),"Mismatch") -> 0 | K35: =IF($B35='Forecast 1'!$B35,INDEX('Forecast 1'!$1:$1048576,MATCH('Forecast 1'!$B35,'Forecast 1'!$B:$B,0),MATCH('Forecast 1'!K$7,'Forecast 1'!$7:$7,0)),"Mismatch") -> 0 | ... V35: =IF($B35='Forecast 1'!$B35,INDEX('Forecast 1'!$1:$1048576,MATCH('Forecast 1'!$B35,'Forecast 1'!$B:$B,0),MATCH('Forecast 1'!V$7,'Forecast 1'!$7:$7,0)),"Mismatch") -> 0
B36: Supplies | C36: Enter Manually | D36: =IF($B36='Forecast 1'!$B36,INDEX('Forecast 1'!$1:$1048576,MATCH('Forecast 1'!$B36,'Forecast 1'!$B:$B,0),MATCH('Forecast 1'!D$7,'Forecast 1'!$7:$7,0)),"Mismatch") -> 0 | E36: =IF($B36='Forecast 1'!$B36,INDEX('Forecast 1'!$1:$1048576,MATCH('Forecast 1'!$B36,'Forecast 1'!$B:$B,0),MATCH('Forecast 1'!E$7,'Forecast 1'!$7:$7,0)),"Mismatch") -> 0 | F36: =IF($B36='Forecast 1'!$B36,INDEX('Forecast 1'!$1:$1048576,MATCH('Forecast 1'!$B36,'Forecast 1'!$B:$B,0),MATCH('Forecast 1'!F$7,'Forecast 1'!$7:$7,0)),"Mismatch") -> 0 | G36: =IF($B36='Forecast 1'!$B36,INDEX('Forecast 1'!$1:$1048576,MATCH('Forecast 1'!$B36,'Forecast 1'!$B:$B,0),MATCH('Forecast 1'!G$7,'Forecast 1'!$7:$7,0)),"Mismatch") -> 0 | H36: =IF($B36='Forecast 1'!$B36,INDEX('Forecast 1'!$1:$1048576,MATCH('Forecast 1'!$B36,'Forecast 1'!$B:$B,0),MATCH('Forecast 1'!H$7,'Forecast 1'!$7:$7,0)),"Mismatch") -> 0 | I36: =IF($B36='Forecast 1'!$B36,INDEX('Forecast 1'!$1:$1048576,MATCH('Forecast 1'!$B36,'Forecast 1'!$B:$B,0),MATCH('Forecast 1'!I$7,'Forecast 1'!$7:$7,0)),"Mismatch") -> 0 | J36: =IF($B36='Forecast 1'!$B36,INDEX('Forecast 1'!$1:$1048576,MATCH('Forecast 1'!$B36,'Forecast 1'!$B:$B,0),MATCH('Forecast 1'!J$7,'Forecast 1'!$7:$7,0)),"Mismatch") -> 0 | K36: =IF($B36='Forecast 1'!$B36,INDEX('Forecast 1'!$1:$1048576,MATCH('Forecast 1'!$B36,'Forecast 1'!$B:$B,0),MATCH('Forecast 1'!K$7,'Forecast 1'!$7:$7,0)),"Mismatch") -> 0 | ... V36: =IF($B36='Forecast 1'!$B36,INDEX('Forecast 1'!$1:$1048576,MATCH('Forecast 1'!$B36,'Forecast 1'!$B:$B,0),MATCH('Forecast 1'!V$7,'Forecast 1'!$7:$7,0)),"Mismatch") -> 0
B37: Licenses | C37: Enter Manually | D37: =IF($B37='Forecast 1'!$B37,INDEX('Forecast 1'!$1:$1048576,MATCH('Forecast 1'!$B37,'Forecast 1'!$B:$B,0),MATCH('Forecast 1'!D$7,'Forecast 1'!$7:$7,0)),"Mismatch") -> 0 | E37: =IF($B37='Forecast 1'!$B37,INDEX('Forecast 1'!$1:$1048576,MATCH('Forecast 1'!$B37,'Forecast 1'!$B:$B,0),MATCH('Forecast 1'!E$7,'Forecast 1'!$7:$7,0)),"Mismatch") -> 0 | F37: =IF($B37='Forecast 1'!$B37,INDEX('Forecast 1'!$1:$1048576,MATCH('Forecast 1'!$B37,'Forecast 1'!$B:$B,0),MATCH('Forecast 1'!F$7,'Forecast 1'!$7:$7,0)),"Mismatch") -> 0 | G37: =IF($B37='Forecast 1'!$B37,INDEX('Forecast 1'!$1:$1048576,MATCH('Forecast 1'!$B37,'Forecast 1'!$B:$B,0),MATCH('Forecast 1'!G$7,'Forecast 1'!$7:$7,0)),"Mismatch") -> 0 | H37: =IF($B37='Forecast 1'!$B37,INDEX('Forecast 1'!$1:$1048576,MATCH('Forecast 1'!$B37,'Forecast 1'!$B:$B,0),MATCH('Forecast 1'!H$7,'Forecast 1'!$7:$7,0)),"Mismatch") -> 0 | I37: =IF($B37='Forecast 1'!$B37,INDEX('Forecast 1'!$1:$1048576,MATCH('Forecast 1'!$B37,'Forecast 1'!$B:$B,0),MATCH('Forecast 1'!I$7,'Forecast 1'!$7:$7,0)),"Mismatch") -> 0 | J37: =IF($B37='Forecast 1'!$B37,INDEX('Forecast 1'!$1:$1048576,MATCH('Forecast 1'!$B37,'Forecast 1'!$B:$B,0),MATCH('Forecast 1'!J$7,'Forecast 1'!$7:$7,0)),"Mismatch") -> 0 | K37: =IF($B37='Forecast 1'!$B37,INDEX('Forecast 1'!$1:$1048576,MATCH('Forecast 1'!$B37,'Forecast 1'!$B:$B,0),MATCH('Forecast 1'!K$7,'Forecast 1'!$7:$7,0)),"Mismatch") -> 0 | ... V37: =IF($B37='Forecast 1'!$B37,INDEX('Forecast 1'!$1:$1048576,MATCH('Forecast 1'!$B37,'Forecast 1'!$B:$B,0),MATCH('Forecast 1'!V$7,'Forecast 1'!$7:$7,0)),"Mismatch") -> 0
... B43: Other Operating Outflows | C43: Trailing 6 Week Average | D43: =IF($B43='Forecast 1'!$B43,INDEX('Forecast 1'!$1:$1048576,MATCH('Forecast 1'!$B43,'Forecast 1'!$B:$B,0),MATCH('Forecast 1'!D$7,'Forecast 1'!$7:$7,0)),"Mismatch") -> -1270 | E43: =IF($B43='Forecast 1'!$B43,INDEX('Forecast 1'!$1:$1048576,MATCH('Forecast 1'!$B43,'Forecast 1'!$B:$B,0),MATCH('Forecast 1'!E$7,'Forecast 1'!$7:$7,0)),"Mismatch") -> -2570 | F43: =IF($B43='Forecast 1'!$B43,INDEX('Forecast 1'!$1:$1048576,MATCH('Forecast 1'!$B43,'Forecast 1'!$B:$B,0),MATCH('Forecast 1'!F$7,'Forecast 1'!$7:$7,0)),"Mismatch") -> 0 | G43: =IF($B43='Forecast 1'!$B43,INDEX('Forecast 1'!$1:$1048576,MATCH('Forecast 1'!$B43,'Forecast 1'!$B:$B,0),MATCH('Forecast 1'!G$7,'Forecast 1'!$7:$7,0)),"Mismatch") -> 0 | H43: =IF($B43='Forecast 1'!$B43,INDEX('Forecast 1'!$1:$1048576,MATCH('Forecast 1'!$B43,'Forecast 1'!$B:$B,0),MATCH('Forecast 1'!H$7,'Forecast 1'!$7:$7,0)),"Mismatch") -> 0 | I43: =IF($B43='Forecast 1'!$B43,INDEX('Forecast 1'!$1:$1048576,MATCH('Forecast 1'!$B43,'Forecast 1'!$B:$B,0),MATCH('Forecast 1'!I$7,'Forecast 1'!$7:$7,0)),"Mismatch") -> -1270 | J43: =IF($B43='Forecast 1'!$B43,INDEX('Forecast 1'!$1:$1048576,MATCH('Forecast 1'!$B43,'Forecast 1'!$B:$B,0),MATCH('Forecast 1'!J$7,'Forecast 1'!$7:$7,0)),"Mismatch") -> -851.66667 | K43: =IF($B43='Forecast 1'!$B43,INDEX('Forecast 1'!$1:$1048576,MATCH('Forecast 1'!$B43,'Forecast 1'!$B:$B,0),MATCH('Forecast 1'!K$7,'Forecast 1'!$7:$7,0)),"Mismatch") -> -781.94444 | ... V43: =IF($B43='Forecast 1'!$B43,INDEX('Forecast 1'!$1:$1048576,MATCH('Forecast 1'!$B43,'Forecast 1'!$B:$B,0),MATCH('Forecast 1'!V$7,'Forecast 1'!$7:$7,0)),"Mismatch") -> -666.46564
B46: Total Operating Cash Outflows | D46: =SUM(D24:D45) -> -114140 | E46: =SUM(E24:E45) -> -374900 | F46: =SUM(F24:F45) -> -124910 | G46: =SUM(G24:G45) -> -180410 | H46: =SUM(H24:H45) -> -66850 | I46: =SUM(I24:I45) -> -166200 | J46: =SUM(J24:J45) -> -413930 | K46: =SUM(K24:K45) -> -56198.333 | ... V46: =SUM(V24:V45) -> -272464.99
B48: Non-Operating Cash Outflows
B49: Capital Expenditures | C49: Enter Manually | D49: =IF($B49='Forecast 1'!$B49,INDEX('Forecast 1'!$1:$1048576,MATCH('Forecast 1'!$B49,'Forecast 1'!$B:$B,0),MATCH('Forecast 1'!D$7,'Forecast 1'!$7:$7,0)),"Mismatch") -> 0 | E49: =IF($B49='Forecast 1'!$B49,INDEX('Forecast 1'!$1:$1048576,MATCH('Forecast 1'!$B49,'Forecast 1'!$B:$B,0),MATCH('Forecast 1'!E$7,'Forecast 1'!$7:$7,0)),"Mismatch") -> 0 | F49: =IF($B49='Forecast 1'!$B49,INDEX('Forecast 1'!$1:$1048576,MATCH('Forecast 1'!$B49,'Forecast 1'!$B:$B,0),MATCH('Forecast 1'!F$7,'Forecast 1'!$7:$7,0)),"Mismatch") -> 0 | G49: =IF($B49='Forecast 1'!$B49,INDEX('Forecast 1'!$1:$1048576,MATCH('Forecast 1'!$B49,'Forecast 1'!$B:$B,0),MATCH('Forecast 1'!G$7,'Forecast 1'!$7:$7,0)),"Mismatch") -> 0 | H49: =IF($B49='Forecast 1'!$B49,INDEX('Forecast 1'!$1:$1048576,MATCH('Forecast 1'!$B49,'Forecast 1'!$B:$B,0),MATCH('Forecast 1'!H$7,'Forecast 1'!$7:$7,0)),"Mismatch") -> 0 | I49: =IF($B49='Forecast 1'!$B49,INDEX('Forecast 1'!$1:$1048576,MATCH('Forecast 1'!$B49,'Forecast 1'!$B:$B,0),MATCH('Forecast 1'!I$7,'Forecast 1'!$7:$7,0)),"Mismatch") -> 0 | J49: =IF($B49='Forecast 1'!$B49,INDEX('Forecast 1'!$1:$1048576,MATCH('Forecast 1'!$B49,'Forecast 1'!$B:$B,0),MATCH('Forecast 1'!J$7,'Forecast 1'!$7:$7,0)),"Mismatch") -> 0 | K49: =IF($B49='Forecast 1'!$B49,INDEX('Forecast 1'!$1:$1048576,MATCH('Forecast 1'!$B49,'Forecast 1'!$B:$B,0),MATCH('Forecast 1'!K$7,'Forecast 1'!$7:$7,0)),"Mismatch") -> 0 | ... V49: =IF($B49='Forecast 1'!$B49,INDEX('Forecast 1'!$1:$1048576,MATCH('Forecast 1'!$B49,'Forecast 1'!$B:$B,0),MATCH('Forecast 1'!V$7,'Forecast 1'!$7:$7,0)),"Mismatch") -> 0
B50: Debt Proceeds | C50: Enter Manually | D50: =IF($B50='Forecast 1'!$B50,INDEX('Forecast 1'!$1:$1048576,MATCH('Forecast 1'!$B50,'Forecast 1'!$B:$B,0),MATCH('Forecast 1'!D$7,'Forecast 1'!$7:$7,0)),"Mismatch") -> 0 | E50: =IF($B50='Forecast 1'!$B50,INDEX('Forecast 1'!$1:$1048576,MATCH('Forecast 1'!$B50,'Forecast 1'!$B:$B,0),MATCH('Forecast 1'!E$7,'Forecast 1'!$7:$7,0)),"Mismatch") -> 0 | F50: =IF($B50='Forecast 1'!$B50,INDEX('Forecast 1'!$1:$1048576,MATCH('Forecast 1'!$B50,'Forecast 1'!$B:$B,0),MATCH('Forecast 1'!F$7,'Forecast 1'!$7:$7,0)),"Mismatch") -> 0 | G50: =IF($B50='Forecast 1'!$B50,INDEX('Forecast 1'!$1:$1048576,MATCH('Forecast 1'!$B50,'Forecast 1'!$B:$B,0),MATCH('Forecast 1'!G$7,'Forecast 1'!$7:$7,0)),"Mismatch") -> 0 | H50: =IF($B50='Forecast 1'!$B50,INDEX('Forecast 1'!$1:$1048576,MATCH('Forecast 1'!$B50,'Forecast 1'!$B:$B,0),MATCH('Forecast 1'!H$7,'Forecast 1'!$7:$7,0)),"Mismatch") -> 0 | I50: =IF($B50='Forecast 1'!$B50,INDEX('Forecast 1'!$1:$1048576,MATCH('Forecast 1'!$B50,'Forecast 1'!$B:$B,0),MATCH('Forecast 1'!I$7,'Forecast 1'!$7:$7,0)),"Mismatch") -> 0 | J50: =IF($B50='Forecast 1'!$B50,INDEX('Forecast 1'!$1:$1048576,MATCH('Forecast 1'!$B50,'Forecast 1'!$B:$B,0),MATCH('Forecast 1'!J$7,'Forecast 1'!$7:$7,0)),"Mismatch") -> 0 | K50: =IF($B50='Forecast 1'!$B50,INDEX('Forecast 1'!$1:$1048576,MATCH('Forecast 1'!$B50,'Forecast 1'!$B:$B,0),MATCH('Forecast 1'!K$7,'Forecast 1'!$7:$7,0)),"Mismatch") -> 0 | ... V50: =IF($B50='Forecast 1'!$B50,INDEX('Forecast 1'!$1:$1048576,MATCH('Forecast 1'!$B50,'Forecast 1'!$B:$B,0),MATCH('Forecast 1'!V$7,'Forecast 1'!$7:$7,0)),"Mismatch") -> 0
B51: Interest Payments | C51: Enter Manually | D51: =IF($B51='Forecast 1'!$B51,INDEX('Forecast 1'!$1:$1048576,MATCH('Forecast 1'!$B51,'Forecast 1'!$B:$B,0),MATCH('Forecast 1'!D$7,'Forecast 1'!$7:$7,0)),"Mismatch") -> 0 | E51: =IF($B51='Forecast 1'!$B51,INDEX('Forecast 1'!$1:$1048576,MATCH('Forecast 1'!$B51,'Forecast 1'!$B:$B,0),MATCH('Forecast 1'!E$7,'Forecast 1'!$7:$7,0)),"Mismatch") -> 0 | F51: =IF($B51='Forecast 1'!$B51,INDEX('Forecast 1'!$1:$1048576,MATCH('Forecast 1'!$B51,'Forecast 1'!$B:$B,0),MATCH('Forecast 1'!F$7,'Forecast 1'!$7:$7,0)),"Mismatch") -> 0 | G51: =IF($B51='Forecast 1'!$B51,INDEX('Forecast 1'!$1:$1048576,MATCH('Forecast 1'!$B51,'Forecast 1'!$B:$B,0),MATCH('Forecast 1'!G$7,'Forecast 1'!$7:$7,0)),"Mismatch") -> 0 | H51: =IF($B51='Forecast 1'!$B51,INDEX('Forecast 1'!$1:$1048576,MATCH('Forecast 1'!$B51,'Forecast 1'!$B:$B,0),MATCH('Forecast 1'!H$7,'Forecast 1'!$7:$7,0)),"Mismatch") -> 0 | I51: =IF($B51='Forecast 1'!$B51,INDEX('Forecast 1'!$1:$1048576,MATCH('Forecast 1'!$B51,'Forecast 1'!$B:$B,0),MATCH('Forecast 1'!I$7,'Forecast 1'!$7:$7,0)),"Mismatch") -> 0 | J51: =IF($B51='Forecast 1'!$B51,INDEX('Forecast 1'!$1:$1048576,MATCH('Forecast 1'!$B51,'Forecast 1'!$B:$B,0),MATCH('Forecast 1'!J$7,'Forecast 1'!$7:$7,0)),"Mismatch") -> 0 | K51: =IF($B51='Forecast 1'!$B51,INDEX('Forecast 1'!$1:$1048576,MATCH('Forecast 1'!$B51,'Forecast 1'!$B:$B,0),MATCH('Forecast 1'!K$7,'Forecast 1'!$7:$7,0)),"Mismatch") -> 0 | ... V51: =IF($B51='Forecast 1'!$B51,INDEX('Forecast 1'!$1:$1048576,MATCH('Forecast 1'!$B51,'Forecast 1'!$B:$B,0),MATCH('Forecast 1'!V$7,'Forecast 1'!$7:$7,0)),"Mismatch") -> 0
B52: Principal Payments | C52: Enter Manually | D52: =IF($B52='Forecast 1'!$B52,INDEX('Forecast 1'!$1:$1048576,MATCH('Forecast 1'!$B52,'Forecast 1'!$B:$B,0),MATCH('Forecast 1'!D$7,'Forecast 1'!$7:$7,0)),"Mismatch") -> 0 | E52: =IF($B52='Forecast 1'!$B52,INDEX('Forecast 1'!$1:$1048576,MATCH('Forecast 1'!$B52,'Forecast 1'!$B:$B,0),MATCH('Forecast 1'!E$7,'Forecast 1'!$7:$7,0)),"Mismatch") -> 0 | F52: =IF($B52='Forecast 1'!$B52,INDEX('Forecast 1'!$1:$1048576,MATCH('Forecast 1'!$B52,'Forecast 1'!$B:$B,0),MATCH('Forecast 1'!F$7,'Forecast 1'!$7:$7,0)),"Mismatch") -> 0 | G52: =IF($B52='Forecast 1'!$B52,INDEX('Forecast 1'!$1:$1048576,MATCH('Forecast 1'!$B52,'Forecast 1'!$B:$B,0),MATCH('Forecast 1'!G$7,'Forecast 1'!$7:$7,0)),"Mismatch") -> 0 | H52: =IF($B52='Forecast 1'!$B52,INDEX('Forecast 1'!$1:$1048576,MATCH('Forecast 1'!$B52,'Forecast 1'!$B:$B,0),MATCH('Forecast 1'!H$7,'Forecast 1'!$7:$7,0)),"Mismatch") -> 0 | I52: =IF($B52='Forecast 1'!$B52,INDEX('Forecast 1'!$1:$1048576,MATCH('Forecast 1'!$B52,'Forecast 1'!$B:$B,0),MATCH('Forecast 1'!I$7,'Forecast 1'!$7:$7,0)),"Mismatch") -> 0 | J52: =IF($B52='Forecast 1'!$B52,INDEX('Forecast 1'!$1:$1048576,MATCH('Forecast 1'!$B52,'Forecast 1'!$B:$B,0),MATCH('Forecast 1'!J$7,'Forecast 1'!$7:$7,0)),"Mismatch") -> 0 | K52: =IF($B52='Forecast 1'!$B52,INDEX('Forecast 1'!$1:$1048576,MATCH('Forecast 1'!$B52,'Forecast 1'!$B:$B,0),MATCH('Forecast 1'!K$7,'Forecast 1'!$7:$7,0)),"Mismatch") -> 0 | ... V52: =IF($B52='Forecast 1'!$B52,INDEX('Forecast 1'!$1:$1048576,MATCH('Forecast 1'!$B52,'Forecast 1'!$B:$B,0),MATCH('Forecast 1'!V$7,'Forecast 1'!$7:$7,0)),"Mismatch") -> 0
B53: Tax Distributions | C53: Trailing 6 Week Average | D53: =IF($B53='Forecast 1'!$B53,INDEX('Forecast 1'!$1:$1048576,MATCH('Forecast 1'!$B53,'Forecast 1'!$B:$B,0),MATCH('Forecast 1'!D$7,'Forecast 1'!$7:$7,0)),"Mismatch") -> -21230 | E53: =IF($B53='Forecast 1'!$B53,INDEX('Forecast 1'!$1:$1048576,MATCH('Forecast 1'!$B53,'Forecast 1'!$B:$B,0),MATCH('Forecast 1'!E$7,'Forecast 1'!$7:$7,0)),"Mismatch") -> -24740 | F53: =IF($B53='Forecast 1'!$B53,INDEX('Forecast 1'!$1:$1048576,MATCH('Forecast 1'!$B53,'Forecast 1'!$B:$B,0),MATCH('Forecast 1'!F$7,'Forecast 1'!$7:$7,0)),"Mismatch") -> -20220 | G53: =IF($B53='Forecast 1'!$B53,INDEX('Forecast 1'!$1:$1048576,MATCH('Forecast 1'!$B53,'Forecast 1'!$B:$B,0),MATCH('Forecast 1'!G$7,'Forecast 1'!$7:$7,0)),"Mismatch") -> -14200 | H53: =IF($B53='Forecast 1'!$B53,INDEX('Forecast 1'!$1:$1048576,MATCH('Forecast 1'!$B53,'Forecast 1'!$B:$B,0),MATCH('Forecast 1'!H$7,'Forecast 1'!$7:$7,0)),"Mismatch") -> -12680 | I53: =IF($B53='Forecast 1'!$B53,INDEX('Forecast 1'!$1:$1048576,MATCH('Forecast 1'!$B53,'Forecast 1'!$B:$B,0),MATCH('Forecast 1'!I$7,'Forecast 1'!$7:$7,0)),"Mismatch") -> -12340 | J53: =IF($B53='Forecast 1'!$B53,INDEX('Forecast 1'!$1:$1048576,MATCH('Forecast 1'!$B53,'Forecast 1'!$B:$B,0),MATCH('Forecast 1'!J$7,'Forecast 1'!$7:$7,0)),"Mismatch") -> -17568.333 | K53: =IF($B53='Forecast 1'!$B53,INDEX('Forecast 1'!$1:$1048576,MATCH('Forecast 1'!$B53,'Forecast 1'!$B:$B,0),MATCH('Forecast 1'!K$7,'Forecast 1'!$7:$7,0)),"Mismatch") -> -16958.056 | ... V53: =IF($B53='Forecast 1'!$B53,INDEX('Forecast 1'!$1:$1048576,MATCH('Forecast 1'!$B53,'Forecast 1'!$B:$B,0),MATCH('Forecast 1'!V$7,'Forecast 1'!$7:$7,0)),"Mismatch") -> -15563.802
B54: Equity Distributions | C54: Enter Manually | D54: =IF($B54='Forecast 1'!$B54,INDEX('Forecast 1'!$1:$1048576,MATCH('Forecast 1'!$B54,'Forecast 1'!$B:$B,0),MATCH('Forecast 1'!D$7,'Forecast 1'!$7:$7,0)),"Mismatch") -> 0 | E54: =IF($B54='Forecast 1'!$B54,INDEX('Forecast 1'!$1:$1048576,MATCH('Forecast 1'!$B54,'Forecast 1'!$B:$B,0),MATCH('Forecast 1'!E$7,'Forecast 1'!$7:$7,0)),"Mismatch") -> 0 | F54: =IF($B54='Forecast 1'!$B54,INDEX('Forecast 1'!$1:$1048576,MATCH('Forecast 1'!$B54,'Forecast 1'!$B:$B,0),MATCH('Forecast 1'!F$7,'Forecast 1'!$7:$7,0)),"Mismatch") -> 0 | G54: =IF($B54='Forecast 1'!$B54,INDEX('Forecast 1'!$1:$1048576,MATCH('Forecast 1'!$B54,'Forecast 1'!$B:$B,0),MATCH('Forecast 1'!G$7,'Forecast 1'!$7:$7,0)),"Mismatch") -> 0 | H54: =IF($B54='Forecast 1'!$B54,INDEX('Forecast 1'!$1:$1048576,MATCH('Forecast 1'!$B54,'Forecast 1'!$B:$B,0),MATCH('Forecast 1'!H$7,'Forecast 1'!$7:$7,0)),"Mismatch") -> 0 | I54: =IF($B54='Forecast 1'!$B54,INDEX('Forecast 1'!$1:$1048576,MATCH('Forecast 1'!$B54,'Forecast 1'!$B:$B,0),MATCH('Forecast 1'!I$7,'Forecast 1'!$7:$7,0)),"Mismatch") -> 0 | J54: =IF($B54='Forecast 1'!$B54,INDEX('Forecast 1'!$1:$1048576,MATCH('Forecast 1'!$B54,'Forecast 1'!$B:$B,0),MATCH('Forecast 1'!J$7,'Forecast 1'!$7:$7,0)),"Mismatch") -> 0 | K54: =IF($B54='Forecast 1'!$B54,INDEX('Forecast 1'!$1:$1048576,MATCH('Forecast 1'!$B54,'Forecast 1'!$B:$B,0),MATCH('Forecast 1'!K$7,'Forecast 1'!$7:$7,0)),"Mismatch") -> 0 | ... V54: =IF($B54='Forecast 1'!$B54,INDEX('Forecast 1'!$1:$1048576,MATCH('Forecast 1'!$B54,'Forecast 1'!$B:$B,0),MATCH('Forecast 1'!V$7,'Forecast 1'!$7:$7,0)),"Mismatch") -> 0
B55: Equity Contributions | C55: Enter Manually | D55: =IF($B55='Forecast 1'!$B55,INDEX('Forecast 1'!$1:$1048576,MATCH('Forecast 1'!$B55,'Forecast 1'!$B:$B,0),MATCH('Forecast 1'!D$7,'Forecast 1'!$7:$7,0)),"Mismatch") -> 0 | E55: =IF($B55='Forecast 1'!$B55,INDEX('Forecast 1'!$1:$1048576,MATCH('Forecast 1'!$B55,'Forecast 1'!$B:$B,0),MATCH('Forecast 1'!E$7,'Forecast 1'!$7:$7,0)),"Mismatch") -> 0 | F55: =IF($B55='Forecast 1'!$B55,INDEX('Forecast 1'!$1:$1048576,MATCH('Forecast 1'!$B55,'Forecast 1'!$B:$B,0),MATCH('Forecast 1'!F$7,'Forecast 1'!$7:$7,0)),"Mismatch") -> 0 | G55: =IF($B55='Forecast 1'!$B55,INDEX('Forecast 1'!$1:$1048576,MATCH('Forecast 1'!$B55,'Forecast 1'!$B:$B,0),MATCH('Forecast 1'!G$7,'Forecast 1'!$7:$7,0)),"Mismatch") -> 0 | H55: =IF($B55='Forecast 1'!$B55,INDEX('Forecast 1'!$1:$1048576,MATCH('Forecast 1'!$B55,'Forecast 1'!$B:$B,0),MATCH('Forecast 1'!H$7,'Forecast 1'!$7:$7,0)),"Mismatch") -> 0 | I55: =IF($B55='Forecast 1'!$B55,INDEX('Forecast 1'!$1:$1048576,MATCH('Forecast 1'!$B55,'Forecast 1'!$B:$B,0),MATCH('Forecast 1'!I$7,'Forecast 1'!$7:$7,0)),"Mismatch") -> 0 | J55: =IF($B55='Forecast 1'!$B55,INDEX('Forecast 1'!$1:$1048576,MATCH('Forecast 1'!$B55,'Forecast 1'!$B:$B,0),MATCH('Forecast 1'!J$7,'Forecast 1'!$7:$7,0)),"Mismatch") -> 0 | K55: =IF($B55='Forecast 1'!$B55,INDEX('Forecast 1'!$1:$1048576,MATCH('Forecast 1'!$B55,'Forecast 1'!$B:$B,0),MATCH('Forecast 1'!K$7,'Forecast 1'!$7:$7,0)),"Mismatch") -> 0 | ... V55: =IF($B55='Forecast 1'!$B55,INDEX('Forecast 1'!$1:$1048576,MATCH('Forecast 1'!$B55,'Forecast 1'!$B:$B,0),MATCH('Forecast 1'!V$7,'Forecast 1'!$7:$7,0)),"Mismatch") -> 0
B56: Other Non-operating Outflows | C56: Trailing 6 Week Average | D56: =IF($B56='Forecast 1'!$B56,INDEX('Forecast 1'!$1:$1048576,MATCH('Forecast 1'!$B56,'Forecast 1'!$B:$B,0),MATCH('Forecast 1'!D$7,'Forecast 1'!$7:$7,0)),"Mismatch") -> 0 | E56: =IF($B56='Forecast 1'!$B56,INDEX('Forecast 1'!$1:$1048576,MATCH('Forecast 1'!$B56,'Forecast 1'!$B:$B,0),MATCH('Forecast 1'!E$7,'Forecast 1'!$7:$7,0)),"Mismatch") -> -8580 | F56: =IF($B56='Forecast 1'!$B56,INDEX('Forecast 1'!$1:$1048576,MATCH('Forecast 1'!$B56,'Forecast 1'!$B:$B,0),MATCH('Forecast 1'!F$7,'Forecast 1'!$7:$7,0)),"Mismatch") -> 0 | G56: =IF($B56='Forecast 1'!$B56,INDEX('Forecast 1'!$1:$1048576,MATCH('Forecast 1'!$B56,'Forecast 1'!$B:$B,0),MATCH('Forecast 1'!G$7,'Forecast 1'!$7:$7,0)),"Mismatch") -> -1140 | H56: =IF($B56='Forecast 1'!$B56,INDEX('Forecast 1'!$1:$1048576,MATCH('Forecast 1'!$B56,'Forecast 1'!$B:$B,0),MATCH('Forecast 1'!H$7,'Forecast 1'!$7:$7,0)),"Mismatch") -> 0 | I56: =IF($B56='Forecast 1'!$B56,INDEX('Forecast 1'!$1:$1048576,MATCH('Forecast 1'!$B56,'Forecast 1'!$B:$B,0),MATCH('Forecast 1'!I$7,'Forecast 1'!$7:$7,0)),"Mismatch") -> 0 | J56: =IF($B56='Forecast 1'!$B56,INDEX('Forecast 1'!$1:$1048576,MATCH('Forecast 1'!$B56,'Forecast 1'!$B:$B,0),MATCH('Forecast 1'!J$7,'Forecast 1'!$7:$7,0)),"Mismatch") -> -1620 | K56: =IF($B56='Forecast 1'!$B56,INDEX('Forecast 1'!$1:$1048576,MATCH('Forecast 1'!$B56,'Forecast 1'!$B:$B,0),MATCH('Forecast 1'!K$7,'Forecast 1'!$7:$7,0)),"Mismatch") -> -1890 | ... V56: =IF($B56='Forecast 1'!$B56,INDEX('Forecast 1'!$1:$1048576,MATCH('Forecast 1'!$B56,'Forecast 1'!$B:$B,0),MATCH('Forecast 1'!V$7,'Forecast 1'!$7:$7,0)),"Mismatch") -> -1054.6767
B58: Total Non-operating Cash Outflows | D58: =SUM(D49:D57) -> -21230 | E58: =SUM(E49:E57) -> -33320 | F58: =SUM(F49:F57) -> -20220 | G58: =SUM(G49:G57) -> -15340 | H58: =SUM(H49:H57) -> -12680 | I58: =SUM(I49:I57) -> -12340 | J58: =SUM(J49:J57) -> -19188.333 | K58: =SUM(K49:K57) -> -18848.056 | ... V58: =SUM(V49:V57) -> -16618.479
B60: Change in Cash | D60: =SUM(D21,D46,D58) -> -135370 | E60: =SUM(E21,E46,E58) -> -36120 | F60: =SUM(F21,F46,F58) -> 65020 | G60: =SUM(G21,G46,G58) -> -195750 | H60: =SUM(H21,H46,H58) -> 281900 | I60: =SUM(I21,I46,I58) -> -110100 | J60: =SUM(J21,J46,J58) -> -103118.33 | K60: =SUM(K21,K46,K58) -> 44953.611 | ... V60: =SUM(V21,V46,V58) -> -289083.47
C62: Week End Date | D62: =+D7 -> 45227 | E62: =+E7 -> 45234 | F62: =+F7 -> 45241 | G62: =+G7 -> 45248 | H62: =+H7 -> 45255 | I62: =+I7 -> 45262 | J62: =+J7 -> 45269 | K62: =+K7 -> 45276 | ... V62: =+V7 -> 45353
C63: This week's forecast | D63: =+D12 -> 210210 | E63: =+E12 -> 174090 | F63: =+F12 -> 239110 | G63: =+G12 -> 43360 | H63: =+H12 -> 325260 | I63: =+I12 -> 215160 | J63: =+J12 -> 112041.67 | K63: =+K12 -> 156995.28 | ... V63: =+V12 -> 291189.57
C64: Last week's forecast | D64: =+D15 -> 0 | E64: =+E15 -> 0 | F64: =+F15 -> 0 | G64: =+G15 -> 0 | H64: =+H15 -> 0 | I64: =+I15 -> 0 | J64: =+J15 -> 0 | K64: =+K15 -> 0 | ... V64: =+V15 -> 0

Sheet Forecast 1
B1: Sharpe and Sortino
B2: Master Error Check Cell | D2: =+'Error Checking'!B2 -> 0
B4: Actual / Forecast | D4: Actual | E4: Actual | F4: Actual | G4: Actual | H4: Actual | I4: Actual | J4: Forecast | K4: Forecast | L4: Forecast | M4: Forecast | N4: Forecast | O4: Forecast | P4: Forecast | Q4: Forecast | R4: Forecast | S4: Forecast | T4: Forecast | U4: Forecast | V4: Forecast
B5: Week Number | D5: 1 | E5: 2 | F5: 3 | G5: 4 | H5: 5 | I5: 6 | J5: 7 | K5: 8 | L5: 9 | M5: 10 | N5: 11 | O5: 12 | P5: 13 | Q5: 14 | R5: 15 | S5: 16 | T5: 17 | U5: 18 | V5: 19
B6: Week Beginning | D6: 45221 | E6: =+D7+1 -> 45228 | F6: =+E7+1 -> 45235 | G6: =+F7+1 -> 45242 | H6: =+G7+1 -> 45249 | I6: =+H7+1 -> 45256 | J6: =+I7+1 -> 45263 | K6: =+J7+1 -> 45270 | L6: =+K7+1 -> 45277 | ... V6: =+U7+1 -> 45347
B7: Week Ending | D7: =+D6+6 -> 45227 | E7: =+E6+6 -> 45234 | F7: =+F6+6 -> 45241 | G7: =+G6+6 -> 45248 | H7: =+H6+6 -> 45255 | I7: =+I6+6 -> 45262 | J7: =+J6+6 -> 45269 | K7: =+K6+6 -> 45276 | ... V7: =+V6+6 -> 45353
B9: Cash Balance
B10: Beginning Cash | D10: =+'Bank Statement Export'!$J$56 -> 345580 | E10: =+D12 -> 210210 | F10: =+E12 -> 174090 | G10: =+F12 -> 239110 | H10: =+G12 -> 43360 | I10: =+H12 -> 325260 | J10: =+I12 -> 215160 | K10: =+J12 -> 112041.67 | L10: =+K12 -> 156995.28 | ... V10: =+U12 -> 580273.04
B11: Change in Cash | D11: =+D60 -> -135370 | E11: =+E60 -> -36120 | F11: =+F60 -> 65020 | G11: =+G60 -> -195750 | H11: =+H60 -> 281900 | I11: =+I60 -> -110100 | J11: =+J60 -> -103118.33 | K11: =+K60 -> 44953.611 | ... V11: =+V60 -> -289083.47
B12: Ending Cash | D12: =SUM(D10:D11) -> 210210 | E12: =SUM(E10:E11) -> 174090 | F12: =SUM(F10:F11) -> 239110 | G12: =SUM(G10:G11) -> 43360 | H12: =SUM(H10:H11) -> 325260 | I12: =SUM(I10:I11) -> 215160 | J12: =SUM(J10:J11) -> 112041.67 | K12: =SUM(K10:K11) -> 156995.28 | ... V12: =SUM(V10:V11) -> 291189.57
B13: Per Bank Statement | D13: =+'Bank Statement Export'!J110 -> 210210 | E13: =+'Bank Statement Export'!J187 -> 174090 | F13: =+'Bank Statement Export'!J241 -> 239110 | G13: =+'Bank Statement Export'!J286 -> 43360 | H13: =+'Bank Statement Export'!J332 -> 325260 | I13: =+'Bank Statement Export'!J381 -> 215160
B14: Double-Check | D14: =IF(D4="Forecast",0,D13-D12) -> 0 | E14: =IF(E4="Forecast",0,E13-E12) -> 0 | F14: =IF(F4="Forecast",0,F13-F12) -> 0 | G14: =IF(G4="Forecast",0,G13-G12) -> 0 | H14: =IF(H4="Forecast",0,H13-H12) -> 0 | I14: =IF(I4="Forecast",0,I13-I12) -> 0 | J14: =IF(J4="Forecast",0,J13-J12) -> 0 | K14: =IF(K4="Forecast",0,K13-K12) -> 0 | ... V14: =IF(V4="Forecast",0,V13-V12) -> 0
B15: Last Week's Forecast
B17: Cash Inflows
B18: Invoice Revenue Receipts | D18: =SUMIFS('Bank Statement Export'!$I:$I,'Bank Statement Export'!$C:$C,'Forecast 1'!$B18,'Bank Statement Export'!$A:$A,'Forecast 1'!D$7) -> 0 | E18: =SUMIFS('Bank Statement Export'!$I:$I,'Bank Statement Export'!$C:$C,'Forecast 1'!$B18,'Bank Statement Export'!$A:$A,'Forecast 1'!E$7) -> 372100 | F18: =SUMIFS('Bank Statement Export'!$I:$I,'Bank Statement Export'!$C:$C,'Forecast 1'!$B18,'Bank Statement Export'!$A:$A,'Forecast 1'!F$7) -> 210150 | G18: =SUMIFS('Bank Statement Export'!$I:$I,'Bank Statement Export'!$C:$C,'Forecast 1'!$B18,'Bank Statement Export'!$A:$A,'Forecast 1'!G$7) -> 0 | H18: =SUMIFS('Bank Statement Export'!$I:$I,'Bank Statement Export'!$C:$C,'Forecast 1'!$B18,'Bank Statement Export'!$A:$A,'Forecast 1'!H$7) -> 361430 | I18: =SUMIFS('Bank Statement Export'!$I:$I,'Bank Statement Export'!$C:$C,'Forecast 1'!$B18,'Bank Statement Export'!$A:$A,'Forecast 1'!I$7) -> 68440 | J18: =SUMIFS('AR Aging 01'!$B:$B,'AR Aging 01'!$A:$A,'Forecast 1'!J$7) -> 330000 | K18: =SUMIFS('AR Aging 01'!$B:$B,'AR Aging 01'!$A:$A,'Forecast 1'!K$7) -> 120000 | L18: =SUMIFS('AR Aging 01'!$B:$B,'AR Aging 01'!$A:$A,'Forecast 1'!L$7) -> 454000 | M18: =SUMIFS('AR Aging 01'!$B:$B,'AR Aging 01'!$A:$A,'Forecast 1'!M$7) -> 80000 | N18: =SUMIFS('AR Aging 01'!$B:$B,'AR Aging 01'!$A:$A,'Forecast 1'!N$7) -> 100000 | O18: =SUMIFS('AR Aging 01'!$B:$B,'AR Aging 01'!$A:$A,'Forecast 1'!O$7) -> 0 | P18: =SUMIFS('AR Aging 01'!$B:$B,'AR Aging 01'!$A:$A,'Forecast 1'!P$7) -> 271800 | Q18: =SUMIFS('AR Aging 01'!$B:$B,'AR Aging 01'!$A:$A,'Forecast 1'!Q$7) -> 80000 | ... V18: =SUMIFS('AR Aging 01'!$B:$B,'AR Aging 01'!$A:$A,'Forecast 1'!V$7) -> 0
B19: Other Receipts | D19: =SUMIFS('Bank Statement Export'!$I:$I,'Bank Statement Export'!$C:$C,'Forecast 1'!$B19,'Bank Statement Export'!$A:$A,'Forecast 1'!D$7) -> 0 | E19: =SUMIFS('Bank Statement Export'!$I:$I,'Bank Statement Export'!$C:$C,'Forecast 1'!$B19,'Bank Statement Export'!$A:$A,'Forecast 1'!E$7) -> 0 | F19: =SUMIFS('Bank Statement Export'!$I:$I,'Bank Statement Export'!$C:$C,'Forecast 1'!$B19,'Bank Statement Export'!$A:$A,'Forecast 1'!F$7) -> 0 | G19: =SUMIFS('Bank Statement Export'!$I:$I,'Bank Statement Export'!$C:$C,'Forecast 1'!$B19,'Bank Statement Export'!$A:$A,'Forecast 1'!G$7) -> 0 | H19: =SUMIFS('Bank Statement Export'!$I:$I,'Bank Statement Export'!$C:$C,'Forecast 1'!$B19,'Bank Statement Export'!$A:$A,'Forecast 1'!H$7) -> 0 | I19: =SUMIFS('Bank Statement Export'!$I:$I,'Bank Statement Export'!$C:$C,'Forecast 1'!$B19,'Bank Statement Export'!$A:$A,'Forecast 1'!I$7) -> 0 | J19: =SUMIFS('Bank Statement Export'!$I:$I,'Bank Statement Export'!$C:$C,'Forecast 1'!$B19,'Bank Statement Export'!$A:$A,'Forecast 1'!J$7) -> 0 | K19: =SUMIFS('Bank Statement Export'!$I:$I,'Bank Statement Export'!$C:$C,'Forecast 1'!$B19,'Bank Statement Export'!$A:$A,'Forecast 1'!K$7) -> 0 | ... V19: =SUMIFS('Bank Statement Export'!$I:$I,'Bank Statement Export'!$C:$C,'Forecast 1'!$B19,'Bank Statement Export'!$A:$A,'Forecast 1'!V$7) -> 0
B21: Total Cash Inflows | D21: =SUM(D18:D20) -> 0 | E21: =SUM(E18:E20) -> 372100 | F21: =SUM(F18:F20) -> 210150 | G21: =SUM(G18:G20) -> 0 | H21: =SUM(H18:H20) -> 361430 | I21: =SUM(I18:I20) -> 68440 | J21: =SUM(J18:J20) -> 330000 | K21: =SUM(K18:K20) -> 120000 | ... V21: =SUM(V18:V20) -> 0
B23: Operating Cash Outflows
B24: Accounts Payable | D24: =SUMIFS('Bank Statement Export'!$I:$I,'Bank Statement Export'!$C:$C,'Forecast 1'!$B24,'Bank Statement Export'!$A:$A,'Forecast 1'!D$7) -> -33620 | E24: =SUMIFS('Bank Statement Export'!$I:$I,'Bank Statement Export'!$C:$C,'Forecast 1'!$B24,'Bank Statement Export'!$A:$A,'Forecast 1'!E$7) -> -83210 | F24: =SUMIFS('Bank Statement Export'!$I:$I,'Bank Statement Export'!$C:$C,'Forecast 1'!$B24,'Bank Statement Export'!$A:$A,'Forecast 1'!F$7) -> -69810 | G24: =SUMIFS('Bank Statement Export'!$I:$I,'Bank Statement Export'!$C:$C,'Forecast 1'!$B24,'Bank Statement Export'!$A:$A,'Forecast 1'!G$7) -> -40140 | H24: =SUMIFS('Bank Statement Export'!$I:$I,'Bank Statement Export'!$C:$C,'Forecast 1'!$B24,'Bank Statement Export'!$A:$A,'Forecast 1'!H$7) -> -18680 | I24: =SUMIFS('Bank Statement Export'!$I:$I,'Bank Statement Export'!$C:$C,'Forecast 1'!$B24,'Bank Statement Export'!$A:$A,'Forecast 1'!I$7) -> -88580 | J24: =-SUMIFS('AP Aging 01'!$B:$B,'AP Aging 01'!$A:$A,'Forecast 1'!J$7,'AP Aging 01'!$D:$D,"<>Yes") -> -800 | K24: =-SUMIFS('AP Aging 01'!$B:$B,'AP Aging 01'!$A:$A,'Forecast 1'!K$7,'AP Aging 01'!$D:$D,"<>Yes") -> -1800 | L24: =-SUMIFS('AP Aging 01'!$B:$B,'AP Aging 01'!$A:$A,'Forecast 1'!L$7,'AP Aging 01'!$D:$D,"<>Yes") -> -145800 | M24: =-SUMIFS('AP Aging 01'!$B:$B,'AP Aging 01'!$A:$A,'Forecast 1'!M$7,'AP Aging 01'!$D:$D,"<>Yes") -> 0 | N24: =-SUMIFS('AP Aging 01'!$B:$B,'AP Aging 01'!$A:$A,'Forecast 1'!N$7,'AP Aging 01'!$D:$D,"<>Yes") -> 0 | O24: =-SUMIFS('AP Aging 01'!$B:$B,'AP Aging 01'!$A:$A,'Forecast 1'!O$7,'AP Aging 01'!$D:$D,"<>Yes") -> 0 | P24: =-SUMIFS('AP Aging 01'!$B:$B,'AP Aging 01'!$A:$A,'Forecast 1'!P$7,'AP Aging 01'!$D:$D,"<>Yes") -> 0 | Q24: =-SUMIFS('AP Aging 01'!$B:$B,'AP Aging 01'!$A:$A,'Forecast 1'!Q$7,'AP Aging 01'!$D:$D,"<>Yes") -> 0 | ... V24: =-SUMIFS('AP Aging 01'!$B:$B,'AP Aging 01'!$A:$A,'Forecast 1'!V$7,'AP Aging 01'!$D:$D,"<>Yes") -> 0
B25: Credit Cards | D25: =SUMIFS('Bank Statement Export'!$I:$I,'Bank Statement Export'!$C:$C,'Forecast 1'!$B25,'Bank Statement Export'!$A:$A,'Forecast 1'!D$7) -> 0 | E25: =SUMIFS('Bank Statement Export'!$I:$I,'Bank Statement Export'!$C:$C,'Forecast 1'!$B25,'Bank Statement Export'!$A:$A,'Forecast 1'!E$7) -> -194090 | F25: =SUMIFS('Bank Statement Export'!$I:$I,'Bank Statement Export'!$C:$C,'Forecast 1'!$B25,'Bank Statement Export'!$A:$A,'Forecast 1'!F$7) -> 0 | G25: =SUMIFS('Bank Statement Export'!$I:$I,'Bank Statement Export'!$C:$C,'Forecast 1'!$B25,'Bank Statement Export'!$A:$A,'Forecast 1'!G$7) -> -100000 | H25: =SUMIFS('Bank Statement Export'!$I:$I,'Bank Statement Export'!$C:$C,'Forecast 1'!$B25,'Bank Statement Export'!$A:$A,'Forecast 1'!H$7) -> 0 | I25: =SUMIFS('Bank Statement Export'!$I:$I,'Bank Statement Export'!$C:$C,'Forecast 1'!$B25,'Bank Statement Export'!$A:$A,'Forecast 1'!I$7) -> -32000 | J25: =-SUMIFS('AP Aging 01'!$B:$B,'AP Aging 01'!$A:$A,'Forecast 1'!J$7,'AP Aging 01'!$D:$D,"Yes") -> -350000 | K25: =-SUMIFS('AP Aging 01'!$B:$B,'AP Aging 01'!$A:$A,'Forecast 1'!K$7,'AP Aging 01'!$D:$D,"Yes") -> 0 | L25: =-SUMIFS('AP Aging 01'!$B:$B,'AP Aging 01'!$A:$A,'Forecast 1'!L$7,'AP Aging 01'!$D:$D,"Yes") -> 0 | M25: =-SUMIFS('AP Aging 01'!$B:$B,'AP Aging 01'!$A:$A,'Forecast 1'!M$7,'AP Aging 01'!$D:$D,"Yes") -> 0 | N25: =-SUMIFS('AP Aging 01'!$B:$B,'AP Aging 01'!$A:$A,'Forecast 1'!N$7,'AP Aging 01'!$D:$D,"Yes") -> -55000 | O25: =-SUMIFS('AP Aging 01'!$B:$B,'AP Aging 01'!$A:$A,'Forecast 1'!O$7,'AP Aging 01'!$D:$D,"Yes") -> 0 | P25: =-SUMIFS('AP Aging 01'!$B:$B,'AP Aging 01'!$A:$A,'Forecast 1'!P$7,'AP Aging 01'!$D:$D,"Yes") -> 0 | Q25: =-SUMIFS('AP Aging 01'!$B:$B,'AP Aging 01'!$A:$A,'Forecast 1'!Q$7,'AP Aging 01'!$D:$D,"Yes") -> 0 | ... V25: =-SUMIFS('AP Aging 01'!$B:$B,'AP Aging 01'!$A:$A,'Forecast 1'!V$7,'AP Aging 01'!$D:$D,"Yes") -> -210000
B26: Payroll | C26: Trailing 6 Week Average | D26: =SUMIFS('Bank Statement Export'!$I:$I,'Bank Statement Export'!$C:$C,'Forecast 1'!$B26,'Bank Statement Export'!$A:$A,'Forecast 1'!D$7) -> -77830 | E26: =SUMIFS('Bank Statement Export'!$I:$I,'Bank Statement Export'!$C:$C,'Forecast 1'!$B26,'Bank Statement Export'!$A:$A,'Forecast 1'!E$7) -> -78050 | F26: =SUMIFS('Bank Statement Export'!$I:$I,'Bank Statement Export'!$C:$C,'Forecast 1'!$B26,'Bank Statement Export'!$A:$A,'Forecast 1'!F$7) -> -51670 | G26: =SUMIFS('Bank Statement Export'!$I:$I,'Bank Statement Export'!$C:$C,'Forecast 1'!$B26,'Bank Statement Export'!$A:$A,'Forecast 1'!G$7) -> -39960 | H26: =SUMIFS('Bank Statement Export'!$I:$I,'Bank Statement Export'!$C:$C,'Forecast 1'!$B26,'Bank Statement Export'!$A:$A,'Forecast 1'!H$7) -> -44380 | I26: =SUMIFS('Bank Statement Export'!$I:$I,'Bank Statement Export'!$C:$C,'Forecast 1'!$B26,'Bank Statement Export'!$A:$A,'Forecast 1'!I$7) -> -35340 | J26: =AVERAGE(D26:I26) -> -54538.333 | K26: =AVERAGE(E26:J26) -> -50656.389 | L26: =AVERAGE(F26:K26) -> -46090.787 | M26: =AVERAGE(G26:L26) -> -45160.918 | N26: =AVERAGE(H26:M26) -> -46027.738 | O26: =AVERAGE(I26:N26) -> -46302.361 | P26: =AVERAGE(J26:O26) -> -48129.421 | Q26: =AVERAGE(K26:P26) -> -47061.269 | ... V26: =AVERAGE(P26:U26) -> -46966.597
B27: Contractors | C27: Enter Manually | D27: =SUMIFS('Bank Statement Export'!$I:$I,'Bank Statement Export'!$C:$C,'Forecast 1'!$B27,'Bank Statement Export'!$A:$A,'Forecast 1'!D$7) -> 0 | E27: =SUMIFS('Bank Statement Export'!$I:$I,'Bank Statement Export'!$C:$C,'Forecast 1'!$B27,'Bank Statement Export'!$A:$A,'Forecast 1'!E$7) -> 0 | F27: =SUMIFS('Bank Statement Export'!$I:$I,'Bank Statement Export'!$C:$C,'Forecast 1'!$B27,'Bank Statement Export'!$A:$A,'Forecast 1'!F$7) -> 0 | G27: =SUMIFS('Bank Statement Export'!$I:$I,'Bank Statement Export'!$C:$C,'Forecast 1'!$B27,'Bank Statement Export'!$A:$A,'Forecast 1'!G$7) -> 0 | H27: =SUMIFS('Bank Statement Export'!$I:$I,'Bank Statement Export'!$C:$C,'Forecast 1'!$B27,'Bank Statement Export'!$A:$A,'Forecast 1'!H$7) -> 0 | I27: =SUMIFS('Bank Statement Export'!$I:$I,'Bank Statement Export'!$C:$C,'Forecast 1'!$B27,'Bank Statement Export'!$A:$A,'Forecast 1'!I$7) -> 0 | J27: 0 | K27: 0 | L27: 0 | M27: 0 | N27: 0 | O27: 0 | P27: 0 | Q27: 0 | R27: 0 | S27: 0 | T27: 0 | U27: 0 | V27: 0
B28: Dues & Subscriptions | C28: Trailing 6 Week Average | D28: =SUMIFS('Bank Statement Export'!$I:$I,'Bank Statement Export'!$C:$C,'Forecast 1'!$B28,'Bank Statement Export'!$A:$A,'Forecast 1'!D$7) -> -310 | E28: =SUMIFS('Bank Statement Export'!$I:$I,'Bank Statement Export'!$C:$C,'Forecast 1'!$B28,'Bank Statement Export'!$A:$A,'Forecast 1'!E$7) -> -310 | F28: =SUMIFS('Bank Statement Export'!$I:$I,'Bank Statement Export'!$C:$C,'Forecast 1'!$B28,'Bank Statement Export'!$A:$A,'Forecast 1'!F$7) -> -310 | G28: =SUMIFS('Bank Statement Export'!$I:$I,'Bank Statement Export'!$C:$C,'Forecast 1'!$B28,'Bank Statement Export'!$A:$A,'Forecast 1'!G$7) -> -310 | H28: =SUMIFS('Bank Statement Export'!$I:$I,'Bank Statement Export'!$C:$C,'Forecast 1'!$B28,'Bank Statement Export'!$A:$A,'Forecast 1'!H$7) -> -310 | I28: =SUMIFS('Bank Statement Export'!$I:$I,'Bank Statement Export'!$C:$C,'Forecast 1'!$B28,'Bank Statement Export'!$A:$A,'Forecast 1'!I$7) -> -310 | J28: =AVERAGE(D28:I28) -> -310 | K28: =AVERAGE(E28:J28) -> -310 | L28: =AVERAGE(F28:K28) -> -310 | M28: =AVERAGE(G28:L28) -> -310 | N28: =AVERAGE(H28:M28) -> -310 | O28: =AVERAGE(I28:N28) -> -310 | P28: =AVERAGE(J28:O28) -> -310 | Q28: =AVERAGE(K28:P28) -> -310 | ... V28: =AVERAGE(P28:U28) -> -310
B29: Insurance | C29: Enter Manually | D29: =SUMIFS('Bank Statement Export'!$I:$I,'Bank Statement Export'!$C:$C,'Forecast 1'!$B29,'Bank Statement Export'!$A:$A,'Forecast 1'!D$7) -> 0 | E29: =SUMIFS('Bank Statement Export'!$I:$I,'Bank Statement Export'!$C:$C,'Forecast 1'!$B29,'Bank Statement Export'!$A:$A,'Forecast 1'!E$7) -> 0 | F29: =SUMIFS('Bank Statement Export'!$I:$I,'Bank Statement Export'!$C:$C,'Forecast 1'!$B29,'Bank Statement Export'!$A:$A,'Forecast 1'!F$7) -> 0 | G29: =SUMIFS('Bank Statement Export'!$I:$I,'Bank Statement Export'!$C:$C,'Forecast 1'!$B29,'Bank Statement Export'!$A:$A,'Forecast 1'!G$7) -> 0 | H29: =SUMIFS('Bank Statement Export'!$I:$I,'Bank Statement Export'!$C:$C,'Forecast 1'!$B29,'Bank Statement Export'!$A:$A,'Forecast 1'!H$7) -> 0 | I29: =SUMIFS('Bank Statement Export'!$I:$I,'Bank Statement Export'!$C:$C,'Forecast 1'!$B29,'Bank Statement Export'!$A:$A,'Forecast 1'!I$7) -> 0 | J29: =SUMIFS('Bank Statement Export'!$I:$I,'Bank Statement Export'!$C:$C,'Forecast 1'!$B29,'Bank Statement Export'!$A:$A,'Forecast 1'!J$7) -> 0 | K29: =SUMIFS('Bank Statement Export'!$I:$I,'Bank Statement Export'!$C:$C,'Forecast 1'!$B29,'Bank Statement Export'!$A:$A,'Forecast 1'!K$7) -> 0 | ... V29: =SUMIFS('Bank Statement Export'!$I:$I,'Bank Statement Export'!$C:$C,'Forecast 1'!$B29,'Bank Statement Export'!$A:$A,'Forecast 1'!V$7) -> 0
B30: Lease Payments | C30: Trailing 6 Week Average | D30: =SUMIFS('Bank Statement Export'!$I:$I,'Bank Statement Export'!$C:$C,'Forecast 1'!$B30,'Bank Statement Export'!$A:$A,'Forecast 1'!D$7) -> 0 | E30: =SUMIFS('Bank Statement Export'!$I:$I,'Bank Statement Export'!$C:$C,'Forecast 1'!$B30,'Bank Statement Export'!$A:$A,'Forecast 1'!E$7) -> -1350 | F30: =SUMIFS('Bank Statement Export'!$I:$I,'Bank Statement Export'!$C:$C,'Forecast 1'!$B30,'Bank Statement Export'!$A:$A,'Forecast 1'!F$7) -> 0 | G30: =SUMIFS('Bank Statement Export'!$I:$I,'Bank Statement Export'!$C:$C,'Forecast 1'!$B30,'Bank Statement Export'!$A:$A,'Forecast 1'!G$7) -> 0 | H30: =SUMIFS('Bank Statement Export'!$I:$I,'Bank Statement Export'!$C:$C,'Forecast 1'!$B30,'Bank Statement Export'!$A:$A,'Forecast 1'!H$7) -> -1350 | I30: =SUMIFS('Bank Statement Export'!$I:$I,'Bank Statement Export'!$C:$C,'Forecast 1'!$B30,'Bank Statement Export'!$A:$A,'Forecast 1'!I$7) -> -1350 | J30: =AVERAGE(D30:I30) -> -675 | K30: =AVERAGE(E30:J30) -> -787.5 | L30: =AVERAGE(F30:K30) -> -693.75 | M30: =AVERAGE(G30:L30) -> -809.375 | N30: =AVERAGE(H30:M30) -> -944.27083 | O30: =AVERAGE(I30:N30) -> -876.64931 | P30: =AVERAGE(J30:O30) -> -797.75752 | Q30: =AVERAGE(K30:P30) -> -818.21711 | ... V30: =AVERAGE(P30:U30) -> -828.39988
B31: Marketing | C31: Trailing 6 Week Average | D31: =SUMIFS('Bank Statement Export'!$I:$I,'Bank Statement Export'!$C:$C,'Forecast 1'!$B31,'Bank Statement Export'!$A:$A,'Forecast 1'!D$7) -> 0 | E31: =SUMIFS('Bank Statement Export'!$I:$I,'Bank Statement Export'!$C:$C,'Forecast 1'!$B31,'Bank Statement Export'!$A:$A,'Forecast 1'!E$7) -> -1510 | F31: =SUMIFS('Bank Statement Export'!$I:$I,'Bank Statement Export'!$C:$C,'Forecast 1'!$B31,'Bank Statement Export'!$A:$A,'Forecast 1'!F$7) -> -1020 | G31: =SUMIFS('Bank Statement Export'!$I:$I,'Bank Statement Export'!$C:$C,'Forecast 1'!$B31,'Bank Statement Export'!$A:$A,'Forecast 1'!G$7) -> 0 | H31: =SUMIFS('Bank Statement Export'!$I:$I,'Bank Statement Export'!$C:$C,'Forecast 1'!$B31,'Bank Statement Export'!$A:$A,'Forecast 1'!H$7) -> 0 | I31: =SUMIFS('Bank Statement Export'!$I:$I,'Bank Statement Export'!$C:$C,'Forecast 1'!$B31,'Bank Statement Export'!$A:$A,'Forecast 1'!I$7) -> -1510 | J31: =AVERAGE(D31:I31) -> -673.33333 | K31: =AVERAGE(E31:J31) -> -785.55556 | L31: =AVERAGE(F31:K31) -> -664.81481 | M31: =AVERAGE(G31:L31) -> -605.61728 | N31: =AVERAGE(H31:M31) -> -706.5535 | O31: =AVERAGE(I31:N31) -> -824.31241 | P31: =AVERAGE(J31:O31) -> -710.03115 | Q31: =AVERAGE(K31:P31) -> -716.14745 | ... V31: =AVERAGE(P31:U31) -> -717.21397
B32: Phone & Internet | C32: Enter Manually | D32: =SUMIFS('Bank Statement Export'!$I:$I,'Bank Statement Export'!$C:$C,'Forecast 1'!$B32,'Bank Statement Export'!$A:$A,'Forecast 1'!D$7) -> 0 | E32: =SUMIFS('Bank Statement Export'!$I:$I,'Bank Statement Export'!$C:$C,'Forecast 1'!$B32,'Bank Statement Export'!$A:$A,'Forecast 1'!E$7) -> 0 | F32: =SUMIFS('Bank Statement Export'!$I:$I,'Bank Statement Export'!$C:$C,'Forecast 1'!$B32,'Bank Statement Export'!$A:$A,'Forecast 1'!F$7) -> 0 | G32: =SUMIFS('Bank Statement Export'!$I:$I,'Bank Statement Export'!$C:$C,'Forecast 1'!$B32,'Bank Statement Export'!$A:$A,'Forecast 1'!G$7) -> 0 | H32: =SUMIFS('Bank Statement Export'!$I:$I,'Bank Statement Export'!$C:$C,'Forecast 1'!$B32,'Bank Statement Export'!$A:$A,'Forecast 1'!H$7) -> 0 | I32: =SUMIFS('Bank Statement Export'!$I:$I,'Bank Statement Export'!$C:$C,'Forecast 1'!$B32,'Bank Statement Export'!$A:$A,'Forecast 1'!I$7) -> 0 | J32: =SUMIFS('Bank Statement Export'!$I:$I,'Bank Statement Export'!$C:$C,'Forecast 1'!$B32,'Bank Statement Export'!$A:$A,'Forecast 1'!J$7) -> 0 | K32: =SUMIFS('Bank Statement Export'!$I:$I,'Bank Statement Export'!$C:$C,'Forecast 1'!$B32,'Bank Statement Export'!$A:$A,'Forecast 1'!K$7) -> 0 | ... V32: =SUMIFS('Bank Statement Export'!$I:$I,'Bank Statement Export'!$C:$C,'Forecast 1'!$B32,'Bank Statement Export'!$A:$A,'Forecast 1'!V$7) -> 0
B33: Professional Fees | C33: $5k each Month | D33: =SUMIFS('Bank Statement Export'!$I:$I,'Bank Statement Export'!$C:$C,'Forecast 1'!$B33,'Bank Statement Export'!$A:$A,'Forecast 1'!D$7) -> 0 | E33: =SUMIFS('Bank Statement Export'!$I:$I,'Bank Statement Export'!$C:$C,'Forecast 1'!$B33,'Bank Statement Export'!$A:$A,'Forecast 1'!E$7) -> -5000 | F33: =SUMIFS('Bank Statement Export'!$I:$I,'Bank Statement Export'!$C:$C,'Forecast 1'!$B33,'Bank Statement Export'!$A:$A,'Forecast 1'!F$7) -> 0 | G33: =SUMIFS('Bank Statement Export'!$I:$I,'Bank Statement Export'!$C:$C,'Forecast 1'!$B33,'Bank Statement Export'!$A:$A,'Forecast 1'!G$7) -> 0 | H33: =SUMIFS('Bank Statement Export'!$I:$I,'Bank Statement Export'!$C:$C,'Forecast 1'!$B33,'Bank Statement Export'!$A:$A,'Forecast 1'!H$7) -> 0 | I33: =SUMIFS('Bank Statement Export'!$I:$I,'Bank Statement Export'!$C:$C,'Forecast 1'!$B33,'Bank Statement Export'!$A:$A,'Forecast 1'!I$7) -> 0 | J33: -5000 | K33: =SUMIFS('Bank Statement Export'!$I:$I,'Bank Statement Export'!$C:$C,'Forecast 1'!$B33,'Bank Statement Export'!$A:$A,'Forecast 1'!K$7) -> 0 | L33: =SUMIFS('Bank Statement Export'!$I:$I,'Bank Statement Export'!$C:$C,'Forecast 1'!$B33,'Bank Statement Export'!$A:$A,'Forecast 1'!L$7) -> 0 | M33: =SUMIFS('Bank Statement Export'!$I:$I,'Bank Statement Export'!$C:$C,'Forecast 1'!$B33,'Bank Statement Export'!$A:$A,'Forecast 1'!M$7) -> 0 | N33: -5000 | O33: =SUMIFS('Bank Statement Export'!$I:$I,'Bank Statement Export'!$C:$C,'Forecast 1'!$B33,'Bank Statement Export'!$A:$A,'Forecast 1'!O$7) -> 0 | P33: =SUMIFS('Bank Statement Export'!$I:$I,'Bank Statement Export'!$C:$C,'Forecast 1'!$B33,'Bank Statement Export'!$A:$A,'Forecast 1'!P$7) -> 0 | Q33: =SUMIFS('Bank Statement Export'!$I:$I,'Bank Statement Export'!$C:$C,'Forecast 1'!$B33,'Bank Statement Export'!$A:$A,'Forecast 1'!Q$7) -> 0 | R33: -5000 | S33: =SUMIFS('Bank Statement Export'!$I:$I,'Bank Statement Export'!$C:$C,'Forecast 1'!$B33,'Bank Statement Export'!$A:$A,'Forecast 1'!S$7) -> 0 | T33: =SUMIFS('Bank Statement Export'!$I:$I,'Bank Statement Export'!$C:$C,'Forecast 1'!$B33,'Bank Statement Export'!$A:$A,'Forecast 1'!T$7) -> 0 | U33: =SUMIFS('Bank Statement Export'!$I:$I,'Bank Statement Export'!$C:$C,'Forecast 1'!$B33,'Bank Statement Export'!$A:$A,'Forecast 1'!U$7) -> 0 | V33: -5000
B34: Rent | C34: Enter Manually | D34: =SUMIFS('Bank Statement Export'!$I:$I,'Bank Statement Export'!$C:$C,'Forecast 1'!$B34,'Bank Statement Export'!$A:$A,'Forecast 1'!D$7) -> 0 | E34: =SUMIFS('Bank Statement Export'!$I:$I,'Bank Statement Export'!$C:$C,'Forecast 1'!$B34,'Bank Statement Export'!$A:$A,'Forecast 1'!E$7) -> 0 | F34: =SUMIFS('Bank Statement Export'!$I:$I,'Bank Statement Export'!$C:$C,'Forecast 1'!$B34,'Bank Statement Export'!$A:$A,'Forecast 1'!F$7) -> 0 | G34: =SUMIFS('Bank Statement Export'!$I:$I,'Bank Statement Export'!$C:$C,'Forecast 1'!$B34,'Bank Statement Export'!$A:$A,'Forecast 1'!G$7) -> 0 | H34: =SUMIFS('Bank Statement Export'!$I:$I,'Bank Statement Export'!$C:$C,'Forecast 1'!$B34,'Bank Statement Export'!$A:$A,'Forecast 1'!H$7) -> 0 | I34: =SUMIFS('Bank Statement Export'!$I:$I,'Bank Statement Export'!$C:$C,'Forecast 1'!$B34,'Bank Statement Export'!$A:$A,'Forecast 1'!I$7) -> 0 | J34: =SUMIFS('Bank Statement Export'!$I:$I,'Bank Statement Export'!$C:$C,'Forecast 1'!$B34,'Bank Statement Export'!$A:$A,'Forecast 1'!J$7) -> 0 | K34: =SUMIFS('Bank Statement Export'!$I:$I,'Bank Statement Export'!$C:$C,'Forecast 1'!$B34,'Bank Statement Export'!$A:$A,'Forecast 1'!K$7) -> 0 | ... V34: =SUMIFS('Bank Statement Export'!$I:$I,'Bank Statement Export'!$C:$C,'Forecast 1'!$B34,'Bank Statement Export'!$A:$A,'Forecast 1'!V$7) -> 0
B35: Repairs & Maintenance | C35: Enter Manually | D35: =SUMIFS('Bank Statement Export'!$I:$I,'Bank Statement Export'!$C:$C,'Forecast 1'!$B35,'Bank Statement Export'!$A:$A,'Forecast 1'!D$7) -> 0 | E35: =SUMIFS('Bank Statement Export'!$I:$I,'Bank Statement Export'!$C:$C,'Forecast 1'!$B35,'Bank Statement Export'!$A:$A,'Forecast 1'!E$7) -> 0 | F35: =SUMIFS('Bank Statement Export'!$I:$I,'Bank Statement Export'!$C:$C,'Forecast 1'!$B35,'Bank Statement Export'!$A:$A,'Forecast 1'!F$7) -> 0 | G35: =SUMIFS('Bank Statement Export'!$I:$I,'Bank Statement Export'!$C:$C,'Forecast 1'!$B35,'Bank Statement Export'!$A:$A,'Forecast 1'!G$7) -> 0 | H35: =SUMIFS('Bank Statement Export'!$I:$I,'Bank Statement Export'!$C:$C,'Forecast 1'!$B35,'Bank Statement Export'!$A:$A,'Forecast 1'!H$7) -> 0 | I35: =SUMIFS('Bank Statement Export'!$I:$I,'Bank Statement Export'!$C:$C,'Forecast 1'!$B35,'Bank Statement Export'!$A:$A,'Forecast 1'!I$7) -> 0 | J35: =SUMIFS('Bank Statement Export'!$I:$I,'Bank Statement Export'!$C:$C,'Forecast 1'!$B35,'Bank Statement Export'!$A:$A,'Forecast 1'!J$7) -> 0 | K35: =SUMIFS('Bank Statement Export'!$I:$I,'Bank Statement Export'!$C:$C,'Forecast 1'!$B35,'Bank Statement Export'!$A:$A,'Forecast 1'!K$7) -> 0 | ... V35: =SUMIFS('Bank Statement Export'!$I:$I,'Bank Statement Export'!$C:$C,'Forecast 1'!$B35,'Bank Statement Export'!$A:$A,'Forecast 1'!V$7) -> 0
B36: Supplies | C36: Enter Manually | D36: =SUMIFS('Bank Statement Export'!$I:$I,'Bank Statement Export'!$C:$C,'Forecast 1'!$B36,'Bank Statement Export'!$A:$A,'Forecast 1'!D$7) -> 0 | E36: =SUMIFS('Bank Statement Export'!$I:$I,'Bank Statement Export'!$C:$C,'Forecast 1'!$B36,'Bank Statement Export'!$A:$A,'Forecast 1'!E$7) -> 0 | F36: =SUMIFS('Bank Statement Export'!$I:$I,'Bank Statement Export'!$C:$C,'Forecast 1'!$B36,'Bank Statement Export'!$A:$A,'Forecast 1'!F$7) -> 0 | G36: =SUMIFS('Bank Statement Export'!$I:$I,'Bank Statement Export'!$C:$C,'Forecast 1'!$B36,'Bank Statement Export'!$A:$A,'Forecast 1'!G$7) -> 0 | H36: =SUMIFS('Bank Statement Export'!$I:$I,'Bank Statement Export'!$C:$C,'Forecast 1'!$B36,'Bank Statement Export'!$A:$A,'Forecast 1'!H$7) -> 0 | I36: =SUMIFS('Bank Statement Export'!$I:$I,'Bank Statement Export'!$C:$C,'Forecast 1'!$B36,'Bank Statement Export'!$A:$A,'Forecast 1'!I$7) -> 0 | J36: =SUMIFS('Bank Statement Export'!$I:$I,'Bank Statement Export'!$C:$C,'Forecast 1'!$B36,'Bank Statement Export'!$A:$A,'Forecast 1'!J$7) -> 0 | K36: =SUMIFS('Bank Statement Export'!$I:$I,'Bank Statement Export'!$C:$C,'Forecast 1'!$B36,'Bank Statement Export'!$A:$A,'Forecast 1'!K$7) -> 0 | ... V36: =SUMIFS('Bank Statement Export'!$I:$I,'Bank Statement Export'!$C:$C,'Forecast 1'!$B36,'Bank Statement Export'!$A:$A,'Forecast 1'!V$7) -> 0
B37: Licenses | C37: Enter Manually | D37: =SUMIFS('Bank Statement Export'!$I:$I,'Bank Statement Export'!$C:$C,'Forecast 1'!$B37,'Bank Statement Export'!$A:$A,'Forecast 1'!D$7) -> 0 | E37: =SUMIFS('Bank Statement Export'!$I:$I,'Bank Statement Export'!$C:$C,'Forecast 1'!$B37,'Bank Statement Export'!$A:$A,'Forecast 1'!E$7) -> 0 | F37: =SUMIFS('Bank Statement Export'!$I:$I,'Bank Statement Export'!$C:$C,'Forecast 1'!$B37,'Bank Statement Export'!$A:$A,'Forecast 1'!F$7) -> 0 | G37: =SUMIFS('Bank Statement Export'!$I:$I,'Bank Statement Export'!$C:$C,'Forecast 1'!$B37,'Bank Statement Export'!$A:$A,'Forecast 1'!G$7) -> 0 | H37: =SUMIFS('Bank Statement Export'!$I:$I,'Bank Statement Export'!$C:$C,'Forecast 1'!$B37,'Bank Statement Export'!$A:$A,'Forecast 1'!H$7) -> 0 | I37: =SUMIFS('Bank Statement Export'!$I:$I,'Bank Statement Export'!$C:$C,'Forecast 1'!$B37,'Bank Statement Export'!$A:$A,'Forecast 1'!I$7) -> 0 | J37: =SUMIFS('Bank Statement Export'!$I:$I,'Bank Statement Export'!$C:$C,'Forecast 1'!$B37,'Bank Statement Export'!$A:$A,'Forecast 1'!J$7) -> 0 | K37: =SUMIFS('Bank Statement Export'!$I:$I,'Bank Statement Export'!$C:$C,'Forecast 1'!$B37,'Bank Statement Export'!$A:$A,'Forecast 1'!K$7) -> 0 | ... V37: =SUMIFS('Bank Statement Export'!$I:$I,'Bank Statement Export'!$C:$C,'Forecast 1'!$B37,'Bank Statement Export'!$A:$A,'Forecast 1'!V$7) -> 0
B38: Technology | C38: Trailing 6 Week Average | D38: =SUMIFS('Bank Statement Export'!$I:$I,'Bank Statement Export'!$C:$C,'Forecast 1'!$B38,'Bank Statement Export'!$A:$A,'Forecast 1'!D$7) -> -1110 | E38: =SUMIFS('Bank Statement Export'!$I:$I,'Bank Statement Export'!$C:$C,'Forecast 1'!$B38,'Bank Statement Export'!$A:$A,'Forecast 1'!E$7) -> -1150 | F38: =SUMIFS('Bank Statement Export'!$I:$I,'Bank Statement Export'!$C:$C,'Forecast 1'!$B38,'Bank Statement Export'!$A:$A,'Forecast 1'!F$7) -> -2100 | G38: =SUMIFS('Bank Statement Export'!$I:$I,'Bank Statement Export'!$C:$C,'Forecast 1'!$B38,'Bank Statement Export'!$A:$A,'Forecast 1'!G$7) -> 0 | H38: =SUMIFS('Bank Statement Export'!$I:$I,'Bank Statement Export'!$C:$C,'Forecast 1'!$B38,'Bank Statement Export'!$A:$A,'Forecast 1'!H$7) -> -2130 | I38: =SUMIFS('Bank Statement Export'!$I:$I,'Bank Statement Export'!$C:$C,'Forecast 1'!$B38,'Bank Statement Export'!$A:$A,'Forecast 1'!I$7) -> 0 | J38: =AVERAGE(D38:I38) -> -1081.6667 | K38: =AVERAGE(E38:J38) -> -1076.9444 | L38: =AVERAGE(F38:K38) -> -1064.7685 | M38: =AVERAGE(G38:L38) -> -892.22994 | N38: =AVERAGE(H38:M38) -> -1040.9349 | O38: =AVERAGE(I38:N38) -> -859.42408 | P38: =AVERAGE(J38:O38) -> -1002.6614 | Q38: =AVERAGE(K38:P38) -> -989.49389 | ... V38: =AVERAGE(P38:U38) -> -976.3099
B39: Training | C39: Enter Manually | D39: =SUMIFS('Bank Statement Export'!$I:$I,'Bank Statement Export'!$C:$C,'Forecast 1'!$B39,'Bank Statement Export'!$A:$A,'Forecast 1'!D$7) -> 0 | E39: =SUMIFS('Bank Statement Export'!$I:$I,'Bank Statement Export'!$C:$C,'Forecast 1'!$B39,'Bank Statement Export'!$A:$A,'Forecast 1'!E$7) -> 0 | F39: =SUMIFS('Bank Statement Export'!$I:$I,'Bank Statement Export'!$C:$C,'Forecast 1'!$B39,'Bank Statement Export'!$A:$A,'Forecast 1'!F$7) -> 0 | G39: =SUMIFS('Bank Statement Export'!$I:$I,'Bank Statement Export'!$C:$C,'Forecast 1'!$B39,'Bank Statement Export'!$A:$A,'Forecast 1'!G$7) -> 0 | H39: =SUMIFS('Bank Statement Export'!$I:$I,'Bank Statement Export'!$C:$C,'Forecast 1'!$B39,'Bank Statement Export'!$A:$A,'Forecast 1'!H$7) -> 0 | I39: =SUMIFS('Bank Statement Export'!$I:$I,'Bank Statement Export'!$C:$C,'Forecast 1'!$B39,'Bank Statement Export'!$A:$A,'Forecast 1'!I$7) -> 0 | J39: =SUMIFS('Bank Statement Export'!$I:$I,'Bank Statement Export'!$C:$C,'Forecast 1'!$B39,'Bank Statement Export'!$A:$A,'Forecast 1'!J$7) -> 0 | K39: =SUMIFS('Bank Statement Export'!$I:$I,'Bank Statement Export'!$C:$C,'Forecast 1'!$B39,'Bank Statement Export'!$A:$A,'Forecast 1'!K$7) -> 0 | ... V39: =SUMIFS('Bank Statement Export'!$I:$I,'Bank Statement Export'!$C:$C,'Forecast 1'!$B39,'Bank Statement Export'!$A:$A,'Forecast 1'!V$7) -> 0
B40: Travel & Entertainment | C40: Enter Manually | D40: =SUMIFS('Bank Statement Export'!$I:$I,'Bank Statement Export'!$C:$C,'Forecast 1'!$B40,'Bank Statement Export'!$A:$A,'Forecast 1'!D$7) -> 0 | E40: =SUMIFS('Bank Statement Export'!$I:$I,'Bank Statement Export'!$C:$C,'Forecast 1'!$B40,'Bank Statement Export'!$A:$A,'Forecast 1'!E$7) -> 0 | F40: =SUMIFS('Bank Statement Export'!$I:$I,'Bank Statement Export'!$C:$C,'Forecast 1'!$B40,'Bank Statement Export'!$A:$A,'Forecast 1'!F$7) -> 0 | G40: =SUMIFS('Bank Statement Export'!$I:$I,'Bank Statement Export'!$C:$C,'Forecast 1'!$B40,'Bank Statement Export'!$A:$A,'Forecast 1'!G$7) -> 0 | H40: =SUMIFS('Bank Statement Export'!$I:$I,'Bank Statement Export'!$C:$C,'Forecast 1'!$B40,'Bank Statement Export'!$A:$A,'Forecast 1'!H$7) -> 0 | I40: =SUMIFS('Bank Statement Export'!$I:$I,'Bank Statement Export'!$C:$C,'Forecast 1'!$B40,'Bank Statement Export'!$A:$A,'Forecast 1'!I$7) -> 0 | J40: =SUMIFS('Bank Statement Export'!$I:$I,'Bank Statement Export'!$C:$C,'Forecast 1'!$B40,'Bank Statement Export'!$A:$A,'Forecast 1'!J$7) -> 0 | K40: =SUMIFS('Bank Statement Export'!$I:$I,'Bank Statement Export'!$C:$C,'Forecast 1'!$B40,'Bank Statement Export'!$A:$A,'Forecast 1'!K$7) -> 0 | ... V40: =SUMIFS('Bank Statement Export'!$I:$I,'Bank Statement Export'!$C:$C,'Forecast 1'!$B40,'Bank Statement Export'!$A:$A,'Forecast 1'!V$7) -> 0
B41: Utilities | C41: Enter Manually | D41: =SUMIFS('Bank Statement Export'!$I:$I,'Bank Statement Export'!$C:$C,'Forecast 1'!$B41,'Bank Statement Export'!$A:$A,'Forecast 1'!D$7) -> 0 | E41: =SUMIFS('Bank Statement Export'!$I:$I,'Bank Statement Export'!$C:$C,'Forecast 1'!$B41,'Bank Statement Export'!$A:$A,'Forecast 1'!E$7) -> 0 | F41: =SUMIFS('Bank Statement Export'!$I:$I,'Bank Statement Export'!$C:$C,'Forecast 1'!$B41,'Bank Statement Export'!$A:$A,'Forecast 1'!F$7) -> 0 | G41: =SUMIFS('Bank Statement Export'!$I:$I,'Bank Statement Export'!$C:$C,'Forecast 1'!$B41,'Bank Statement Export'!$A:$A,'Forecast 1'!G$7) -> 0 | H41: =SUMIFS('Bank Statement Export'!$I:$I,'Bank Statement Export'!$C:$C,'Forecast 1'!$B41,'Bank Statement Export'!$A:$A,'Forecast 1'!H$7) -> 0 | I41: =SUMIFS('Bank Statement Export'!$I:$I,'Bank Statement Export'!$C:$C,'Forecast 1'!$B41,'Bank Statement Export'!$A:$A,'Forecast 1'!I$7) -> 0 | J41: =SUMIFS('Bank Statement Export'!$I:$I,'Bank Statement Export'!$C:$C,'Forecast 1'!$B41,'Bank Statement Export'!$A:$A,'Forecast 1'!J$7) -> 0 | K41: =SUMIFS('Bank Statement Export'!$I:$I,'Bank Statement Export'!$C:$C,'Forecast 1'!$B41,'Bank Statement Export'!$A:$A,'Forecast 1'!K$7) -> 0 | ... V41: =SUMIFS('Bank Statement Export'!$I:$I,'Bank Statement Export'!$C:$C,'Forecast 1'!$B41,'Bank Statement Export'!$A:$A,'Forecast 1'!V$7) -> 0
B42: Vehicles | C42: $7k each Month | D42: =SUMIFS('Bank Statement Export'!$I:$I,'Bank Statement Export'!$C:$C,'Forecast 1'!$B42,'Bank Statement Export'!$A:$A,'Forecast 1'!D$7) -> 0 | E42: =SUMIFS('Bank Statement Export'!$I:$I,'Bank Statement Export'!$C:$C,'Forecast 1'!$B42,'Bank Statement Export'!$A:$A,'Forecast 1'!E$7) -> -7660 | F42: =SUMIFS('Bank Statement Export'!$I:$I,'Bank Statement Export'!$C:$C,'Forecast 1'!$B42,'Bank Statement Export'!$A:$A,'Forecast 1'!F$7) -> 0 | G42: =SUMIFS('Bank Statement Export'!$I:$I,'Bank Statement Export'!$C:$C,'Forecast 1'!$B42,'Bank Statement Export'!$A:$A,'Forecast 1'!G$7) -> 0 | H42: =SUMIFS('Bank Statement Export'!$I:$I,'Bank Statement Export'!$C:$C,'Forecast 1'!$B42,'Bank Statement Export'!$A:$A,'Forecast 1'!H$7) -> 0 | I42: =SUMIFS('Bank Statement Export'!$I:$I,'Bank Statement Export'!$C:$C,'Forecast 1'!$B42,'Bank Statement Export'!$A:$A,'Forecast 1'!I$7) -> -5840 | J42: 0 | K42: =SUMIFS('Bank Statement Export'!$I:$I,'Bank Statement Export'!$C:$C,'Forecast 1'!$B42,'Bank Statement Export'!$A:$A,'Forecast 1'!K$7) -> 0 | L42: =SUMIFS('Bank Statement Export'!$I:$I,'Bank Statement Export'!$C:$C,'Forecast 1'!$B42,'Bank Statement Export'!$A:$A,'Forecast 1'!L$7) -> 0 | M42: =SUMIFS('Bank Statement Export'!$I:$I,'Bank Statement Export'!$C:$C,'Forecast 1'!$B42,'Bank Statement Export'!$A:$A,'Forecast 1'!M$7) -> 0 | N42: -7000 | O42: =SUMIFS('Bank Statement Export'!$I:$I,'Bank Statement Export'!$C:$C,'Forecast 1'!$B42,'Bank Statement Export'!$A:$A,'Forecast 1'!O$7) -> 0 | P42: =SUMIFS('Bank Statement Export'!$I:$I,'Bank Statement Export'!$C:$C,'Forecast 1'!$B42,'Bank Statement Export'!$A:$A,'Forecast 1'!P$7) -> 0 | Q42: =SUMIFS('Bank Statement Export'!$I:$I,'Bank Statement Export'!$C:$C,'Forecast 1'!$B42,'Bank Statement Export'!$A:$A,'Forecast 1'!Q$7) -> 0 | R42: -7000 | S42: =SUMIFS('Bank Statement Export'!$I:$I,'Bank Statement Export'!$C:$C,'Forecast 1'!$B42,'Bank Statement Export'!$A:$A,'Forecast 1'!S$7) -> 0 | T42: =SUMIFS('Bank Statement Export'!$I:$I,'Bank Statement Export'!$C:$C,'Forecast 1'!$B42,'Bank Statement Export'!$A:$A,'Forecast 1'!T$7) -> 0 | U42: =SUMIFS('Bank Statement Export'!$I:$I,'Bank Statement Export'!$C:$C,'Forecast 1'!$B42,'Bank Statement Export'!$A:$A,'Forecast 1'!U$7) -> 0 | V42: -7000
B43: Other Operating Outflows | C43: Trailing 6 Week Average | D43: =SUMIFS('Bank Statement Export'!$I:$I,'Bank Statement Export'!$C:$C,'Forecast 1'!$B43,'Bank Statement Export'!$A:$A,'Forecast 1'!D$7) -> -1270 | E43: =SUMIFS('Bank Statement Export'!$I:$I,'Bank Statement Export'!$C:$C,'Forecast 1'!$B43,'Bank Statement Export'!$A:$A,'Forecast 1'!E$7) -> -2570 | F43: =SUMIFS('Bank Statement Export'!$I:$I,'Bank Statement Export'!$C:$C,'Forecast 1'!$B43,'Bank Statement Export'!$A:$A,'Forecast 1'!F$7) -> 0 | G43: =SUMIFS('Bank Statement Export'!$I:$I,'Bank Statement Export'!$C:$C,'Forecast 1'!$B43,'Bank Statement Export'!$A:$A,'Forecast 1'!G$7) -> 0 | H43: =SUMIFS('Bank Statement Export'!$I:$I,'Bank Statement Export'!$C:$C,'Forecast 1'!$B43,'Bank Statement Export'!$A:$A,'Forecast 1'!H$7) -> 0 | I43: =SUMIFS('Bank Statement Export'!$I:$I,'Bank Statement Export'!$C:$C,'Forecast 1'!$B43,'Bank Statement Export'!$A:$A,'Forecast 1'!I$7) -> -1270 | J43: =AVERAGE(D43:I43) -> -851.66667 | K43: =AVERAGE(E43:J43) -> -781.94444 | L43: =AVERAGE(F43:K43) -> -483.93519 | M43: =AVERAGE(G43:L43) -> -564.59105 | N43: =AVERAGE(H43:M43) -> -658.68956 | O43: =AVERAGE(I43:N43) -> -768.47115 | P43: =AVERAGE(J43:O43) -> -684.88301 | Q43: =AVERAGE(K43:P43) -> -657.08573 | ... V43: =AVERAGE(P43:U43) -> -666.46564
D44: =SUMIFS('Bank Statement Export'!$I:$I,'Bank Statement Export'!$C:$C,'Forecast 1'!$B44,'Bank Statement Export'!$A:$A,'Forecast 1'!D$7) -> 0 | E44: =SUMIFS('Bank Statement Export'!$I:$I,'Bank Statement Export'!$C:$C,'Forecast 1'!$B44,'Bank Statement Export'!$A:$A,'Forecast 1'!E$7) -> 0 | F44: =SUMIFS('Bank Statement Export'!$I:$I,'Bank Statement Export'!$C:$C,'Forecast 1'!$B44,'Bank Statement Export'!$A:$A,'Forecast 1'!F$7) -> 0 | G44: =SUMIFS('Bank Statement Export'!$I:$I,'Bank Statement Export'!$C:$C,'Forecast 1'!$B44,'Bank Statement Export'!$A:$A,'Forecast 1'!G$7) -> 0 | H44: =SUMIFS('Bank Statement Export'!$I:$I,'Bank Statement Export'!$C:$C,'Forecast 1'!$B44,'Bank Statement Export'!$A:$A,'Forecast 1'!H$7) -> 0 | I44: =SUMIFS('Bank Statement Export'!$I:$I,'Bank Statement Export'!$C:$C,'Forecast 1'!$B44,'Bank Statement Export'!$A:$A,'Forecast 1'!I$7) -> 0 | J44: =SUMIFS('Bank Statement Export'!$I:$I,'Bank Statement Export'!$C:$C,'Forecast 1'!$B44,'Bank Statement Export'!$A:$A,'Forecast 1'!J$7) -> 0 | K44: =SUMIFS('Bank Statement Export'!$I:$I,'Bank Statement Export'!$C:$C,'Forecast 1'!$B44,'Bank Statement Export'!$A:$A,'Forecast 1'!K$7) -> 0 | ... V44: =SUMIFS('Bank Statement Export'!$I:$I,'Bank Statement Export'!$C:$C,'Forecast 1'!$B44,'Bank Statement Export'!$A:$A,'Forecast 1'!V$7) -> 0
B46: Total Operating Cash Outflows | D46: =SUM(D24:D45) -> -114140 | E46: =SUM(E24:E45) -> -374900 | F46: =SUM(F24:F45) -> -124910 | G46: =SUM(G24:G45) -> -180410 | H46: =SUM(H24:H45) -> -66850 | I46: =SUM(I24:I45) -> -166200 | J46: =SUM(J24:J45) -> -413930 | K46: =SUM(K24:K45) -> -56198.333 | ... V46: =SUM(V24:V45) -> -272464.99
B48: Non-Operating Cash Outflows
B49: Capital Expenditures | C49: Enter Manually | D49: =SUMIFS('Bank Statement Export'!$I:$I,'Bank Statement Export'!$C:$C,'Forecast 1'!$B49,'Bank Statement Export'!$A:$A,'Forecast 1'!D$7) -> 0 | E49: =SUMIFS('Bank Statement Export'!$I:$I,'Bank Statement Export'!$C:$C,'Forecast 1'!$B49,'Bank Statement Export'!$A:$A,'Forecast 1'!E$7) -> 0 | F49: =SUMIFS('Bank Statement Export'!$I:$I,'Bank Statement Export'!$C:$C,'Forecast 1'!$B49,'Bank Statement Export'!$A:$A,'Forecast 1'!F$7) -> 0 | G49: =SUMIFS('Bank Statement Export'!$I:$I,'Bank Statement Export'!$C:$C,'Forecast 1'!$B49,'Bank Statement Export'!$A:$A,'Forecast 1'!G$7) -> 0 | H49: =SUMIFS('Bank Statement Export'!$I:$I,'Bank Statement Export'!$C:$C,'Forecast 1'!$B49,'Bank Statement Export'!$A:$A,'Forecast 1'!H$7) -> 0 | I49: =SUMIFS('Bank Statement Export'!$I:$I,'Bank Statement Export'!$C:$C,'Forecast 1'!$B49,'Bank Statement Export'!$A:$A,'Forecast 1'!I$7) -> 0 | J49: =SUMIFS('Bank Statement Export'!$I:$I,'Bank Statement Export'!$C:$C,'Forecast 1'!$B49,'Bank Statement Export'!$A:$A,'Forecast 1'!J$7) -> 0 | K49: =SUMIFS('Bank Statement Export'!$I:$I,'Bank Statement Export'!$C:$C,'Forecast 1'!$B49,'Bank Statement Export'!$A:$A,'Forecast 1'!K$7) -> 0 | ... V49: =SUMIFS('Bank Statement Export'!$I:$I,'Bank Statement Export'!$C:$C,'Forecast 1'!$B49,'Bank Statement Export'!$A:$A,'Forecast 1'!V$7) -> 0
B50: Debt Proceeds | C50: Enter Manually | D50: =SUMIFS('Bank Statement Export'!$I:$I,'Bank Statement Export'!$C:$C,'Forecast 1'!$B50,'Bank Statement Export'!$A:$A,'Forecast 1'!D$7) -> 0 | E50: =SUMIFS('Bank Statement Export'!$I:$I,'Bank Statement Export'!$C:$C,'Forecast 1'!$B50,'Bank Statement Export'!$A:$A,'Forecast 1'!E$7) -> 0 | F50: =SUMIFS('Bank Statement Export'!$I:$I,'Bank Statement Export'!$C:$C,'Forecast 1'!$B50,'Bank Statement Export'!$A:$A,'Forecast 1'!F$7) -> 0 | G50: =SUMIFS('Bank Statement Export'!$I:$I,'Bank Statement Export'!$C:$C,'Forecast 1'!$B50,'Bank Statement Export'!$A:$A,'Forecast 1'!G$7) -> 0 | H50: =SUMIFS('Bank Statement Export'!$I:$I,'Bank Statement Export'!$C:$C,'Forecast 1'!$B50,'Bank Statement Export'!$A:$A,'Forecast 1'!H$7) -> 0 | I50: =SUMIFS('Bank Statement Export'!$I:$I,'Bank Statement Export'!$C:$C,'Forecast 1'!$B50,'Bank Statement Export'!$A:$A,'Forecast 1'!I$7) -> 0 | J50: =SUMIFS('Bank Statement Export'!$I:$I,'Bank Statement Export'!$C:$C,'Forecast 1'!$B50,'Bank Statement Export'!$A:$A,'Forecast 1'!J$7) -> 0 | K50: =SUMIFS('Bank Statement Export'!$I:$I,'Bank Statement Export'!$C:$C,'Forecast 1'!$B50,'Bank Statement Export'!$A:$A,'Forecast 1'!K$7) -> 0 | ... V50: =SUMIFS('Bank Statement Export'!$I:$I,'Bank Statement Export'!$C:$C,'Forecast 1'!$B50,'Bank Statement Export'!$A:$A,'Forecast 1'!V$7) -> 0
B51: Interest Payments | C51: Enter Manually | D51: =SUMIFS('Bank Statement Export'!$I:$I,'Bank Statement Export'!$C:$C,'Forecast 1'!$B51,'Bank Statement Export'!$A:$A,'Forecast 1'!D$7) -> 0 | E51: =SUMIFS('Bank Statement Export'!$I:$I,'Bank Statement Export'!$C:$C,'Forecast 1'!$B51,'Bank Statement Export'!$A:$A,'Forecast 1'!E$7) -> 0 | F51: =SUMIFS('Bank Statement Export'!$I:$I,'Bank Statement Export'!$C:$C,'Forecast 1'!$B51,'Bank Statement Export'!$A:$A,'Forecast 1'!F$7) -> 0 | G51: =SUMIFS('Bank Statement Export'!$I:$I,'Bank Statement Export'!$C:$C,'Forecast 1'!$B51,'Bank Statement Export'!$A:$A,'Forecast 1'!G$7) -> 0 | H51: =SUMIFS('Bank Statement Export'!$I:$I,'Bank Statement Export'!$C:$C,'Forecast 1'!$B51,'Bank Statement Export'!$A:$A,'Forecast 1'!H$7) -> 0 | I51: =SUMIFS('Bank Statement Export'!$I:$I,'Bank Statement Export'!$C:$C,'Forecast 1'!$B51,'Bank Statement Export'!$A:$A,'Forecast 1'!I$7) -> 0 | J51: =SUMIFS('Bank Statement Export'!$I:$I,'Bank Statement Export'!$C:$C,'Forecast 1'!$B51,'Bank Statement Export'!$A:$A,'Forecast 1'!J$7) -> 0 | K51: =SUMIFS('Bank Statement Export'!$I:$I,'Bank Statement Export'!$C:$C,'Forecast 1'!$B51,'Bank Statement Export'!$A:$A,'Forecast 1'!K$7) -> 0 | ... V51: =SUMIFS('Bank Statement Export'!$I:$I,'Bank Statement Export'!$C:$C,'Forecast 1'!$B51,'Bank Statement Export'!$A:$A,'Forecast 1'!V$7) -> 0
B52: Principal Payments | C52: Enter Manually | D52: =SUMIFS('Bank Statement Export'!$I:$I,'Bank Statement Export'!$C:$C,'Forecast 1'!$B52,'Bank Statement Export'!$A:$A,'Forecast 1'!D$7) -> 0 | E52: =SUMIFS('Bank Statement Export'!$I:$I,'Bank Statement Export'!$C:$C,'Forecast 1'!$B52,'Bank Statement Export'!$A:$A,'Forecast 1'!E$7) -> 0 | F52: =SUMIFS('Bank Statement Export'!$I:$I,'Bank Statement Export'!$C:$C,'Forecast 1'!$B52,'Bank Statement Export'!$A:$A,'Forecast 1'!F$7) -> 0 | G52: =SUMIFS('Bank Statement Export'!$I:$I,'Bank Statement Export'!$C:$C,'Forecast 1'!$B52,'Bank Statement Export'!$A:$A,'Forecast 1'!G$7) -> 0 | H52: =SUMIFS('Bank Statement Export'!$I:$I,'Bank Statement Export'!$C:$C,'Forecast 1'!$B52,'Bank Statement Export'!$A:$A,'Forecast 1'!H$7) -> 0 | I52: =SUMIFS('Bank Statement Export'!$I:$I,'Bank Statement Export'!$C:$C,'Forecast 1'!$B52,'Bank Statement Export'!$A:$A,'Forecast 1'!I$7) -> 0 | J52: =SUMIFS('Bank Statement Export'!$I:$I,'Bank Statement Export'!$C:$C,'Forecast 1'!$B52,'Bank Statement Export'!$A:$A,'Forecast 1'!J$7) -> 0 | K52: =SUMIFS('Bank Statement Export'!$I:$I,'Bank Statement Export'!$C:$C,'Forecast 1'!$B52,'Bank Statement Export'!$A:$A,'Forecast 1'!K$7) -> 0 | ... V52: =SUMIFS('Bank Statement Export'!$I:$I,'Bank Statement Export'!$C:$C,'Forecast 1'!$B52,'Bank Statement Export'!$A:$A,'Forecast 1'!V$7) -> 0
B53: Tax Distributions | C53: Trailing 6 Week Average | D53: =SUMIFS('Bank Statement Export'!$I:$I,'Bank Statement Export'!$C:$C,'Forecast 1'!$B53,'Bank Statement Export'!$A:$A,'Forecast 1'!D$7) -> -21230 | E53: =SUMIFS('Bank Statement Export'!$I:$I,'Bank Statement Export'!$C:$C,'Forecast 1'!$B53,'Bank Statement Export'!$A:$A,'Forecast 1'!E$7) -> -24740 | F53: =SUMIFS('Bank Statement Export'!$I:$I,'Bank Statement Export'!$C:$C,'Forecast 1'!$B53,'Bank Statement Export'!$A:$A,'Forecast 1'!F$7) -> -20220 | G53: =SUMIFS('Bank Statement Export'!$I:$I,'Bank Statement Export'!$C:$C,'Forecast 1'!$B53,'Bank Statement Export'!$A:$A,'Forecast 1'!G$7) -> -14200 | H53: =SUMIFS('Bank Statement Export'!$I:$I,'Bank Statement Export'!$C:$C,'Forecast 1'!$B53,'Bank Statement Export'!$A:$A,'Forecast 1'!H$7) -> -12680 | I53: =SUMIFS('Bank Statement Export'!$I:$I,'Bank Statement Export'!$C:$C,'Forecast 1'!$B53,'Bank Statement Export'!$A:$A,'Forecast 1'!I$7) -> -12340 | J53: =AVERAGE(D53:I53) -> -17568.333 | K53: =AVERAGE(E53:J53) -> -16958.056 | L53: =AVERAGE(F53:K53) -> -15661.065 | M53: =AVERAGE(G53:L53) -> -14901.242 | N53: =AVERAGE(H53:M53) -> -15018.116 | O53: =AVERAGE(I53:N53) -> -15407.802 | P53: =AVERAGE(J53:O53) -> -15919.102 | Q53: =AVERAGE(K53:P53) -> -15644.23 | ... V53: =AVERAGE(P53:U53) -> -15563.802
B54: Equity Distributions | C54: Enter Manually | D54: =SUMIFS('Bank Statement Export'!$I:$I,'Bank Statement Export'!$C:$C,'Forecast 1'!$B54,'Bank Statement Export'!$A:$A,'Forecast 1'!D$7) -> 0 | E54: =SUMIFS('Bank Statement Export'!$I:$I,'Bank Statement Export'!$C:$C,'Forecast 1'!$B54,'Bank Statement Export'!$A:$A,'Forecast 1'!E$7) -> 0 | F54: =SUMIFS('Bank Statement Export'!$I:$I,'Bank Statement Export'!$C:$C,'Forecast 1'!$B54,'Bank Statement Export'!$A:$A,'Forecast 1'!F$7) -> 0 | G54: =SUMIFS('Bank Statement Export'!$I:$I,'Bank Statement Export'!$C:$C,'Forecast 1'!$B54,'Bank Statement Export'!$A:$A,'Forecast 1'!G$7) -> 0 | H54: =SUMIFS('Bank Statement Export'!$I:$I,'Bank Statement Export'!$C:$C,'Forecast 1'!$B54,'Bank Statement Export'!$A:$A,'Forecast 1'!H$7) -> 0 | I54: =SUMIFS('Bank Statement Export'!$I:$I,'Bank Statement Export'!$C:$C,'Forecast 1'!$B54,'Bank Statement Export'!$A:$A,'Forecast 1'!I$7) -> 0 | J54: =SUMIFS('Bank Statement Export'!$I:$I,'Bank Statement Export'!$C:$C,'Forecast 1'!$B54,'Bank Statement Export'!$A:$A,'Forecast 1'!J$7) -> 0 | K54: =SUMIFS('Bank Statement Export'!$I:$I,'Bank Statement Export'!$C:$C,'Forecast 1'!$B54,'Bank Statement Export'!$A:$A,'Forecast 1'!K$7) -> 0 | ... V54: =SUMIFS('Bank Statement Export'!$I:$I,'Bank Statement Export'!$C:$C,'Forecast 1'!$B54,'Bank Statement Export'!$A:$A,'Forecast 1'!V$7) -> 0
B55: Equity Contributions | C55: Enter Manually | D55: =SUMIFS('Bank Statement Export'!$I:$I,'Bank Statement Export'!$C:$C,'Forecast 1'!$B55,'Bank Statement Export'!$A:$A,'Forecast 1'!D$7) -> 0 | E55: =SUMIFS('Bank Statement Export'!$I:$I,'Bank Statement Export'!$C:$C,'Forecast 1'!$B55,'Bank Statement Export'!$A:$A,'Forecast 1'!E$7) -> 0 | F55: =SUMIFS('Bank Statement Export'!$I:$I,'Bank Statement Export'!$C:$C,'Forecast 1'!$B55,'Bank Statement Export'!$A:$A,'Forecast 1'!F$7) -> 0 | G55: =SUMIFS('Bank Statement Export'!$I:$I,'Bank Statement Export'!$C:$C,'Forecast 1'!$B55,'Bank Statement Export'!$A:$A,'Forecast 1'!G$7) -> 0 | H55: =SUMIFS('Bank Statement Export'!$I:$I,'Bank Statement Export'!$C:$C,'Forecast 1'!$B55,'Bank Statement Export'!$A:$A,'Forecast 1'!H$7) -> 0 | I55: =SUMIFS('Bank Statement Export'!$I:$I,'Bank Statement Export'!$C:$C,'Forecast 1'!$B55,'Bank Statement Export'!$A:$A,'Forecast 1'!I$7) -> 0 | J55: =SUMIFS('Bank Statement Export'!$I:$I,'Bank Statement Export'!$C:$C,'Forecast 1'!$B55,'Bank Statement Export'!$A:$A,'Forecast 1'!J$7) -> 0 | K55: =SUMIFS('Bank Statement Export'!$I:$I,'Bank Statement Export'!$C:$C,'Forecast 1'!$B55,'Bank Statement Export'!$A:$A,'Forecast 1'!K$7) -> 0 | ... V55: =SUMIFS('Bank Statement Export'!$I:$I,'Bank Statement Export'!$C:$C,'Forecast 1'!$B55,'Bank Statement Export'!$A:$A,'Forecast 1'!V$7) -> 0
B56: Other Non-operating Outflows | C56: Trailing 6 Week Average | D56: =SUMIFS('Bank Statement Export'!$I:$I,'Bank Statement Export'!$C:$C,'Forecast 1'!$B56,'Bank Statement Export'!$A:$A,'Forecast 1'!D$7) -> 0 | E56: =SUMIFS('Bank Statement Export'!$I:$I,'Bank Statement Export'!$C:$C,'Forecast 1'!$B56,'Bank Statement Export'!$A:$A,'Forecast 1'!E$7) -> -8580 | F56: =SUMIFS('Bank Statement Export'!$I:$I,'Bank Statement Export'!$C:$C,'Forecast 1'!$B56,'Bank Statement Export'!$A:$A,'Forecast 1'!F$7) -> 0 | G56: =SUMIFS('Bank Statement Export'!$I:$I,'Bank Statement Export'!$C:$C,'Forecast 1'!$B56,'Bank Statement Export'!$A:$A,'Forecast 1'!G$7) -> -1140 | H56: =SUMIFS('Bank Statement Export'!$I:$I,'Bank Statement Export'!$C:$C,'Forecast 1'!$B56,'Bank Statement Export'!$A:$A,'Forecast 1'!H$7) -> 0 | I56: =SUMIFS('Bank Statement Export'!$I:$I,'Bank Statement Export'!$C:$C,'Forecast 1'!$B56,'Bank Statement Export'!$A:$A,'Forecast 1'!I$7) -> 0 | J56: =AVERAGE(D56:I56) -> -1620 | K56: =AVERAGE(E56:J56) -> -1890 | L56: =AVERAGE(F56:K56) -> -775 | M56: =AVERAGE(G56:L56) -> -904.16667 | N56: =AVERAGE(H56:M56) -> -864.86111 | O56: =AVERAGE(I56:N56) -> -1009.0046 | P56: =AVERAGE(J56:O56) -> -1177.1721 | Q56: =AVERAGE(K56:P56) -> -1103.3674 | ... V56: =AVERAGE(P56:U56) -> -1054.6767
B58: Total Non-operating Cash Outflows | D58: =SUM(D49:D57) -> -21230 | E58: =SUM(E49:E57) -> -33320 | F58: =SUM(F49:F57) -> -20220 | G58: =SUM(G49:G57) -> -15340 | H58: =SUM(H49:H57) -> -12680 | I58: =SUM(I49:I57) -> -12340 | J58: =SUM(J49:J57) -> -19188.333 | K58: =SUM(K49:K57) -> -18848.056 | ... V58: =SUM(V49:V57) -> -16618.479
B60: Change in Cash | D60: =SUM(D21,D46,D58) -> -135370 | E60: =SUM(E21,E46,E58) -> -36120 | F60: =SUM(F21,F46,F58) -> 65020 | G60: =SUM(G21,G46,G58) -> -195750 | H60: =SUM(H21,H46,H58) -> 281900 | I60: =SUM(I21,I46,I58) -> -110100 | J60: =SUM(J21,J46,J58) -> -103118.33 | K60: =SUM(K21,K46,K58) -> 44953.611 | ... V60: =SUM(V21,V46,V58) -> -289083.47

Sheet Bank Statement Export
A1: WEEK ENDING | B1: UNIQUE ID | C1: CATEGORY | D1: CATEGORY CHECK | E1: TRANSACTION NUMBER | F1: DATE | G1: TRANSACTION | H1: DESCRIPTION | I1: AMOUNT | J1: BALANCE
A2: =F2+7-WEEKDAY(F2) -> 45220 | B2: =CONCATENATE(E2," ",H2) -> 1 WEB AUTHORIZED PMT KRYPTONIX | C2: {=IFERROR(INDEX(Mapping!$B$2:$B$22,MATCH('Bank Statement Export'!B2,Mapping!$A$2:$A$22,0)),INDEX(Table3[Category],MATCH(TRUE,ISNUMBER(SEARCH(Table3[Unique ID Contains],B2)),0)))} -> Dues & Subscriptions | D2: =INDEX('Forecast 1'!$B$9:$B$56,MATCH('Bank Statement Export'!C2,'Forecast 1'!$B$9:$B$56,0)) -> Dues & Subscriptions | E2: 1 | F2: 45215 | G2: DEBIT | H2: WEB AUTHORIZED PMT KRYPTONIX | I2: -83 | J2: 29760
A3: =F3+7-WEEKDAY(F3) -> 45220 | B3: =CONCATENATE(E3," ",H3) -> 2 WEB AUTHORIZED PMT KRYPTONIX | C3: {=IFERROR(INDEX(Mapping!$B$2:$B$22,MATCH('Bank Statement Export'!B3,Mapping!$A$2:$A$22,0)),INDEX(Table3[Category],MATCH(TRUE,ISNUMBER(SEARCH(Table3[Unique ID Contains],B3)),0)))} -> Dues & Subscriptions | D3: =INDEX('Forecast 1'!$B$9:$B$56,MATCH('Bank Statement Export'!C3,'Forecast 1'!$B$9:$B$56,0)) -> Dues & Subscriptions | E3: 2 | F3: 45215 | G3: DEBIT | H3: WEB AUTHORIZED PMT KRYPTONIX | I3: -230 | J3: 29530
A4: =F4+7-WEEKDAY(F4) -> 45220 | B4: =CONCATENATE(E4," ",H4) -> 3 CHECK | C4: {=IFERROR(INDEX(Mapping!$B$2:$B$22,MATCH('Bank Statement Export'!B4,Mapping!$A$2:$A$22,0)),INDEX(Table3[Category],MATCH(TRUE,ISNUMBER(SEARCH(Table3[Unique ID Contains],B4)),0)))} -> Payroll | D4: =INDEX('Forecast 1'!$B$9:$B$56,MATCH('Bank Statement Export'!C4,'Forecast 1'!$B$9:$B$56,0)) -> Payroll | E4: 3 | F4: 45215 | G4: 79613 | H4: CHECK | I4: -2000 | J4: 27530
A5: =F5+7-WEEKDAY(F5) -> 45220 | B5: =CONCATENATE(E5," ",H5) -> 4 CHECK | C5: {=IFERROR(INDEX(Mapping!$B$2:$B$22,MATCH('Bank Statement Export'!B5,Mapping!$A$2:$A$22,0)),INDEX(Table3[Category],MATCH(TRUE,ISNUMBER(SEARCH(Table3[Unique ID Contains],B5)),0)))} -> Payroll | D5: =INDEX('Forecast 1'!$B$9:$B$56,MATCH('Bank Statement Export'!C5,'Forecast 1'!$B$9:$B$56,0)) -> Payroll | E5: 4 | F5: 45215 | G5: 79671 | H5: CHECK | I5: -1270 | J5: 26260
A6: =F6+7-WEEKDAY(F6) -> 45220 | B6: =CONCATENATE(E6," ",H6) -> 5 CHECK | C6: {=IFERROR(INDEX(Mapping!$B$2:$B$22,MATCH('Bank Statement Export'!B6,Mapping!$A$2:$A$22,0)),INDEX(Table3[Category],MATCH(TRUE,ISNUMBER(SEARCH(Table3[Unique ID Contains],B6)),0)))} -> Accounts Payable | D6: =INDEX('Forecast 1'!$B$9:$B$56,MATCH('Bank Statement Export'!C6,'Forecast 1'!$B$9:$B$56,0)) -> Accounts Payable | E6: 5 | F6: 45215 | G6: 79673 | H6: CHECK | I6: -6570 | J6: 19690
A7: =F7+7-WEEKDAY(F7) -> 45220 | B7: =CONCATENATE(E7," ",H7) -> 6 DEPOSIT | C7: {=IFERROR(INDEX(Mapping!$B$2:$B$22,MATCH('Bank Statement Export'!B7,Mapping!$A$2:$A$22,0)),INDEX(Table3[Category],MATCH(TRUE,ISNUMBER(SEARCH(Table3[Unique ID Contains],B7)),0)))} -> Invoice Revenue Receipts | D7: =INDEX('Forecast 1'!$B$9:$B$56,MATCH('Bank Statement Export'!C7,'Forecast 1'!$B$9:$B$56,0)) -> Invoice Revenue Receipts | E7: 6 | F7: 45216 | G7: CREDIT | H7: DEPOSIT | I7: 3270 | J7: 22960
A8: =F8+7-WEEKDAY(F8) -> 45220 | B8: =CONCATENATE(E8," ",H8) -> 7 ELECTRONIC WITHDRAWAL GLOWTECH | C8: {=IFERROR(INDEX(Mapping!$B$2:$B$22,MATCH('Bank Statement Export'!B8,Mapping!$A$2:$A$22,0)),INDEX(Table3[Category],MATCH(TRUE,ISNUMBER(SEARCH(Table3[Unique ID Contains],B8)),0)))} -> Technology | D8: =INDEX('Forecast 1'!$B$9:$B$56,MATCH('Bank Statement Export'!C8,'Forecast 1'!$B$9:$B$56,0)) -> Technology | E8: 7 | F8: 45216 | G8: DEBIT | H8: ELECTRONIC WITHDRAWAL GLOWTECH | I8: -1030 | J8: 21930
A9: =F9+7-WEEKDAY(F9) -> 45220 | B9: =CONCATENATE(E9," ",H9) -> 8 CHECK | C9: {=IFERROR(INDEX(Mapping!$B$2:$B$22,MATCH('Bank Statement Export'!B9,Mapping!$A$2:$A$22,0)),INDEX(Table3[Category],MATCH(TRUE,ISNUMBER(SEARCH(Table3[Unique ID Contains],B9)),0)))} -> Payroll | D9: =INDEX('Forecast 1'!$B$9:$B$56,MATCH('Bank Statement Export'!C9,'Forecast 1'!$B$9:$B$56,0)) -> Payroll | E9: 8 | F9: 45216 | G9: 79685 | H9: CHECK | I9: -1150 | J9: 20780
A10: =F10+7-WEEKDAY(F10) -> 45220 | B10: =CONCATENATE(E10," ",H10) -> 9 CHECK | C10: {=IFERROR(INDEX(Mapping!$B$2:$B$22,MATCH('Bank Statement Export'!B10,Mapping!$A$2:$A$22,0)),INDEX(Table3[Category],MATCH(TRUE,ISNUMBER(SEARCH(Table3[Unique ID Contains],B10)),0)))} -> Payroll | D10: =INDEX('Forecast 1'!$B$9:$B$56,MATCH('Bank Statement Export'!C10,'Forecast 1'!$B$9:$B$56,0)) -> Payroll | E10: 9 | F10: 45216 | G10: 79719 | H10: CHECK | I10: -100 | J10: 20680
A11: =F11+7-WEEKDAY(F11) -> 45220 | B11: =CONCATENATE(E11," ",H11) -> 10 DEPOSIT | C11: {=IFERROR(INDEX(Mapping!$B$2:$B$22,MATCH('Bank Statement Export'!B11,Mapping!$A$2:$A$22,0)),INDEX(Table3[Category],MATCH(TRUE,ISNUMBER(SEARCH(Table3[Unique ID Contains],B11)),0)))} -> Invoice Revenue Receipts | D11: =INDEX('Forecast 1'!$B$9:$B$56,MATCH('Bank Statement Export'!C11,'Forecast 1'!$B$9:$B$56,0)) -> Invoice Revenue Receipts | E11: 10 | F11: 45217 | G11: CREDIT | H11: DEPOSIT | I11: 20000 | J11: 40680
A12: =F12+7-WEEKDAY(F12) -> 45220 | B12: =CONCATENATE(E12," ",H12) -> 11 DEPOSIT | C12: {=IFERROR(INDEX(Mapping!$B$2:$B$22,MATCH('Bank Statement Export'!B12,Mapping!$A$2:$A$22,0)),INDEX(Table3[Category],MATCH(TRUE,ISNUMBER(SEARCH(Table3[Unique ID Contains],B12)),0)))} -> Invoice Revenue Receipts | D12: =INDEX('Forecast 1'!$B$9:$B$56,MATCH('Bank Statement Export'!C12,'Forecast 1'!$B$9:$B$56,0)) -> Invoice Revenue Receipts | E12: 11 | F12: 45217 | G12: CREDIT | H12: DEPOSIT | I12: 12180 | J12: 52860
A13: =F13+7-WEEKDAY(F13) -> 45220 | B13: =CONCATENATE(E13," ",H13) -> 12 DEPOSIT | C13: {=IFERROR(INDEX(Mapping!$B$2:$B$22,MATCH('Bank Statement Export'!B13,Mapping!$A$2:$A$22,0)),INDEX(Table3[Category],MATCH(TRUE,ISNUMBER(SEARCH(Table3[Unique ID Contains],B13)),0)))} -> Invoice Revenue Receipts | D13: =INDEX('Forecast 1'!$B$9:$B$56,MATCH('Bank Statement Export'!C13,'Forecast 1'!$B$9:$B$56,0)) -> Invoice Revenue Receipts | E13: 12 | F13: 45217 | G13: CREDIT | H13: DEPOSIT | I13: 7780 | J13: 60640
A14: =F14+7-WEEKDAY(F14) -> 45220 | B14: =CONCATENATE(E14," ",H14) -> 13 ELECTRONIC WITHDRAWAL STATE DEPT REVENUE | C14: {=IFERROR(INDEX(Mapping!$B$2:$B$22,MATCH('Bank Statement Export'!B14,Mapping!$A$2:$A$22,0)),INDEX(Table3[Category],MATCH(TRUE,ISNUMBER(SEARCH(Table3[Unique ID Contains],B14)),0)))} -> Tax Distributions | D14: =INDEX('Forecast 1'!$B$9:$B$56,MATCH('Bank Statement Export'!C14,'Forecast 1'!$B$9:$B$56,0)) -> Tax Distributions | E14: 13 | F14: 45217 | G14: DEBIT | H14: ELECTRONIC WITHDRAWAL STATE DEPT REVENUE | I14: -3230 | J14: 57410
A15: =F15+7-WEEKDAY(F15) -> 45220 | B15: =CONCATENATE(E15," ",H15) -> 14 ELECTRONIC WITHDRAWAL IRS | C15: {=IFERROR(INDEX(Mapping!$B$2:$B$22,MATCH('Bank Statement Export'!B15,Mapping!$A$2:$A$22,0)),INDEX(Table3[Category],MATCH(TRUE,ISNUMBER(SEARCH(Table3[Unique ID Contains],B15)),0)))} -> Tax Distributions | D15: =INDEX('Forecast 1'!$B$9:$B$56,MATCH('Bank Statement Export'!C15,'Forecast 1'!$B$9:$B$56,0)) -> Tax Distributions | E15: 14 | F15: 45217 | G15: DEBIT | H15: ELECTRONIC WITHDRAWAL IRS | I15: -16370 | J15: 41040
A16: =F16+7-WEEKDAY(F16) -> 45220 | B16: =CONCATENATE(E16," ",H16) -> 15 CHECK | C16: {=IFERROR(INDEX(Mapping!$B$2:$B$22,MATCH('Bank Statement Export'!B16,Mapping!$A$2:$A$22,0)),INDEX(Table3[Category],MATCH(TRUE,ISNUMBER(SEARCH(Table3[Unique ID Contains],B16)),0)))} -> Accounts Payable | D16: =INDEX('Forecast 1'!$B$9:$B$56,MATCH('Bank Statement Export'!C16,'Forecast 1'!$B$9:$B$56,0)) -> Accounts Payable | E16: 15 | F16: 45217 | G16: 79665 | H16: CHECK | I16: -11630 | J16: 29410
A17: =F17+7-WEEKDAY(F17) -> 45220 | B17: =CONCATENATE(E17," ",H17) -> 16 DEPOSIT | C17: {=IFERROR(INDEX(Mapping!$B$2:$B$22,MATCH('Bank Statement Export'!B17,Mapping!$A$2:$A$22,0)),INDEX(Table3[Category],MATCH(TRUE,ISNUMBER(SEARCH(Table3[Unique ID Contains],B17)),0)))} -> Invoice Revenue Receipts | D17: =INDEX('Forecast 1'!$B$9:$B$56,MATCH('Bank Statement Export'!C17,'Forecast 1'!$B$9:$B$56,0)) -> Invoice Revenue Receipts | E17: 16 | F17: 45218 | G17: CREDIT | H17: DEPOSIT | I17: 475690 | J17: 505100
A18: =F18+7-WEEKDAY(F18) -> 45220 | B18: =CONCATENATE(E18," ",H18) -> 17 ELECTRONIC WITHDRAWAL PAYROLL | C18: {=IFERROR(INDEX(Mapping!$B$2:$B$22,MATCH('Bank Statement Export'!B18,Mapping!$A$2:$A$22,0)),INDEX(Table3[Category],MATCH(TRUE,ISNUMBER(SEARCH(Table3[Unique ID Contains],B18)),0)))} -> Payroll | D18: =INDEX('Forecast 1'!$B$9:$B$56,MATCH('Bank Statement Export'!C18,'Forecast 1'!$B$9:$B$56,0)) -> Payroll | E18: 17 | F18: 45218 | G18: DEBIT | H18: ELECTRONIC WITHDRAWAL PAYROLL | I18: -21670 | J18: 483430
A19: =F19+7-WEEKDAY(F19) -> 45220 | B19: =CONCATENATE(E19," ",H19) -> 18 CHECK | C19: {=IFERROR(INDEX(Mapping!$B$2:$B$22,MATCH('Bank Statement Export'!B19,Mapping!$A$2:$A$22,0)),INDEX(Table3[Category],MATCH(TRUE,ISNUMBER(SEARCH(Table3[Unique ID Contains],B19)),0)))} -> Accounts Payable | D19: =INDEX('Forecast 1'!$B$9:$B$56,MATCH('Bank Statement Export'!C19,'Forecast 1'!$B$9:$B$56,0)) -> Accounts Payable | E19: 18 | F19: 45218 | G19: 79764 | H19: CHECK | I19: -94000 | J19: 389430
A20: =F20+7-WEEKDAY(F20) -> 45220 | B20: =CONCATENATE(E20," ",H20) -> 19 DEPOSIT | C20: {=IFERROR(INDEX(Mapping!$B$2:$B$22,MATCH('Bank Statement Export'!B20,Mapping!$A$2:$A$22,0)),INDEX(Table3[Category],MATCH(TRUE,ISNUMBER(SEARCH(Table3[Unique ID Contains],B20)),0)))} -> Invoice Revenue Receipts | D20: =INDEX('Forecast 1'!$B$9:$B$56,MATCH('Bank Statement Export'!C20,'Forecast 1'!$B$9:$B$56,0)) -> Invoice Revenue Receipts | E20: 19 | F20: 45219 | G20: CREDIT | H20: DEPOSIT | I20: 1650 | J20: 391080
A21: =F21+7-WEEKDAY(F21) -> 45220 | B21: =CONCATENATE(E21," ",H21) -> 20 ELECTRONIC WITHDRAWAL FRACTALIX | C21: {=IFERROR(INDEX(Mapping!$B$2:$B$22,MATCH('Bank Statement Export'!B21,Mapping!$A$2:$A$22,0)),INDEX(Table3[Category],MATCH(TRUE,ISNUMBER(SEARCH(Table3[Unique ID Contains],B21)),0)))} -> Lease Payments | D21: =INDEX('Forecast 1'!$B$9:$B$56,MATCH('Bank Statement Export'!C21,'Forecast 1'!$B$9:$B$56,0)) -> Lease Payments | E21: 20 | F21: 45219 | G21: DEBIT | H21: ELECTRONIC WITHDRAWAL FRACTALIX | I21: -1350 | J21: 389730
A22: =F22+7-WEEKDAY(F22) -> 45220 | B22: =CONCATENATE(E22," ",H22) -> 21 CHECK | C22: {=IFERROR(INDEX(Mapping!$B$2:$B$22,MATCH('Bank Statement Export'!B22,Mapping!$A$2:$A$22,0)),INDEX(Table3[Category],MATCH(TRUE,ISNUMBER(SEARCH(Table3[Unique ID Contains],B22)),0)))} -> Payroll | D22: =INDEX('Forecast 1'!$B$9:$B$56,MATCH('Bank Statement Export'!C22,'Forecast 1'!$B$9:$B$56,0)) -> Payroll | E22: 21 | F22: 45219 | G22: 79722 | H22: CHECK | I22: -1110 | J22: 388620
A23: =F23+7-WEEKDAY(F23) -> 45220 | B23: =CONCATENATE(E23," ",H23) -> 22 CHECK | C23: {=IFERROR(INDEX(Mapping!$B$2:$B$22,MATCH('Bank Statement Export'!B23,Mapping!$A$2:$A$22,0)),INDEX(Table3[Category],MATCH(TRUE,ISNUMBER(SEARCH(Table3[Unique ID Contains],B23)),0)))} -> Payroll | D23: =INDEX('Forecast 1'!$B$9:$B$56,MATCH('Bank Statement Export'!C23,'Forecast 1'!$B$9:$B$56,0)) -> Payroll | E23: 22 | F23: 45219 | G23: 79723 | H23: CHECK | I23: -760 | J23: 387860
A24: =F24+7-WEEKDAY(F24) -> 45220 | B24: =CONCATENATE(E24," ",H24) -> 23 CHECK | C24: {=IFERROR(INDEX(Mapping!$B$2:$B$22,MATCH('Bank Statement Export'!B24,Mapping!$A$2:$A$22,0)),INDEX(Table3[Category],MATCH(TRUE,ISNUMBER(SEARCH(Table3[Unique ID Contains],B24)),0)))} -> Payroll | D24: =INDEX('Forecast 1'!$B$9:$B$56,MATCH('Bank Statement Export'!C24,'Forecast 1'!$B$9:$B$56,0)) -> Payroll | E24: 23 | F24: 45219 | G24: 79724 | H24: CHECK | I24: -720 | J24: 387140
A25: =F25+7-WEEKDAY(F25) -> 45220 | B25: =CONCATENATE(E25," ",H25) -> 24 CHECK | C25: {=IFERROR(INDEX(Mapping!$B$2:$B$22,MATCH('Bank Statement Export'!B25,Mapping!$A$2:$A$22,0)),INDEX(Table3[Category],MATCH(TRUE,ISNUMBER(SEARCH(Table3[Unique ID Contains],B25)),0)))} -> Payroll | D25: =INDEX('Forecast 1'!$B$9:$B$56,MATCH('Bank Statement Export'!C25,'Forecast 1'!$B$9:$B$56,0)) -> Payroll | E25: 24 | F25: 45219 | G25: 79726 | H25: CHECK | I25: -1880 | J25: 385260
A26: =F26+7-WEEKDAY(F26) -> 45220 | B26: =CONCATENATE(E26," ",H26) -> 25 CHECK | C26: {=IFERROR(INDEX(Mapping!$B$2:$B$22,MATCH('Bank Statement Export'!B26,Mapping!$A$2:$A$22,0)),INDEX(Table3[Category],MATCH(TRUE,ISNUMBER(SEARCH(Table3[Unique ID Contains],B26)),0)))} -> Payroll | D26: =INDEX('Forecast 1'!$B$9:$B$56,MATCH('Bank Statement Export'!C26,'Forecast 1'!$B$9:$B$56,0)) -> Payroll | E26: 25 | F26: 45219 | G26: 79727 | H26: CHECK | I26: -1130 | J26: 384130
A27: =F27+7-WEEKDAY(F27) -> 45220 | B27: =CONCATENATE(E27," ",H27) -> 26 CHECK | C27: {=IFERROR(INDEX(Mapping!$B$2:$B$22,MATCH('Bank Statement Export'!B27,Mapping!$A$2:$A$22,0)),INDEX(Table3[Category],MATCH(TRUE,ISNUMBER(SEARCH(Table3[Unique ID Contains],B27)),0)))} -> Payroll | D27: =INDEX('Forecast 1'!$B$9:$B$56,MATCH('Bank Statement Export'!C27,'Forecast 1'!$B$9:$B$56,0)) -> Payroll | E27: 26 | F27: 45219 | G27: 79728 | H27: CHECK | I27: -1260 | J27: 382870
A28: =F28+7-WEEKDAY(F28) -> 45220 | B28: =CONCATENATE(E28," ",H28) -> 27 CHECK | C28: {=IFERROR(INDEX(Mapping!$B$2:$B$22,MATCH('Bank Statement Export'!B28,Mapping!$A$2:$A$22,0)),INDEX(Table3[Category],MATCH(TRUE,ISNUMBER(SEARCH(Table3[Unique ID Contains],B28)),0)))} -> Payroll | D28: =INDEX('Forecast 1'!$B$9:$B$56,MATCH('Bank Statement Export'!C28,'Forecast 1'!$B$9:$B$56,0)) -> Payroll | E28: 27 | F28: 45219 | G28: 79729 | H28: CHECK | I28: -1160 | J28: 381710
A29: =F29+7-WEEKDAY(F29) -> 45220 | B29: =CONCATENATE(E29," ",H29) -> 28 CHECK | C29: {=IFERROR(INDEX(Mapping!$B$2:$B$22,MATCH('Bank Statement Export'!B29,Mapping!$A$2:$A$22,0)),INDEX(Table3[Category],MATCH(TRUE,ISNUMBER(SEARCH(Table3[Unique ID Contains],B29)),0)))} -> Payroll | D29: =INDEX('Forecast 1'!$B$9:$B$56,MATCH('Bank Statement Export'!C29,'Forecast 1'!$B$9:$B$56,0)) -> Payroll | E29: 28 | F29: 45219 | G29: 79730 | H29: CHECK | I29: -1280 | J29: 380430
A30: =F30+7-WEEKDAY(F30) -> 45220 | B30: =CONCATENATE(E30," ",H30) -> 29 CHECK | C30: {=IFERROR(INDEX(Mapping!$B$2:$B$22,MATCH('Bank Statement Export'!B30,Mapping!$A$2:$A$22,0)),INDEX(Table3[Category],MATCH(TRUE,ISNUMBER(SEARCH(Table3[Unique ID Contains],B30)),0)))} -> Payroll | D30: =INDEX('Forecast 1'!$B$9:$B$56,MATCH('Bank Statement Export'!C30,'Forecast 1'!$B$9:$B$56,0)) -> Payroll | E30: 29 | F30: 45219 | G30: 79731 | H30: CHECK | I30: -1180 | J30: 379250
A31: =F31+7-WEEKDAY(F31) -> 45220 | B31: =CONCATENATE(E31," ",H31) -> 30 CHECK | C31: {=IFERROR(INDEX(Mapping!$B$2:$B$22,MATCH('Bank Statement Export'!B31,Mapping!$A$2:$A$22,0)),INDEX(Table3[Category],MATCH(TRUE,ISNUMBER(SEARCH(Table3[Unique ID Contains],B31)),0)))} -> Payroll | D31: =INDEX('Forecast 1'!$B$9:$B$56,MATCH('Bank Statement Export'!C31,'Forecast 1'!$B$9:$B$56,0)) -> Payroll | E31: 30 | F31: 45219 | G31: 79732 | H31: CHECK | I31: -1260 | J31: 377990
A32: =F32+7-WEEKDAY(F32) -> 45220 | B32: =CONCATENATE(E32," ",H32) -> 31 CHECK | C32: {=IFERROR(INDEX(Mapping!$B$2:$B$22,MATCH('Bank Statement Export'!B32,Mapping!$A$2:$A$22,0)),INDEX(Table3[Category],MATCH(TRUE,ISNUMBER(SEARCH(Table3[Unique ID Contains],B32)),0)))} -> Payroll | D32: =INDEX('Forecast 1'!$B$9:$B$56,MATCH('Bank Statement Export'!C32,'Forecast 1'!$B$9:$B$56,0)) -> Payroll | E32: 31 | F32: 45219 | G32: 79734 | H32: CHECK | I32: -1310 | J32: 376680
A33: =F33+7-WEEKDAY(F33) -> 45220 | B33: =CONCATENATE(E33," ",H33) -> 32 CHECK | C33: {=IFERROR(INDEX(Mapping!$B$2:$B$22,MATCH('Bank Statement Export'!B33,Mapping!$A$2:$A$22,0)),INDEX(Table3[Category],MATCH(TRUE,ISNUMBER(SEARCH(Table3[Unique ID Contains],B33)),0)))} -> Payroll | D33: =INDEX('Forecast 1'!$B$9:$B$56,MATCH('Bank Statement Export'!C33,'Forecast 1'!$B$9:$B$56,0)) -> Payroll | E33: 32 | F33: 45219 | G33: 79736 | H33: CHECK | I33: -1020 | J33: 375660
... A56: =F56+7-WEEKDAY(F56) -> 45220 | B56: =CONCATENATE(E56," ",H56) -> 55 CHECK | C56: {=IFERROR(INDEX(Mapping!$B$2:$B$22,MATCH('Bank Statement Export'!B56,Mapping!$A$2:$A$22,0)),INDEX(Table3[Category],MATCH(TRUE,ISNUMBER(SEARCH(Table3[Unique ID Contains],B56)),0)))} -> Payroll | D56: =INDEX('Forecast 1'!$B$9:$B$56,MATCH('Bank Statement Export'!C56,'Forecast 1'!$B$9:$B$56,0)) -> Payroll | E56: 55 | F56: 45219 | G56: 79763 | H56: CHECK | I56: -1040 | J56: 345580
A57: =F57+7-WEEKDAY(F57) -> 45227 | B57: =CONCATENATE(E57," ",H57) -> 56 WEB AUTHORIZED PMT KRYPTONIX | C57: {=IFERROR(INDEX(Mapping!$B$2:$B$22,MATCH('Bank Statement Export'!B57,Mapping!$A$2:$A$22,0)),INDEX(Table3[Category],MATCH(TRUE,ISNUMBER(SEARCH(Table3[Unique ID Contains],B57)),0)))} -> Dues & Subscriptions | D57: =INDEX('Forecast 1'!$B$9:$B$56,MATCH('Bank Statement Export'!C57,'Forecast 1'!$B$9:$B$56,0)) -> Dues & Subscriptions | E57: 56 | F57: 45222 | G57: DEBIT | H57: WEB AUTHORIZED PMT KRYPTONIX | I57: -80 | J57: 345500
A58: =F58+7-WEEKDAY(F58) -> 45227 | B58: =CONCATENATE(E58," ",H58) -> 57 WEB AUTHORIZED PMT KRYPTONIX | C58: {=IFERROR(INDEX(Mapping!$B$2:$B$22,MATCH('Bank Statement Export'!B58,Mapping!$A$2:$A$22,0)),INDEX(Table3[Category],MATCH(TRUE,ISNUMBER(SEARCH(Table3[Unique ID Contains],B58)),0)))} -> Dues & Subscriptions | D58: =INDEX('Forecast 1'!$B$9:$B$56,MATCH('Bank Statement Export'!C58,'Forecast 1'!$B$9:$B$56,0)) -> Dues & Subscriptions | E58: 57 | F58: 45222 | G58: DEBIT | H58: WEB AUTHORIZED PMT KRYPTONIX | I58: -230 | J58: 345270
A59: =F59+7-WEEKDAY(F59) -> 45227 | B59: =CONCATENATE(E59," ",H59) -> 58 CHECK | C59: {=IFERROR(INDEX(Mapping!$B$2:$B$22,MATCH('Bank Statement Export'!B59,Mapping!$A$2:$A$22,0)),INDEX(Table3[Category],MATCH(TRUE,ISNUMBER(SEARCH(Table3[Unique ID Contains],B59)),0)))} -> Payroll | D59: =INDEX('Forecast 1'!$B$9:$B$56,MATCH('Bank Statement Export'!C59,'Forecast 1'!$B$9:$B$56,0)) -> Payroll | E59: 58 | F59: 45222 | G59: 79725 | H59: CHECK | I59: -1210 | J59: 344060
A60: =F60+7-WEEKDAY(F60) -> 45227 | B60: =CONCATENATE(E60," ",H60) -> 59 CHECK | C60: {=IFERROR(INDEX(Mapping!$B$2:$B$22,MATCH('Bank Statement Export'!B60,Mapping!$A$2:$A$22,0)),INDEX(Table3[Category],MATCH(TRUE,ISNUMBER(SEARCH(Table3[Unique ID Contains],B60)),0)))} -> Payroll | D60: =INDEX('Forecast 1'!$B$9:$B$56,MATCH('Bank Statement Export'!C60,'Forecast 1'!$B$9:$B$56,0)) -> Payroll | E60: 59 | F60: 45222 | G60: 79733 | H60: CHECK | I60: -1270 | J60: 342790
A61: =F61+7-WEEKDAY(F61) -> 45227 | B61: =CONCATENATE(E61," ",H61) -> 60 CHECK | C61: {=IFERROR(INDEX(Mapping!$B$2:$B$22,MATCH('Bank Statement Export'!B61,Mapping!$A$2:$A$22,0)),INDEX(Table3[Category],MATCH(TRUE,ISNUMBER(SEARCH(Table3[Unique ID Contains],B61)),0)))} -> Payroll | D61: =INDEX('Forecast 1'!$B$9:$B$56,MATCH('Bank Statement Export'!C61,'Forecast 1'!$B$9:$B$56,0)) -> Payroll | E61: 60 | F61: 45222 | G61: 79737 | H61: CHECK | I61: -1340 | J61: 341450
A62: =F62+7-WEEKDAY(F62) -> 45227 | B62: =CONCATENATE(E62," ",H62) -> 61 CHECK | C62: {=IFERROR(INDEX(Mapping!$B$2:$B$22,MATCH('Bank Statement Export'!B62,Mapping!$A$2:$A$22,0)),INDEX(Table3[Category],MATCH(TRUE,ISNUMBER(SEARCH(Table3[Unique ID Contains],B62)),0)))} -> Payroll | D62: =INDEX('Forecast 1'!$B$9:$B$56,MATCH('Bank Statement Export'!C62,'Forecast 1'!$B$9:$B$56,0)) -> Payroll | E62: 61 | F62: 45222 | G62: 79742 | H62: CHECK | I62: -1690 | J62: 339760
A63: =F63+7-WEEKDAY(F63) -> 45227 | B63: =CONCATENATE(E63," ",H63) -> 62 CHECK | C63: {=IFERROR(INDEX(Mapping!$B$2:$B$22,MATCH('Bank Statement Export'!B63,Mapping!$A$2:$A$22,0)),INDEX(Table3[Category],MATCH(TRUE,ISNUMBER(SEARCH(Table3[Unique ID Contains],B63)),0)))} -> Payroll | D63: =INDEX('Forecast 1'!$B$9:$B$56,MATCH('Bank Statement Export'!C63,'Forecast 1'!$B$9:$B$56,0)) -> Payroll | E63: 62 | F63: 45222 | G63: 79746 | H63: CHECK | I63: -150 | J63: 339610
A64: =F64+7-WEEKDAY(F64) -> 45227 | B64: =CONCATENATE(E64," ",H64) -> 63 CHECK | C64: {=IFERROR(INDEX(Mapping!$B$2:$B$22,MATCH('Bank Statement Export'!B64,Mapping!$A$2:$A$22,0)),INDEX(Table3[Category],MATCH(TRUE,ISNUMBER(SEARCH(Table3[Unique ID Contains],B64)),0)))} -> Payroll | D64: =INDEX('Forecast 1'!$B$9:$B$56,MATCH('Bank Statement Export'!C64,'Forecast 1'!$B$9:$B$56,0)) -> Payroll | E64: 63 | F64: 45222 | G64: 79765 | H64: CHECK | I64: -290 | J64: 339320
A65: =F65+7-WEEKDAY(F65) -> 45227 | B65: =CONCATENATE(E65," ",H65) -> 64 ELECTRONIC WITHDRAWAL GLOWTECH | C65: {=IFERROR(INDEX(Mapping!$B$2:$B$22,MATCH('Bank Statement Export'!B65,Mapping!$A$2:$A$22,0)),INDEX(Table3[Category],MATCH(TRUE,ISNUMBER(SEARCH(Table3[Unique ID Contains],B65)),0)))} -> Technology | D65: =INDEX('Forecast 1'!$B$9:$B$56,MATCH('Bank Statement Export'!C65,'Forecast 1'!$B$9:$B$56,0)) -> Technology | E65: 64 | F65: 45223 | G65: DEBIT | H65: ELECTRONIC WITHDRAWAL GLOWTECH | I65: -1110 | J65: 338210
A66: =F66+7-WEEKDAY(F66) -> 45227 | B66: =CONCATENATE(E66," ",H66) -> 65 CHECK | C66: {=IFERROR(INDEX(Mapping!$B$2:$B$22,MATCH('Bank Statement Export'!B66,Mapping!$A$2:$A$22,0)),INDEX(Table3[Category],MATCH(TRUE,ISNUMBER(SEARCH(Table3[Unique ID Contains],B66)),0)))} -> Payroll | D66: =INDEX('Forecast 1'!$B$9:$B$56,MATCH('Bank Statement Export'!C66,'Forecast 1'!$B$9:$B$56,0)) -> Payroll | E66: 65 | F66: 45223 | G66: 79768 | H66: CHECK | I66: -260 | J66: 337950
A67: =F67+7-WEEKDAY(F67) -> 45227 | B67: =CONCATENATE(E67," ",H67) -> 66 ELECTRONIC WITHDRAWAL CRYONIX | C67: {=IFERROR(INDEX(Mapping!$B$2:$B$22,MATCH('Bank Statement Export'!B67,Mapping!$A$2:$A$22,0)),INDEX(Table3[Category],MATCH(TRUE,ISNUMBER(SEARCH(Table3[Unique ID Contains],B67)),0)))} -> Other Operating Outflows | D67: =INDEX('Forecast 1'!$B$9:$B$56,MATCH('Bank Statement Export'!C67,'Forecast 1'!$B$9:$B$56,0)) -> Other Operating Outflows | E67: 66 | F67: 45224 | G67: DEBIT | H67: ELECTRONIC WITHDRAWAL CRYONIX | I67: -1270 | J67: 336680
A68: =F68+7-WEEKDAY(F68) -> 45227 | B68: =CONCATENATE(E68," ",H68) -> 67 ELECTRONIC WITHDRAWAL PAYROLL | C68: {=IFERROR(INDEX(Mapping!$B$2:$B$22,MATCH('Bank Statement Export'!B68,Mapping!$A$2:$A$22,0)),INDEX(Table3[Category],MATCH(TRUE,ISNUMBER(SEARCH(Table3[Unique ID Contains],B68)),0)))} -> Payroll | D68: =INDEX('Forecast 1'!$B$9:$B$56,MATCH('Bank Statement Export'!C68,'Forecast 1'!$B$9:$B$56,0)) -> Payroll | E68: 67 | F68: 45225 | G68: DEBIT | H68: ELECTRONIC WITHDRAWAL PAYROLL | I68: -22720 | J68: 313960
A69: =F69+7-WEEKDAY(F69) -> 45227 | B69: =CONCATENATE(E69," ",H69) -> 68 ELECTRONIC WITHDRAWAL IRS | C69: {=IFERROR(INDEX(Mapping!$B$2:$B$22,MATCH('Bank Statement Export'!B69,Mapping!$A$2:$A$22,0)),INDEX(Table3[Category],MATCH(TRUE,ISNUMBER(SEARCH(Table3[Unique ID Contains],B69)),0)))} -> Tax Distributions | D69: =INDEX('Forecast 1'!$B$9:$B$56,MATCH('Bank Statement Export'!C69,'Forecast 1'!$B$9:$B$56,0)) -> Tax Distributions | E69: 68 | F69: 45225 | G69: DEBIT | H69: ELECTRONIC WITHDRAWAL IRS | I69: -17760 | J69: 296200
A70: =F70+7-WEEKDAY(F70) -> 45227 | B70: =CONCATENATE(E70," ",H70) -> 69 CHECK | C70: {=IFERROR(INDEX(Mapping!$B$2:$B$22,MATCH('Bank Statement Export'!B70,Mapping!$A$2:$A$22,0)),INDEX(Table3[Category],MATCH(TRUE,ISNUMBER(SEARCH(Table3[Unique ID Contains],B70)),0)))} -> Accounts Payable | D70: =INDEX('Forecast 1'!$B$9:$B$56,MATCH('Bank Statement Export'!C70,'Forecast 1'!$B$9:$B$56,0)) -> Accounts Payable | E70: 69 | F70: 45225 | G70: 79805 | H70: CHECK | I70: -3580 | J70: 292620
A71: =F71+7-WEEKDAY(F71) -> 45227 | B71: =CONCATENATE(E71," ",H71) -> 70 ELECTRONIC WITHDRAWAL STATE DEPT REVENUE | C71: {=IFERROR(INDEX(Mapping!$B$2:$B$22,MATCH('Bank Statement Export'!B71,Mapping!$A$2:$A$22,0)),INDEX(Table3[Category],MATCH(TRUE,ISNUMBER(SEARCH(Table3[Unique ID Contains],B71)),0)))} -> Tax Distributions | D71: =INDEX('Forecast 1'!$B$9:$B$56,MATCH('Bank Statement Export'!C71,'Forecast 1'!$B$9:$B$56,0)) -> Tax Distributions | E71: 70 | F71: 45226 | G71: DEBIT | H71: ELECTRONIC WITHDRAWAL STATE DEPT REVENUE | I71: -3470 | J71: 289150
A72: =F72+7-WEEKDAY(F72) -> 45227 | B72: =CONCATENATE(E72," ",H72) -> 71 CHECK | C72: {=IFERROR(INDEX(Mapping!$B$2:$B$22,MATCH('Bank Statement Export'!B72,Mapping!$A$2:$A$22,0)),INDEX(Table3[Category],MATCH(TRUE,ISNUMBER(SEARCH(Table3[Unique ID Contains],B72)),0)))} -> Payroll | D72: =INDEX('Forecast 1'!$B$9:$B$56,MATCH('Bank Statement Export'!C72,'Forecast 1'!$B$9:$B$56,0)) -> Payroll | E72: 71 | F72: 45226 | G72: 79767 | H72: CHECK | I72: -210 | J72: 288940
A73: =F73+7-WEEKDAY(F73) -> 45227 | B73: =CONCATENATE(E73," ",H73) -> 72 CHECK | C73: {=IFERROR(INDEX(Mapping!$B$2:$B$22,MATCH('Bank Statement Export'!B73,Mapping!$A$2:$A$22,0)),INDEX(Table3[Category],MATCH(TRUE,ISNUMBER(SEARCH(Table3[Unique ID Contains],B73)),0)))} -> Accounts Payable | D73: =INDEX('Forecast 1'!$B$9:$B$56,MATCH('Bank Statement Export'!C73,'Forecast 1'!$B$9:$B$56,0)) -> Accounts Payable | E73: 72 | F73: 45226 | G73: 79806 | H73: CHECK | I73: -6420 | J73: 282520
A74: =F74+7-WEEKDAY(F74) -> 45227 | B74: =CONCATENATE(E74," ",H74) -> 73 CHECK | C74: {=IFERROR(INDEX(Mapping!$B$2:$B$22,MATCH('Bank Statement Export'!B74,Mapping!$A$2:$A$22,0)),INDEX(Table3[Category],MATCH(TRUE,ISNUMBER(SEARCH(Table3[Unique ID Contains],B74)),0)))} -> Accounts Payable | D74: =INDEX('Forecast 1'!$B$9:$B$56,MATCH('Bank Statement Export'!C74,'Forecast 1'!$B$9:$B$56,0)) -> Accounts Payable | E74: 73 | F74: 45226 | G74: 79807 | H74: CHECK | I74: -23620 | J74: 258900
A75: =F75+7-WEEKDAY(F75) -> 45227 | B75: =CONCATENATE(E75," ",H75) -> 74 CHECK | C75: {=IFERROR(INDEX(Mapping!$B$2:$B$22,MATCH('Bank Statement Export'!B75,Mapping!$A$2:$A$22,0)),INDEX(Table3[Category],MATCH(TRUE,ISNUMBER(SEARCH(Table3[Unique ID Contains],B75)),0)))} -> Payroll | D75: =INDEX('Forecast 1'!$B$9:$B$56,MATCH('Bank Statement Export'!C75,'Forecast 1'!$B$9:$B$56,0)) -> Payroll | E75: 74 | F75: 45226 | G75: 79810 | H75: CHECK | I75: -1360 | J75: 257540
A76: =F76+7-WEEKDAY(F76) -> 45227 | B76: =CONCATENATE(E76," ",H76) -> 75 CHECK | C76: {=IFERROR(INDEX(Mapping!$B$2:$B$22,MATCH('Bank Statement Export'!B76,Mapping!$A$2:$A$22,0)),INDEX(Table3[Category],MATCH(TRUE,ISNUMBER(SEARCH(Table3[Unique ID Contains],B76)),0)))} -> Payroll | D76: =INDEX('Forecast 1'!$B$9:$B$56,MATCH('Bank Statement Export'!C76,'Forecast 1'!$B$9:$B$56,0)) -> Payroll | E76: 75 | F76: 45226 | G76: 79811 | H76: CHECK | I76: -1300 | J76: 256240
A77: =F77+7-WEEKDAY(F77) -> 45227 | B77: =CONCATENATE(E77," ",H77) -> 76 CHECK | C77: {=IFERROR(INDEX(Mapping!$B$2:$B$22,MATCH('Bank Statement Export'!B77,Mapping!$A$2:$A$22,0)),INDEX(Table3[Category],MATCH(TRUE,ISNUMBER(SEARCH(Table3[Unique ID Contains],B77)),0)))} -> Payroll | D77: =INDEX('Forecast 1'!$B$9:$B$56,MATCH('Bank Statement Export'!C77,'Forecast 1'!$B$9:$B$56,0)) -> Payroll | E77: 76 | F77: 45226 | G77: 79813 | H77: CHECK | I77: -1880 | J77: 254360
A78: =F78+7-WEEKDAY(F78) -> 45227 | B78: =CONCATENATE(E78," ",H78) -> 77 CHECK | C78: {=IFERROR(INDEX(Mapping!$B$2:$B$22,MATCH('Bank Statement Export'!B78,Mapping!$A$2:$A$22,0)),INDEX(Table3[Category],MATCH(TRUE,ISNUMBER(SEARCH(Table3[Unique ID Contains],B78)),0)))} -> Payroll | D78: =INDEX('Forecast 1'!$B$9:$B$56,MATCH('Bank Statement Export'!C78,'Forecast 1'!$B$9:$B$56,0)) -> Payroll | E78: 77 | F78: 45226 | G78: 79814 | H78: CHECK | I78: -1300 | J78: 253060
A79: =F79+7-WEEKDAY(F79) -> 45227 | B79: =CONCATENATE(E79," ",H79) -> 78 CHECK | C79: {=IFERROR(INDEX(Mapping!$B$2:$B$22,MATCH('Bank Statement Export'!B79,Mapping!$A$2:$A$22,0)),INDEX(Table3[Category],MATCH(TRUE,ISNUMBER(SEARCH(Table3[Unique ID Contains],B79)),0)))} -> Payroll | D79: =INDEX('Forecast 1'!$B$9:$B$56,MATCH('Bank Statement Export'!C79,'Forecast 1'!$B$9:$B$56,0)) -> Payroll | E79: 78 | F79: 45226 | G79: 79816 | H79: CHECK | I79: -1300 | J79: 251760
A80: =F80+7-WEEKDAY(F80) -> 45227 | B80: =CONCATENATE(E80," ",H80) -> 79 CHECK | C80: {=IFERROR(INDEX(Mapping!$B$2:$B$22,MATCH('Bank Statement Export'!B80,Mapping!$A$2:$A$22,0)),INDEX(Table3[Category],MATCH(TRUE,ISNUMBER(SEARCH(Table3[Unique ID Contains],B80)),0)))} -> Payroll | D80: =INDEX('Forecast 1'!$B$9:$B$56,MATCH('Bank Statement Export'!C80,'Forecast 1'!$B$9:$B$56,0)) -> Payroll | E80: 79 | F80: 45226 | G80: 79817 | H80: CHECK | I80: -1320 | J80: 250440
A81: =F81+7-WEEKDAY(F81) -> 45227 | B81: =CONCATENATE(E81," ",H81) -> 80 CHECK | C81: {=IFERROR(INDEX(Mapping!$B$2:$B$22,MATCH('Bank Statement Export'!B81,Mapping!$A$2:$A$22,0)),INDEX(Table3[Category],MATCH(TRUE,ISNUMBER(SEARCH(Table3[Unique ID Contains],B81)),0)))} -> Payroll | D81: =INDEX('Forecast 1'!$B$9:$B$56,MATCH('Bank Statement Export'!C81,'Forecast 1'!$B$9:$B$56,0)) -> Payroll | E81: 80 | F81: 45226 | G81: 79818 | H81: CHECK | I81: -1080 | J81: 249360
A82: =F82+7-WEEKDAY(F82) -> 45227 | B82: =CONCATENATE(E82," ",H82) -> 81 CHECK | C82: {=IFERROR(INDEX(Mapping!$B$2:$B$22,MATCH('Bank Statement Export'!B82,Mapping!$A$2:$A$22,0)),INDEX(Table3[Category],MATCH(TRUE,ISNUMBER(SEARCH(Table3[Unique ID Contains],B82)),0)))} -> Payroll | D82: =INDEX('Forecast 1'!$B$9:$B$56,MATCH('Bank Statement Export'!C82,'Forecast 1'!$B$9:$B$56,0)) -> Payroll | E82: 81 | F82: 45226 | G82: 79819 | H82: CHECK | I82: -1390 | J82: 247970
A83: =F83+7-WEEKDAY(F83) -> 45227 | B83: =CONCATENATE(E83," ",H83) -> 82 CHECK | C83: {=IFERROR(INDEX(Mapping!$B$2:$B$22,MATCH('Bank Statement Export'!B83,Mapping!$A$2:$A$22,0)),INDEX(Table3[Category],MATCH(TRUE,ISNUMBER(SEARCH(Table3[Unique ID Contains],B83)),0)))} -> Payroll | D83: =INDEX('Forecast 1'!$B$9:$B$56,MATCH('Bank Statement Export'!C83,'Forecast 1'!$B$9:$B$56,0)) -> Payroll | E83: 82 | F83: 45226 | G83: 79822 | H83: CHECK | I83: -1340 | J83: 246630
... A110: =F110+7-WEEKDAY(F110) -> 45227 | B110: =CONCATENATE(E110," ",H110) -> 109 CHECK | C110: {=IFERROR(INDEX(Mapping!$B$2:$B$22,MATCH('Bank Statement Export'!B110,Mapping!$A$2:$A$22,0)),INDEX(Table3[Category],MATCH(TRUE,ISNUMBER(SEARCH(Table3[Unique ID Contains],B110)),0)))} -> Payroll | D110: =INDEX('Forecast 1'!$B$9:$B$56,MATCH('Bank Statement Export'!C110,'Forecast 1'!$B$9:$B$56,0)) -> Payroll | E110: 109 | F110: 45226 | G110: 79858 | H110: CHECK | I110: -1200 | J110: 210210
A111: =F111+7-WEEKDAY(F111) -> 45234 | B111: =CONCATENATE(E111," ",H111) -> 110 WEB AUTHORIZED PMT KRYPTONIX | C111: {=IFERROR(INDEX(Mapping!$B$2:$B$22,MATCH('Bank Statement Export'!B111,Mapping!$A$2:$A$22,0)),INDEX(Table3[Category],MATCH(TRUE,ISNUMBER(SEARCH(Table3[Unique ID Contains],B111)),0)))} -> Dues & Subscriptions | D111: =INDEX('Forecast 1'!$B$9:$B$56,MATCH('Bank Statement Export'!C111,'Forecast 1'!$B$9:$B$56,0)) -> Dues & Subscriptions | E111: 110 | F111: 45229 | G111: DEBIT | H111: WEB AUTHORIZED PMT KRYPTONIX | I111: -80 | J111: 210130
A112: =F112+7-WEEKDAY(F112) -> 45234 | B112: =CONCATENATE(E112," ",H112) -> 111 WEB AUTHORIZED PMT KRYPTONIX | C112: {=IFERROR(INDEX(Mapping!$B$2:$B$22,MATCH('Bank Statement Export'!B112,Mapping!$A$2:$A$22,0)),INDEX(Table3[Category],MATCH(TRUE,ISNUMBER(SEARCH(Table3[Unique ID Contains],B112)),0)))} -> Dues & Subscriptions | D112: =INDEX('Forecast 1'!$B$9:$B$56,MATCH('Bank Statement Export'!C112,'Forecast 1'!$B$9:$B$56,0)) -> Dues & Subscriptions | E112: 111 | F112: 45229 | G112: DEBIT | H112: WEB AUTHORIZED PMT KRYPTONIX | I112: -230 | J112: 209900
A113: =F113+7-WEEKDAY(F113) -> 45234 | B113: =CONCATENATE(E113," ",H113) -> 112 ELECTRONIC WITHDRAWAL FRACTALIX | C113: {=IFERROR(INDEX(Mapping!$B$2:$B$22,MATCH('Bank Statement Export'!B113,Mapping!$A$2:$A$22,0)),INDEX(Table3[Category],MATCH(TRUE,ISNUMBER(SEARCH(Table3[Unique ID Contains],B113)),0)))} -> Lease Payments | D113: =INDEX('Forecast 1'!$B$9:$B$56,MATCH('Bank Statement Export'!C113,'Forecast 1'!$B$9:$B$56,0)) -> Lease Payments | E113: 112 | F113: 45229 | G113: DEBIT | H113: ELECTRONIC WITHDRAWAL FRACTALIX | I113: -1350 | J113: 208550
A114: =F114+7-WEEKDAY(F114) -> 45234 | B114: =CONCATENATE(E114," ",H114) -> 113 CHECK | C114: {=IFERROR(INDEX(Mapping!$B$2:$B$22,MATCH('Bank Statement Export'!B114,Mapping!$A$2:$A$22,0)),INDEX(Table3[Category],MATCH(TRUE,ISNUMBER(SEARCH(Table3[Unique ID Contains],B114)),0)))} -> Payroll | D114: =INDEX('Forecast 1'!$B$9:$B$56,MATCH('Bank Statement Export'!C114,'Forecast 1'!$B$9:$B$56,0)) -> Payroll | E114: 113 | F114: 45229 | G114: 79735 | H114: CHECK | I114: -1130 | J114: 207420
A115: =F115+7-WEEKDAY(F115) -> 45234 | B115: =CONCATENATE(E115," ",H115) -> 114 CHECK | C115: {=IFERROR(INDEX(Mapping!$B$2:$B$22,MATCH('Bank Statement Export'!B115,Mapping!$A$2:$A$22,0)),INDEX(Table3[Category],MATCH(TRUE,ISNUMBER(SEARCH(Table3[Unique ID Contains],B115)),0)))} -> Payroll | D115: =INDEX('Forecast 1'!$B$9:$B$56,MATCH('Bank Statement Export'!C115,'Forecast 1'!$B$9:$B$56,0)) -> Payroll | E115: 114 | F115: 45229 | G115: 79808 | H115: CHECK | I115: -100 | J115: 207320
A116: =F116+7-WEEKDAY(F116) -> 45234 | B116: =CONCATENATE(E116," ",H116) -> 115 CHECK | C116: {=IFERROR(INDEX(Mapping!$B$2:$B$22,MATCH('Bank Statement Export'!B116,Mapping!$A$2:$A$22,0)),INDEX(Table3[Category],MATCH(TRUE,ISNUMBER(SEARCH(Table3[Unique ID Contains],B116)),0)))} -> Payroll | D116: =INDEX('Forecast 1'!$B$9:$B$56,MATCH('Bank Statement Export'!C116,'Forecast 1'!$B$9:$B$56,0)) -> Payroll | E116: 115 | F116: 45229 | G116: 79812 | H116: CHECK | I116: -1210 | J116: 206110
A117: =F117+7-WEEKDAY(F117) -> 45234 | B117: =CONCATENATE(E117," ",H117) -> 116 CHECK | C117: {=IFERROR(INDEX(Mapping!$B$2:$B$22,MATCH('Bank Statement Export'!B117,Mapping!$A$2:$A$22,0)),INDEX(Table3[Category],MATCH(TRUE,ISNUMBER(SEARCH(Table3[Unique ID Contains],B117)),0)))} -> Payroll | D117: =INDEX('Forecast 1'!$B$9:$B$56,MATCH('Bank Statement Export'!C117,'Forecast 1'!$B$9:$B$56,0)) -> Payroll | E117: 116 | F117: 45229 | G117: 79820 | H117: CHECK | I117: -1190 | J117: 204920
A118: =F118+7-WEEKDAY(F118) -> 45234 | B118: =CONCATENATE(E118," ",H118) -> 117 CHECK | C118: {=IFERROR(INDEX(Mapping!$B$2:$B$22,MATCH('Bank Statement Export'!B118,Mapping!$A$2:$A$22,0)),INDEX(Table3[Category],MATCH(TRUE,ISNUMBER(SEARCH(Table3[Unique ID Contains],B118)),0)))} -> Payroll | D118: =INDEX('Forecast 1'!$B$9:$B$56,MATCH('Bank Statement Export'!C118,'Forecast 1'!$B$9:$B$56,0)) -> Payroll | E118: 117 | F118: 45229 | G118: 79827 | H118: CHECK | I118: -1770 | J118: 203150
A119: =F119+7-WEEKDAY(F119) -> 45234 | B119: =CONCATENATE(E119," ",H119) -> 118 CHECK | C119: {=IFERROR(INDEX(Mapping!$B$2:$B$22,MATCH('Bank Statement Export'!B119,Mapping!$A$2:$A$22,0)),INDEX(Table3[Category],MATCH(TRUE,ISNUMBER(SEARCH(Table3[Unique ID Contains],B119)),0)))} -> Payroll | D119: =INDEX('Forecast 1'!$B$9:$B$56,MATCH('Bank Statement Export'!C119,'Forecast 1'!$B$9:$B$56,0)) -> Payroll | E119: 118 | F119: 45229 | G119: 79846 | H119: CHECK | I119: -990 | J119: 202160
A120: =F120+7-WEEKDAY(F120) -> 45234 | B120: =CONCATENATE(E120," ",H120) -> 119 ELECTRONIC WITHDRAWAL HYPERTECH | C120: {=IFERROR(INDEX(Mapping!$B$2:$B$22,MATCH('Bank Statement Export'!B120,Mapping!$A$2:$A$22,0)),INDEX(Table3[Category],MATCH(TRUE,ISNUMBER(SEARCH(Table3[Unique ID Contains],B120)),0)))} -> Marketing | D120: =INDEX('Forecast 1'!$B$9:$B$56,MATCH('Bank Statement Export'!C120,'Forecast 1'!$B$9:$B$56,0)) -> Marketing | E120: 119 | F120: 45230 | G120: DEBIT | H120: ELECTRONIC WITHDRAWAL HYPERTECH | I120: -1510 | J120: 200650
A121: =F121+7-WEEKDAY(F121) -> 45234 | B121: =CONCATENATE(E121," ",H121) -> 120 ELECTRONIC WITHDRAWAL IRS | C121: {=IFERROR(INDEX(Mapping!$B$2:$B$22,MATCH('Bank Statement Export'!B121,Mapping!$A$2:$A$22,0)),INDEX(Table3[Category],MATCH(TRUE,ISNUMBER(SEARCH(Table3[Unique ID Contains],B121)),0)))} -> Tax Distributions | D121: =INDEX('Forecast 1'!$B$9:$B$56,MATCH('Bank Statement Export'!C121,'Forecast 1'!$B$9:$B$56,0)) -> Tax Distributions | E121: 120 | F121: 45230 | G121: DEBIT | H121: ELECTRONIC WITHDRAWAL IRS | I121: -1140 | J121: 199510
A122: =F122+7-WEEKDAY(F122) -> 45234 | B122: =CONCATENATE(E122," ",H122) -> 121 CHECK | C122: {=IFERROR(INDEX(Mapping!$B$2:$B$22,MATCH('Bank Statement Export'!B122,Mapping!$A$2:$A$22,0)),INDEX(Table3[Category],MATCH(TRUE,ISNUMBER(SEARCH(Table3[Unique ID Contains],B122)),0)))} -> Payroll | D122: =INDEX('Forecast 1'!$B$9:$B$56,MATCH('Bank Statement Export'!C122,'Forecast 1'!$B$9:$B$56,0)) -> Payroll | E122: 121 | F122: 45230 | G122: 79721 | H122: CHECK | I122: -600 | J122: 198910
A123: =F123+7-WEEKDAY(F123) -> 45234 | B123: =CONCATENATE(E123," ",H123) -> 122 ELECTRONIC DEPOSIT ZONIX | C123: {=IFERROR(INDEX(Mapping!$B$2:$B$22,MATCH('Bank Statement Export'!B123,Mapping!$A$2:$A$22,0)),INDEX(Table3[Category],MATCH(TRUE,ISNUMBER(SEARCH(Table3[Unique ID Contains],B123)),0)))} -> Invoice Revenue Receipts | D123: =INDEX('Forecast 1'!$B$9:$B$56,MATCH('Bank Statement Export'!C123,'Forecast 1'!$B$9:$B$56,0)) -> Invoice Revenue Receipts | E123: 122 | F123: 45231 | G123: CREDIT | H123: ELECTRONIC DEPOSIT ZONIX | I123: 131830 | J123: 330740
A124: =F124+7-WEEKDAY(F124) -> 45234 | B124: =CONCATENATE(E124," ",H124) -> 123 ELECTRONIC WITHDRAWAL GLOWTECH | C124: {=IFERROR(INDEX(Mapping!$B$2:$B$22,MATCH('Bank Statement Export'!B124,Mapping!$A$2:$A$22,0)),INDEX(Table3[Category],MATCH(TRUE,ISNUMBER(SEARCH(Table3[Unique ID Contains],B124)),0)))} -> Technology | D124: =INDEX('Forecast 1'!$B$9:$B$56,MATCH('Bank Statement Export'!C124,'Forecast 1'!$B$9:$B$56,0)) -> Technology | E124: 123 | F124: 45231 | G124: DEBIT | H124: ELECTRONIC WITHDRAWAL GLOWTECH | I124: -1150 | J124: 329590
A125: =F125+7-WEEKDAY(F125) -> 45234 | B125: =CONCATENATE(E125," ",H125) -> 124 WEB AUTHORIZED PMT LUCENTIX | C125: {=IFERROR(INDEX(Mapping!$B$2:$B$22,MATCH('Bank Statement Export'!B125,Mapping!$A$2:$A$22,0)),INDEX(Table3[Category],MATCH(TRUE,ISNUMBER(SEARCH(Table3[Unique ID Contains],B125)),0)))} -> Vehicles | D125: =INDEX('Forecast 1'!$B$9:$B$56,MATCH('Bank Statement Export'!C125,'Forecast 1'!$B$9:$B$56,0)) -> Vehicles | E125: 124 | F125: 45231 | G125: DEBIT | H125: WEB AUTHORIZED PMT LUCENTIX | I125: -4480 | J125: 325110
A126: =F126+7-WEEKDAY(F126) -> 45234 | B126: =CONCATENATE(E126," ",H126) -> 125 ELECTRONIC WITHDRAWAL IRS | C126: {=IFERROR(INDEX(Mapping!$B$2:$B$22,MATCH('Bank Statement Export'!B126,Mapping!$A$2:$A$22,0)),INDEX(Table3[Category],MATCH(TRUE,ISNUMBER(SEARCH(Table3[Unique ID Contains],B126)),0)))} -> Tax Distributions | D126: =INDEX('Forecast 1'!$B$9:$B$56,MATCH('Bank Statement Export'!C126,'Forecast 1'!$B$9:$B$56,0)) -> Tax Distributions | E126: 125 | F126: 45231 | G126: DEBIT | H126: ELECTRONIC WITHDRAWAL IRS | I126: -19800 | J126: 305310
A127: =F127+7-WEEKDAY(F127) -> 45234 | B127: =CONCATENATE(E127," ",H127) -> 126 ELECTRONIC WITHDRAWAL STATE DMV | C127: {=IFERROR(INDEX(Mapping!$B$2:$B$22,MATCH('Bank Statement Export'!B127,Mapping!$A$2:$A$22,0)),INDEX(Table3[Category],MATCH(TRUE,ISNUMBER(SEARCH(Table3[Unique ID Contains],B127)),0)))} -> Vehicles | D127: =INDEX('Forecast 1'!$B$9:$B$56,MATCH('Bank Statement Export'!C127,'Forecast 1'!$B$9:$B$56,0)) -> Vehicles | E127: 126 | F127: 45231 | G127: DEBIT | H127: ELECTRONIC WITHDRAWAL STATE DMV | I127: -300 | J127: 305010
A128: =F128+7-WEEKDAY(F128) -> 45234 | B128: =CONCATENATE(E128," ",H128) -> 127 ELECTRONIC WITHDRAWAL STATE DMV | C128: {=IFERROR(INDEX(Mapping!$B$2:$B$22,MATCH('Bank Statement Export'!B128,Mapping!$A$2:$A$22,0)),INDEX(Table3[Category],MATCH(TRUE,ISNUMBER(SEARCH(Table3[Unique ID Contains],B128)),0)))} -> Vehicles | D128: =INDEX('Forecast 1'!$B$9:$B$56,MATCH('Bank Statement Export'!C128,'Forecast 1'!$B$9:$B$56,0)) -> Vehicles | E128: 127 | F128: 45231 | G128: DEBIT | H128: ELECTRONIC WITHDRAWAL STATE DMV | I128: -2880 | J128: 302130
A129: =F129+7-WEEKDAY(F129) -> 45234 | B129: =CONCATENATE(E129," ",H129) -> 128 DEPOSIT | C129: {=IFERROR(INDEX(Mapping!$B$2:$B$22,MATCH('Bank Statement Export'!B129,Mapping!$A$2:$A$22,0)),INDEX(Table3[Category],MATCH(TRUE,ISNUMBER(SEARCH(Table3[Unique ID Contains],B129)),0)))} -> Invoice Revenue Receipts | D129: =INDEX('Forecast 1'!$B$9:$B$56,MATCH('Bank Statement Export'!C129,'Forecast 1'!$B$9:$B$56,0)) -> Invoice Revenue Receipts | E129: 128 | F129: 45232 | G129: CREDIT | H129: DEPOSIT | I129: 122750 | J129: 424880
A130: =F130+7-WEEKDAY(F130) -> 45234 | B130: =CONCATENATE(E130," ",H130) -> 129 DEPOSIT | C130: {=IFERROR(INDEX(Mapping!$B$2:$B$22,MATCH('Bank Statement Export'!B130,Mapping!$A$2:$A$22,0)),INDEX(Table3[Category],MATCH(TRUE,ISNUMBER(SEARCH(Table3[Unique ID Contains],B130)),0)))} -> Invoice Revenue Receipts | D130: =INDEX('Forecast 1'!$B$9:$B$56,MATCH('Bank Statement Export'!C130,'Forecast 1'!$B$9:$B$56,0)) -> Invoice Revenue Receipts | E130: 129 | F130: 45232 | G130: CREDIT | H130: DEPOSIT | I130: 71280 | J130: 496160
A131: =F131+7-WEEKDAY(F131) -> 45234 | B131: =CONCATENATE(E131," ",H131) -> 130 ELECTRONIC WITHDRAWAL BLITZIX | C131: {=IFERROR(INDEX(Mapping!$B$2:$B$22,MATCH('Bank Statement Export'!B131,Mapping!$A$2:$A$22,0)),INDEX(Table3[Category],MATCH(TRUE,ISNUMBER(SEARCH(Table3[Unique ID Contains],B131)),0)))} -> Other Operating Outflows | D131: =INDEX('Forecast 1'!$B$9:$B$56,MATCH('Bank Statement Export'!C131,'Forecast 1'!$B$9:$B$56,0)) -> Other Operating Outflows | E131: 130 | F131: 45232 | G131: DEBIT | H131: ELECTRONIC WITHDRAWAL BLITZIX | I131: -1780 | J131: 494380
A132: =F132+7-WEEKDAY(F132) -> 45234 | B132: =CONCATENATE(E132," ",H132) -> 131 ELECTRONIC WITHDRAWAL STATE DEPT REVENUE | C132: {=IFERROR(INDEX(Mapping!$B$2:$B$22,MATCH('Bank Statement Export'!B132,Mapping!$A$2:$A$22,0)),INDEX(Table3[Category],MATCH(TRUE,ISNUMBER(SEARCH(Table3[Unique ID Contains],B132)),0)))} -> Tax Distributions | D132: =INDEX('Forecast 1'!$B$9:$B$56,MATCH('Bank Statement Export'!C132,'Forecast 1'!$B$9:$B$56,0)) -> Tax Distributions | E132: 131 | F132: 45232 | G132: DEBIT | H132: ELECTRONIC WITHDRAWAL STATE DEPT REVENUE | I132: -3800 | J132: 490580
A133: =F133+7-WEEKDAY(F133) -> 45234 | B133: =CONCATENATE(E133," ",H133) -> 132 ELECTRONIC WITHDRAWAL CAPITALONE | C133: {=IFERROR(INDEX(Mapping!$B$2:$B$22,MATCH('Bank Statement Export'!B133,Mapping!$A$2:$A$22,0)),INDEX(Table3[Category],MATCH(TRUE,ISNUMBER(SEARCH(Table3[Unique ID Contains],B133)),0)))} -> Credit Cards | D133: =INDEX('Forecast 1'!$B$9:$B$56,MATCH('Bank Statement Export'!C133,'Forecast 1'!$B$9:$B$56,0)) -> Credit Cards | E133: 132 | F133: 45232 | G133: DEBIT | H133: ELECTRONIC WITHDRAWAL CAPITALONE | I133: -6270 | J133: 484310
A134: =F134+7-WEEKDAY(F134) -> 45234 | B134: =CONCATENATE(E134," ",H134) -> 133 ELECTRONIC WITHDRAWAL PAYROLL | C134: {=IFERROR(INDEX(Mapping!$B$2:$B$22,MATCH('Bank Statement Export'!B134,Mapping!$A$2:$A$22,0)),INDEX(Table3[Category],MATCH(TRUE,ISNUMBER(SEARCH(Table3[Unique ID Contains],B134)),0)))} -> Payroll | D134: =INDEX('Forecast 1'!$B$9:$B$56,MATCH('Bank Statement Export'!C134,'Forecast 1'!$B$9:$B$56,0)) -> Payroll | E134: 133 | F134: 45232 | G134: DEBIT | H134: ELECTRONIC WITHDRAWAL PAYROLL | I134: -12260 | J134: 472050
A135: =F135+7-WEEKDAY(F135) -> 45234 | B135: =CONCATENATE(E135," ",H135) -> 134 ELECTRONIC WITHDRAWAL ETERNIX | C135: {=IFERROR(INDEX(Mapping!$B$2:$B$22,MATCH('Bank Statement Export'!B135,Mapping!$A$2:$A$22,0)),INDEX(Table3[Category],MATCH(TRUE,ISNUMBER(SEARCH(Table3[Unique ID Contains],B135)),0)))} -> Professional Fees | D135: =INDEX('Forecast 1'!$B$9:$B$56,MATCH('Bank Statement Export'!C135,'Forecast 1'!$B$9:$B$56,0)) -> Professional Fees | E135: 134 | F135: 45232 | G135: DEBIT | H135: ELECTRONIC WITHDRAWAL ETERNIX | I135: -5000 | J135: 467050
A136: =F136+7-WEEKDAY(F136) -> 45234 | B136: =CONCATENATE(E136," ",H136) -> 135 CHECK | C136: {=IFERROR(INDEX(Mapping!$B$2:$B$22,MATCH('Bank Statement Export'!B136,Mapping!$A$2:$A$22,0)),INDEX(Table3[Category],MATCH(TRUE,ISNUMBER(SEARCH(Table3[Unique ID Contains],B136)),0)))} -> Payroll | D136: =INDEX('Forecast 1'!$B$9:$B$56,MATCH('Bank Statement Export'!C136,'Forecast 1'!$B$9:$B$56,0)) -> Payroll | E136: 135 | F136: 45232 | G136: 79770 | H136: CHECK | I136: -190 | J136: 466860
A137: =F137+7-WEEKDAY(F137) -> 45234 | B137: =CONCATENATE(E137," ",H137) -> 136 CHECK | C137: {=IFERROR(INDEX(Mapping!$B$2:$B$22,MATCH('Bank Statement Export'!B137,Mapping!$A$2:$A$22,0)),INDEX(Table3[Category],MATCH(TRUE,ISNUMBER(SEARCH(Table3[Unique ID Contains],B137)),0)))} -> Accounts Payable | D137: =INDEX('Forecast 1'!$B$9:$B$56,MATCH('Bank Statement Export'!C137,'Forecast 1'!$B$9:$B$56,0)) -> Accounts Payable | E137: 136 | F137: 45232 | G137: 79772 | H137: CHECK | I137: -3060 | J137: 463800
A138: =F138+7-WEEKDAY(F138) -> 45234 | B138: =CONCATENATE(E138," ",H138) -> 137 CHECK | C138: {=IFERROR(INDEX(Mapping!$B$2:$B$22,MATCH('Bank Statement Export'!B138,Mapping!$A$2:$A$22,0)),INDEX(Table3[Category],MATCH(TRUE,ISNUMBER(SEARCH(Table3[Unique ID Contains],B138)),0)))} -> Payroll | D138: =INDEX('Forecast 1'!$B$9:$B$56,MATCH('Bank Statement Export'!C138,'Forecast 1'!$B$9:$B$56,0)) -> Payroll | E138: 137 | F138: 45232 | G138: 79780 | H138: CHECK | I138: -1730 | J138: 462070
A139: =F139+7-WEEKDAY(F139) -> 45234 | B139: =CONCATENATE(E139," ",H139) -> 138 CHECK | C139: {=IFERROR(INDEX(Mapping!$B$2:$B$22,MATCH('Bank Statement Export'!B139,Mapping!$A$2:$A$22,0)),INDEX(Table3[Category],MATCH(TRUE,ISNUMBER(SEARCH(Table3[Unique ID Contains],B139)),0)))} -> Payroll | D139: =INDEX('Forecast 1'!$B$9:$B$56,MATCH('Bank Statement Export'!C139,'Forecast 1'!$B$9:$B$56,0)) -> Payroll | E139: 138 | F139: 45232 | G139: 79781 | H139: CHECK | I139: -1580 | J139: 460490
A140: =F140+7-WEEKDAY(F140) -> 45234 | B140: =CONCATENATE(E140," ",H140) -> 139 CHECK | C140: {=IFERROR(INDEX(Mapping!$B$2:$B$22,MATCH('Bank Statement Export'!B140,Mapping!$A$2:$A$22,0)),INDEX(Table3[Category],MATCH(TRUE,ISNUMBER(SEARCH(Table3[Unique ID Contains],B140)),0)))} -> Payroll | D140: =INDEX('Forecast 1'!$B$9:$B$56,MATCH('Bank Statement Export'!C140,'Forecast 1'!$B$9:$B$56,0)) -> Payroll | E140: 139 | F140: 45232 | G140: 79783 | H140: CHECK | I140: -1580 | J140: 458910
A141: =F141+7-WEEKDAY(F141) -> 45234 | B141: =CONCATENATE(E141," ",H141) -> 140 CHECK | C141: {=IFERROR(INDEX(Mapping!$B$2:$B$22,MATCH('Bank Statement Export'!B141,Mapping!$A$2:$A$22,0)),INDEX(Table3[Category],MATCH(TRUE,ISNUMBER(SEARCH(Table3[Unique ID Contains],B141)),0)))} -> Payroll | D141: =INDEX('Forecast 1'!$B$9:$B$56,MATCH('Bank Statement Export'!C141,'Forecast 1'!$B$9:$B$56,0)) -> Payroll | E141: 140 | F141: 45232 | G141: 79784 | H141: CHECK | I141: -1440 | J141: 457470
A142: =F142+7-WEEKDAY(F142) -> 45234 | B142: =CONCATENATE(E142," ",H142) -> 141 CHECK | C142: {=IFERROR(INDEX(Mapping!$B$2:$B$22,MATCH('Bank Statement Export'!B142,Mapping!$A$2:$A$22,0)),INDEX(Table3[Category],MATCH(TRUE,ISNUMBER(SEARCH(Table3[Unique ID Contains],B142)),0)))} -> Payroll | D142: =INDEX('Forecast 1'!$B$9:$B$56,MATCH('Bank Statement Export'!C142,'Forecast 1'!$B$9:$B$56,0)) -> Payroll | E142: 141 | F142: 45232 | G142: 79785 | H142: CHECK | I142: -1640 | J142: 455830
A143: =F143+7-WEEKDAY(F143) -> 45234 | B143: =CONCATENATE(E143," ",H143) -> 142 CHECK | C143: {=IFERROR(INDEX(Mapping!$B$2:$B$22,MATCH('Bank Statement Export'!B143,Mapping!$A$2:$A$22,0)),INDEX(Table3[Category],MATCH(TRUE,ISNUMBER(SEARCH(Table3[Unique ID Contains],B143)),0)))} -> Payroll | D143: =INDEX('Forecast 1'!$B$9:$B$56,MATCH('Bank Statement Export'!C143,'Forecast 1'!$B$9:$B$56,0)) -> Payroll | E143: 142 | F143: 45232 | G143: 79786 | H143: CHECK | I143: -1610 | J143: 454220
A144: =F144+7-WEEKDAY(F144) -> 45234 | B144: =CONCATENATE(E144," ",H144) -> 143 CHECK | C144: {=IFERROR(INDEX(Mapping!$B$2:$B$22,MATCH('Bank Statement Export'!B144,Mapping!$A$2:$A$22,0)),INDEX(Table3[Category],MATCH(TRUE,ISNUMBER(SEARCH(Table3[Unique ID Contains],B144)),0)))} -> Payroll | D144: =INDEX('Forecast 1'!$B$9:$B$56,MATCH('Bank Statement Export'!C144,'Forecast 1'!$B$9:$B$56,0)) -> Payroll | E144: 143 | F144: 45232 | G144: 79787 | H144: CHECK | I144: -1430 | J144: 452790
A145: =F145+7-WEEKDAY(F145) -> 45234 | B145: =CONCATENATE(E145," ",H145) -> 144 CHECK | C145: {=IFERROR(INDEX(Mapping!$B$2:$B$22,MATCH('Bank Statement Export'!B145,Mapping!$A$2:$A$22,0)),INDEX(Table3[Category],MATCH(TRUE,ISNUMBER(SEARCH(Table3[Unique ID Contains],B145)),0)))} -> Payroll | D145: =INDEX('Forecast 1'!$B$9:$B$56,MATCH('Bank Statement Export'!C145,'Forecast 1'!$B$9:$B$56,0)) -> Payroll | E145: 144 | F145: 45232 | G145: 79788 | H145: CHECK | I145: -1460 | J145: 451330
A146: =F146+7-WEEKDAY(F146) -> 45234 | B146: =CONCATENATE(E146," ",H146) -> 145 CHECK | C146: {=IFERROR(INDEX(Mapping!$B$2:$B$22,MATCH('Bank Statement Export'!B146,Mapping!$A$2:$A$22,0)),INDEX(Table3[Category],MATCH(TRUE,ISNUMBER(SEARCH(Table3[Unique ID Contains],B146)),0)))} -> Payroll | D146: =INDEX('Forecast 1'!$B$9:$B$56,MATCH('Bank Statement Export'!C146,'Forecast 1'!$B$9:$B$56,0)) -> Payroll | E146: 145 | F146: 45232 | G146: 79789 | H146: CHECK | I146: -1660 | J146: 449670
A147: =F147+7-WEEKDAY(F147) -> 45234 | B147: =CONCATENATE(E147," ",H147) -> 146 DEPOSIT | C147: {=IFERROR(INDEX(Mapping!$B$2:$B$22,MATCH('Bank Statement Export'!B147,Mapping!$A$2:$A$22,0)),INDEX(Table3[Category],MATCH(TRUE,ISNUMBER(SEARCH(Table3[Unique ID Contains],B147)),0)))} -> Invoice Revenue Receipts | D147: =INDEX('Forecast 1'!$B$9:$B$56,MATCH('Bank Statement Export'!C147,'Forecast 1'!$B$9:$B$56,0)) -> Invoice Revenue Receipts | E147: 146 | F147: 45233 | G147: CREDIT | H147: DEPOSIT | I147: 46240 | J147: 495910
A148: =F148+7-WEEKDAY(F148) -> 45234 | B148: =CONCATENATE(E148," ",H148) -> 147 ELECTRONIC WITHDRAWAL DYNACORP | C148: {=IFERROR(INDEX(Mapping!$B$2:$B$22,MATCH('Bank Statement Export'!B148,Mapping!$A$2:$A$22,0)),INDEX(Table3[Category],MATCH(TRUE,ISNUMBER(SEARCH(Table3[Unique ID Contains],B148)),0)))} -> Other Operating Outflows | D148: =INDEX('Forecast 1'!$B$9:$B$56,MATCH('Bank Statement Export'!C148,'Forecast 1'!$B$9:$B$56,0)) -> Other Operating Outflows | E148: 147 | F148: 45233 | G148: DEBIT | H148: ELECTRONIC WITHDRAWAL DYNACORP | I148: -790 | J148: 495120
...

Sheet Data
A1: Description Contains | B1: Category
A2: BLITZIX | B2: Other Operating Outflows
A3: CAPITALONE | B3: Credit Cards
A4: CHECK | B4: Payroll
A5: CRYONIX | B5: Other Operating Outflows
A6: DEPOSIT | B6: Invoiced AR + New Revenue
A7: DYNACORP | B7: Other Operating Outflows
A8: ETERNIX | B8: Professional Fees
A9: IRS | B9: Tax Distributions
A10: KRYPTONIX | B10: Dues & Subscriptions
A11: DISCOVER | B11: Credit Cards
A12: FRACTALIX | B12: Lease Payments
... A23: JUNCTIX | B23: Other Non-operating Outflows

Sheet AP Aging 01
B1: ↓ Flows thru Model | E1: ↓ Raw Data from AP Aging Report
A2: WEEK ENDING | B2: Amount | C2: Date | D2: Credit Card? | E2: Vendor | F2: Current | G2: 1 - 30 | H2: 31 - 60 | I2: 61 - 90 | J2: > 90 | K2: TOTAL
A3: =C3+7-WEEKDAY(C3) -> 45325 | B3: 1300 | C3: 45323 | D3: Yes | E3: METRIX | F3: 1300 | G3: 0 | H3: 0 | I3: 0 | J3: 0 | K3: =SUM(F3:J3) -> 1300
A4: =C4+7-WEEKDAY(C4) -> 45297 | B4: 5000 | C4: 45292 | D4: Yes | E4: CAPITALONE | F4: 0 | G4: 0 | H4: 0 | I4: 0 | J4: 0 | K4: =SUM(F4:J4) -> 0
A5: =C5+7-WEEKDAY(C5) -> 45325 | B5: 5000 | C5: 45323 | D5: Yes | E5: CAPITALONE | F5: 0 | G5: 0 | H5: 0 | I5: 0 | J5: 0 | K5: =SUM(F5:J5) -> 0
A6: =C6+7-WEEKDAY(C6) -> 45353 | B6: 5000 | C6: 45352 | D6: Yes | E6: CAPITALONE | F6: 0 | G6: 0 | H6: 0 | I6: 0 | J6: 0 | K6: =SUM(F6:J6) -> 0
A7: =C7+7-WEEKDAY(C7) -> 45325 | B7: 900 | C7: 45323 | D7: Yes | E7: ORACLETECH | F7: 0 | G7: 900 | H7: 0 | I7: 0 | J7: 0 | K7: =SUM(F7:J7) -> 900
A8: =C8+7-WEEKDAY(C8) -> 45283 | B8: 37000 | C8: 45280 | E8: PHOENIXCORP | F8: 0 | G8: 0 | H8: 37000 | I8: 0 | J8: 0 | K8: =SUM(F8:J8) -> 37000
A9: =C9+7-WEEKDAY(C9) -> 45325 | B9: 3100 | C9: 45323 | D9: Yes | E9: QUANTUMIX | F9: 0 | G9: 3100 | H9: 0 | I9: 0 | J9: 0 | K9: =SUM(F9:J9) -> 3100
A10: =C10+7-WEEKDAY(C10) -> 45325 | B10: 11900 | C10: 45323 | D10: Yes | E10: RIFTTECH | F10: 0 | G10: 11900 | H10: 0 | I10: 0 | J10: 0 | K10: =SUM(F10:J10) -> 11900
A11: =C11+7-WEEKDAY(C11) -> 45325 | B11: 1500 | C11: 45323 | D11: Yes | E11: SILVERTECH | F11: 1200 | G11: 1200 | H11: 11600 | I11: 300 | J11: 200 | K11: =SUM(F11:J11) -> 14500
A12: =C12+7-WEEKDAY(C12) -> 45325 | B12: 1700 | C12: 45323 | D12: Yes | E12: TITANIX | F12: 1700 | G12: 0 | H12: 0 | I12: 0 | J12: 0 | K12: =SUM(F12:J12) -> 1700
A13: =C13+7-WEEKDAY(C13) -> 45325 | B13: 23100 | C13: 45323 | D13: Yes | E13: UNICORE | F13: 16900 | G13: 6200 | H13: 0 | I13: 0 | J13: 0 | K13: =SUM(F13:J13) -> 23100
A14: =C14+7-WEEKDAY(C14) -> 45283 | B14: 56200 | C14: 45280 | E14: VORTEXCORP | F14: 0 | G14: 56200 | H14: 0 | I14: 0 | J14: 0 | K14: =SUM(F14:J14) -> 56200
A15: =C15+7-WEEKDAY(C15) -> 45325 | B15: 2000 | C15: 45323 | D15: Yes | E15: WINDTECH | F15: 0 | G15: 2000 | H15: 0 | I15: 0 | J15: 0 | K15: =SUM(F15:J15) -> 2000
A16: =C16+7-WEEKDAY(C16) -> 45325 | B16: 500 | C16: 45323 | D16: Yes | E16: GRAVITONIX | F16: 500 | G16: 0 | H16: 0 | I16: 0 | J16: 0 | K16: =SUM(F16:J16) -> 500
A17: =C17+7-WEEKDAY(C17) -> 45269 | B17: 800 | C17: 45266 | E17: YONICORP | F17: 0 | G17: 800 | H17: 0 | I17: 0 | J17: 0 | K17: =SUM(F17:J17) -> 800
A18: =C18+7-WEEKDAY(C18) -> 45325 | B18: 6500 | C18: 45323 | D18: Yes | E18: ZYMOTECH | F18: 6500 | G18: 0 | H18: 0 | I18: 0 | J18: 0 | K18: =SUM(F18:J18) -> 6500
A19: =C19+7-WEEKDAY(C19) -> 45283 | B19: 30000 | C19: 45280 | E19: ASTRATECH | F19: 0 | G19: 61400 | H19: 40400 | I19: 17000 | J19: 13300 | K19: =SUM(F19:J19) -> 132100
A20: =C20+7-WEEKDAY(C20) -> 45297 | B20: 50000 | C20: 45296 | D20: Yes | E20: ASTRATECH | F20: 0 | G20: 0 | H20: 0 | I20: 0 | J20: 0 | K20: =SUM(F20:J20) -> 0
A21: =C21+7-WEEKDAY(C21) -> 45339 | B21: 50000 | C21: 45337 | E21: ASTRATECH | F21: 0 | G21: 0 | H21: 0 | I21: 0 | J21: 0 | K21: =SUM(F21:J21) -> 0
A22: =C22+7-WEEKDAY(C22) -> 45325 | B22: 2000 | C22: 45323 | D22: Yes | E22: BIOSIX | F22: 2000 | G22: 0 | H22: 0 | I22: 0 | J22: 0 | K22: =SUM(F22:J22) -> 2000
A23: =C23+7-WEEKDAY(C23) -> 45325 | B23: 120000 | C23: 45323 | D23: Yes | E23: CORETECH | F23: 75200 | G23: 156500 | H23: 74200 | I23: 95500 | J23: 15500 | K23: =SUM(F23:J23) -> 416900
A24: =C24+7-WEEKDAY(C24) -> 45353 | B24: 205000 | C24: 45352 | D24: Yes | E24: CORETECH | F24: 0 | G24: 0 | H24: 0 | I24: 0 | J24: 0 | K24: =SUM(F24:J24) -> 0
A25: =C25+7-WEEKDAY(C25) -> 45332 | B25: 300 | C25: 45327 | E25: DIODETECH | F25: 0 | G25: 300 | H25: 0 | I25: 0 | J25: 0 | K25: =SUM(F25:J25) -> 300
A26: =C26+7-WEEKDAY(C26) -> 45332 | B26: 700 | C26: 45327 | E26: ELEMENTIX | F26: 700 | G26: 0 | H26: 0 | I26: 0 | J26: 0 | K26: =SUM(F26:J26) -> 700
A27: =C27+7-WEEKDAY(C27) -> 45332 | B27: 6000 | C27: 45327 | E27: FROSTIX | F27: 0 | G27: 6000 | H27: 0 | I27: 0 | J27: 0 | K27: =SUM(F27:J27) -> 6000
A28: =C28+7-WEEKDAY(C28) -> 45269 | B28: 350000 | C28: 45265 | D28: Yes | E28: DISCOVER | F28: 0 | G28: 355300 | H28: 0 | I28: 0 | J28: 0 | K28: =SUM(F28:J28) -> 355300
A29: =C29+7-WEEKDAY(C29) -> 45332 | B29: 2500 | C29: 45327 | E29: HYDROTECH | F29: 0 | G29: 1700 | H29: 800 | I29: 0 | J29: 0 | K29: =SUM(F29:J29) -> 2500
A30: =C30+7-WEEKDAY(C30) -> 45332 | B30: 11700 | C30: 45327 | E30: IMPULSETECH | F30: 0 | G30: 11300 | H30: 400 | I30: 0 | J30: 0 | K30: =SUM(F30:J30) -> 11700
A31: =C31+7-WEEKDAY(C31) -> 45283 | B31: 300 | C31: 45280 | E31: JOLTIX | F31: 100 | G31: 200 | H31: 0 | I31: 0 | J31: 0 | K31: =SUM(F31:J31) -> 300
A32: =C32+7-WEEKDAY(C32) -> 45332 | B32: 6600 | C32: 45327 | E32: KONTACTIX | F32: 6600 | G32: 0 | H32: 0 | I32: 0 | J32: 0 | K32: =SUM(F32:J32) -> 6600
A33: =C33+7-WEEKDAY(C33) -> 45332 | B33: 3600 | C33: 45327 | E33: LYNXTECH | F33: 0 | G33: 3400 | H33: 200 | I33: 0 | J33: 0 | K33: =SUM(F33:J33) -> 3600
A34: =C34+7-WEEKDAY(C34) -> 45332 | B34: 7500 | C34: 45327 | E34: MATRIXIX | F34: 0 | G34: 7500 | H34: 0 | I34: 0 | J34: 0 | K34: =SUM(F34:J34) -> 7500
A35: =C35+7-WEEKDAY(C35) -> 45283 | B35: 5800 | C35: 45280 | E35: NOMADIX | F35: 0 | G35: 5800 | H35: 0 | I35: 0 | J35: 0 | K35: =SUM(F35:J35) -> 5800
A36: =C36+7-WEEKDAY(C36) -> 45332 | B36: 32000 | C36: 45327 | E36: OXYTECH | F36: 22800 | G36: 23100 | H36: 0 | I36: 0 | J36: 0 | K36: =SUM(F36:J36) -> 45900
A37: =C37+7-WEEKDAY(C37) -> 45332 | B37: 6800 | C37: 45327 | E37: PIONIX | F37: 0 | G37: 6800 | H37: 0 | I37: 0 | J37: 0 | K37: =SUM(F37:J37) -> 6800
A38: =C38+7-WEEKDAY(C38) -> 45332 | B38: 2500 | C38: 45327 | E38: QUORATECH | F38: 0 | G38: 2500 | H38: 0 | I38: 0 | J38: 0 | K38: =SUM(F38:J38) -> 2500
A39: =C39+7-WEEKDAY(C39) -> 45332 | B39: 15700 | C39: 45327 | E39: RAZORIX | F39: 0 | G39: 15700 | H39: 0 | I39: 0 | J39: 0 | K39: =SUM(F39:J39) -> 15700
A40: =C40+7-WEEKDAY(C40) -> 45332 | B40: 30000 | C40: 45327 | E40: STORMTECH | F40: 1000 | G40: 0 | H40: 100 | I40: 0 | J40: 0 | K40: =SUM(F40:J40) -> 1100
... A46: =C46+7-WEEKDAY(C46) -> 45332 | B46: 0 | C46: 45327 | E46: YETITECH | F46: 0 | G46: 0 | H46: 0 | I46: 0 | J46: 0 | K46: =SUM(F46:J46) -> 0

Sheet AR Aging 01
B1: ↓ Flows thru Model | D1: ↓ Raw Data from AR Aging Report
A2: WEEK ENDING | B2: Amount | C2: Date | D2: Customer | E2: Current | F2: 1 - 30 | G2: 31 - 60 | H2: 61 - 90 | I2: > 90 | J2: TOTAL
A3: =C3+7-WEEKDAY(C3) -> 45283 | B3: 65900 | C3: 45280 | D3: AQUATECH | E3: 65900 | F3: 0 | G3: 0 | H3: 0 | I3: 0 | J3: =SUM(E3:I3) -> 65900
A4: =C4+7-WEEKDAY(C4) -> 45311 | B4: 75000 | C4: 45311 | D4: AQUATECH | E4: 0 | F4: 0 | G4: 0 | H4: 0 | I4: 0 | J4: =SUM(E4:I4) -> 0
A5: =C5+7-WEEKDAY(C5) -> 45346 | B5: 100000 | C5: 45342 | D5: AQUATECH | E5: 0 | F5: 0 | G5: 0 | H5: 0 | I5: 0 | J5: =SUM(E5:I5) -> 0
A6: =C6+7-WEEKDAY(C6) -> 45269 | B6: 225000 | C6: 45269 | D6: BLAZECORP | E6: 0 | F6: 240300 | G6: 25000 | H6: 16700 | I6: 0 | J6: =SUM(E6:I6) -> 282000
A7: =C7+7-WEEKDAY(C7) -> 0 | D7: CORELIX | E7: 0 | F7: 0 | G7: 0 | H7: 0 | I7: 7000 | J7: =SUM(E7:I7) -> 7000
A8: =C8+7-WEEKDAY(C8) -> 45297 | B8: 100000 | C8: 45291 | D8: DIAMONTECH | E8: 48900 | F8: 101900 | G8: 1400 | H8: 0 | I8: 0 | J8: =SUM(E8:I8) -> 152200
A9: =C9+7-WEEKDAY(C9) -> 45325 | B9: 48000 | C9: 45321 | D9: DIAMONTECH | E9: 0 | F9: 0 | G9: 0 | H9: 0 | I9: 0 | J9: =SUM(E9:I9) -> 0
A10: =C10+7-WEEKDAY(C10) -> 45290 | B10: 80000 | C10: 45285 | D10: ECHOIX | E10: 0 | F10: 83200 | G10: 68200 | H10: 18000 | I10: 21200 | J10: =SUM(E10:I10) -> 190600
A11: =C11+7-WEEKDAY(C11) -> 45318 | B11: 80000 | C11: 45316 | D11: ECHOIX | E11: 0 | F11: 0 | G11: 0 | H11: 0 | I11: 0 | J11: =SUM(E11:I11) -> 0
A12: =C12+7-WEEKDAY(C12) -> 45283 | B12: 150000 | C12: 45280 | D12: FLARETECH | E12: 150000 | F12: 0 | G12: 0 | H12: 0 | I12: 0 | J12: =SUM(E12:I12) -> 150000
A13: =C13+7-WEEKDAY(C13) -> 0 | D13: GRAVITONIX | E13: 0 | F13: 0 | G13: 0 | H13: 0 | I13: 500 | J13: =SUM(E13:I13) -> 500
A14: =C14+7-WEEKDAY(C14) -> 0 | D14: HELIXCORP | E14: 0 | F14: 0 | G14: 0 | H14: 0 | I14: 500 | J14: =SUM(E14:I14) -> 500
A15: =C15+7-WEEKDAY(C15) -> 0 | D15: ILLUMIX | E15: 0 | F15: 0 | G15: 0 | H15: 0 | I15: 7500 | J15: =SUM(E15:I15) -> 7500
A16: =C16+7-WEEKDAY(C16) -> 45283 | B16: 43800 | C16: 45280 | D16: JADETECH | E16: 0 | F16: 43800 | G16: 0 | H16: 12700 | I16: 0 | J16: =SUM(E16:I16) -> 56500
A17: =C17+7-WEEKDAY(C17) -> 0 | D17: KRYSTALIX | E17: 0 | F17: 0 | G17: 0 | H17: 0 | I17: 900 | J17: =SUM(E17:I17) -> 900
A18: =C18+7-WEEKDAY(C18) -> 0 | D18: LUXORTECH | E18: 0 | F18: 0 | G18: 0 | H18: 15100 | I18: 0 | J18: =SUM(E18:I18) -> 15100
A19: =C19+7-WEEKDAY(C19) -> 0 | D19: MAGMACORP | E19: 0 | F19: 0 | G19: 0 | H19: 0 | I19: 1000 | J19: =SUM(E19:I19) -> 1000
A20: =C20+7-WEEKDAY(C20) -> 0 | D20: NEOTRONIX | E20: 0 | F20: 0 | G20: 0 | H20: 0 | I20: 700 | J20: =SUM(E20:I20) -> 700
A21: =C21+7-WEEKDAY(C21) -> 0 | D21: OMEGATECH | E21: 0 | F21: 0 | G21: 0 | H21: 0 | I21: 1000 | J21: =SUM(E21:I21) -> 1000
A22: =C22+7-WEEKDAY(C22) -> 45339 | B22: 250000 | C22: 45337 | D22: SONTECH | E22: 0 | F22: 0 | G22: 0 | H22: 0 | I22: 0 | J22: =SUM(E22:I22) -> 0
A23: =C23+7-WEEKDAY(C23) -> 0 | D23: QUARTZTECH | E23: 0 | F23: 0 | G23: 0 | H23: 0 | I23: 900 | J23: =SUM(E23:I23) -> 900
A24: =C24+7-WEEKDAY(C24) -> 0 | D24: REFLUXIX | E24: 0 | F24: 0 | G24: 0 | H24: 0 | I24: 500 | J24: =SUM(E24:I24) -> 500
A25: =C25+7-WEEKDAY(C25) -> 45276 | B25: 120000 | C25: 45275 | D25: SOLARIX | E25: 0 | F25: 132800 | G25: 8400 | H25: 1500 | I25: 90500 | J25: =SUM(E25:I25) -> 233200
A26: =C26+7-WEEKDAY(C26) -> 45311 | B26: 80000 | C26: 45306 | D26: SOLARIX | E26: 0 | F26: 0 | G26: 0 | H26: 0 | I26: 0 | J26: =SUM(E26:I26) -> 0
A27: =C27+7-WEEKDAY(C27) -> 0 | D27: TURBOTRON | E27: 0 | F27: 0 | G27: 0 | H27: 0 | I27: 23200 | J27: =SUM(E27:I27) -> 23200
A28: =C28+7-WEEKDAY(C28) -> 0 | D28: UNITYCORP | E28: 0 | F28: 0 | G28: 0 | H28: 0 | I28: 14000 | J28: =SUM(E28:I28) -> 14000
A29: =C29+7-WEEKDAY(C29) -> 0 | D29: VIBECH | E29: 0 | F29: 0 | G29: 0 | H29: 0 | I29: 0 | J29: =SUM(E29:I29) -> 0
A30: =C30+7-WEEKDAY(C30) -> 45325 | B30: 150000 | C30: 45321 | D30: VALEY X | E30: 0 | F30: 0 | G30: 0 | H30: 0 | I30: 150000 | J30: =SUM(E30:I30) -> 150000
A31: =C31+7-WEEKDAY(C31) -> 45283 | B31: 30700 | C31: 45280 | D31: XORTECH | E31: 30700 | F31: 0 | G31: 0 | H31: 0 | I31: 0 | J31: =SUM(E31:I31) -> 30700
A32: =C32+7-WEEKDAY(C32) -> 45269 | B32: 105000 | C32: 45264 | D32: YONIX | E32: 0 | F32: 900 | G32: 1000 | H32: 2000 | I32: 2600 | J32: =SUM(E32:I32) -> 6500
A33: =C33+7-WEEKDAY(C33) -> 45283 | B33: 38500 | C33: 45280 | D33: ZIONTECH | E33: 27000 | F33: 0 | G33: 11500 | H33: 0 | I33: 0 | J33: =SUM(E33:I33) -> 38500
A34: =C34+7-WEEKDAY(C34) -> 0 | D34: ASCENTIX | E34: 0 | F34: 0 | G34: 0 | H34: 0 | I34: 29600 | J34: =SUM(E34:I34) -> 29600
A35: =C35+7-WEEKDAY(C35) -> 0 | D35: BRILLIATECH | E35: 0 | F35: 0 | G35: 0 | H35: 0 | I35: 0 | J35: =SUM(E35:I35) -> 0
A36: =C36+7-WEEKDAY(C36) -> 45311 | B36: 50000 | C36: 45311 | D36: CRYSTALTECH | E36: 0 | F36: 0 | G36: 0 | H36: 0 | I36: 0 | J36: =SUM(E36:I36) -> 0
A37: =C37+7-WEEKDAY(C37) -> 45346 | B37: 150000 | C37: 45342 | D37: CRYSTALTECH | E37: 0 | F37: 0 | G37: 0 | H37: 0 | I37: 0 | J37: =SUM(E37:I37) -> 0
A38: =C38+7-WEEKDAY(C38) -> 45311 | B38: 66800 | C38: 45306 | D38: THJADETECH | E38: 0 | F38: 6500 | G38: 0 | H38: 2400 | I38: 64000 | J38: =SUM(E38:I38) -> 72900
A39: =C39+7-WEEKDAY(C39) -> 45346 | B39: 75000 | C39: 45342 | D39: ENERGIX | E39: 0 | F39: 0 | G39: 0 | H39: 0 | I39: 0 | J39: =SUM(E39:I39) -> 0
A40: =C40+7-WEEKDAY(C40) -> 0 | D40: FLUXATECH | E40: 0 | F40: 0 | G40: 0 | H40: 6500 | I40: 16100 | J40: =SUM(E40:I40) -> 22600
A41: =C41+7-WEEKDAY(C41) -> 0 | D41: GLOTECH | E41: 0 | F41: 0 | G41: 400 | H41: 3600 | I41: 27600 | J41: =SUM(E41:I41) -> 31600
A42: =C42+7-WEEKDAY(C42) -> 0 | D42: HALOCORP | E42: 0 | F42: 0 | G42: 0 | H42: 0 | I42: 70900 | J42: =SUM(E42:I42) -> 70900
A43: =C43+7-WEEKDAY(C43) -> 0 | D43: INTELIX | E43: 0 | F43: 700 | G43: 900 | H43: 2300 | I43: 6000 | J43: =SUM(E43:I43) -> 9900
A44: =C44+7-WEEKDAY(C44) -> 0 | D44: JUPITERIX | E44: 0 | F44: 0 | G44: 0 | H44: 15200 | I44: 15200 | J44: =SUM(E44:I44) -> 30400
A45: =C45+7-WEEKDAY(C45) -> 0 | D45: KOSMIX | E45: 0 | F45: 0 | G45: 0 | H45: 0 | I45: 9600 | J45: =SUM(E45:I45) -> 9600
A46: =C46+7-WEEKDAY(C46) -> 45283 | B46: 125100 | C46: 45280 | D46: ZJADETECH | E46: 0 | F46: 113200 | G46: 0 | H46: 2700 | I46: 9100 | J46: =SUM(E46:I46) -> 125000

Sheet Mapping
A1: Unique ID Match | B1: Category | C1: Category Check | E1: Unique ID Contains | F1: Category | G1: Category Check
A2: 5 CHECK | B2: Accounts Payable | C2: =INDEX('Forecast 1'!$B$9:$B$56,MATCH(Table2[[#This Row],[Category]],'Forecast 1'!$B$9:$B$56,0)) -> Accounts Payable | E2: BLITZIX | F2: Other Operating Outflows | G2: =INDEX('Forecast 1'!$B$9:$B$56,MATCH(Table3[[#This Row],[Category]],'Forecast 1'!$B$9:$B$56,0)) -> Other Operating Outflows
A3: 15 CHECK | B3: Accounts Payable | C3: =INDEX('Forecast 1'!$B$9:$B$56,MATCH(Table2[[#This Row],[Category]],'Forecast 1'!$B$9:$B$56,0)) -> Accounts Payable | E3: CAPITALONE | F3: Credit Cards | G3: =INDEX('Forecast 1'!$B$9:$B$56,MATCH(Table3[[#This Row],[Category]],'Forecast 1'!$B$9:$B$56,0)) -> Credit Cards
A4: 18 CHECK | B4: Accounts Payable | C4: =INDEX('Forecast 1'!$B$9:$B$56,MATCH(Table2[[#This Row],[Category]],'Forecast 1'!$B$9:$B$56,0)) -> Accounts Payable | E4: CHECK | F4: Payroll | G4: =INDEX('Forecast 1'!$B$9:$B$56,MATCH(Table3[[#This Row],[Category]],'Forecast 1'!$B$9:$B$56,0)) -> Payroll
A5: 69 CHECK | B5: Accounts Payable | C5: =INDEX('Forecast 1'!$B$9:$B$56,MATCH(Table2[[#This Row],[Category]],'Forecast 1'!$B$9:$B$56,0)) -> Accounts Payable | E5: CRYONIX | F5: Other Operating Outflows | G5: =INDEX('Forecast 1'!$B$9:$B$56,MATCH(Table3[[#This Row],[Category]],'Forecast 1'!$B$9:$B$56,0)) -> Other Operating Outflows
A6: 72 CHECK | B6: Accounts Payable | C6: =INDEX('Forecast 1'!$B$9:$B$56,MATCH(Table2[[#This Row],[Category]],'Forecast 1'!$B$9:$B$56,0)) -> Accounts Payable | E6: DEPOSIT | F6: Invoice Revenue Receipts | G6: =INDEX('Forecast 1'!$B$9:$B$56,MATCH(Table3[[#This Row],[Category]],'Forecast 1'!$B$9:$B$56,0)) -> Invoice Revenue Receipts
A7: 73 CHECK | B7: Accounts Payable | C7: =INDEX('Forecast 1'!$B$9:$B$56,MATCH(Table2[[#This Row],[Category]],'Forecast 1'!$B$9:$B$56,0)) -> Accounts Payable | E7: DYNACORP | F7: Other Operating Outflows | G7: =INDEX('Forecast 1'!$B$9:$B$56,MATCH(Table3[[#This Row],[Category]],'Forecast 1'!$B$9:$B$56,0)) -> Other Operating Outflows
A8: 136 CHECK | B8: Accounts Payable | C8: =INDEX('Forecast 1'!$B$9:$B$56,MATCH(Table2[[#This Row],[Category]],'Forecast 1'!$B$9:$B$56,0)) -> Accounts Payable | E8: ETERNIX | F8: Professional Fees | G8: =INDEX('Forecast 1'!$B$9:$B$56,MATCH(Table3[[#This Row],[Category]],'Forecast 1'!$B$9:$B$56,0)) -> Professional Fees
A9: 150 CHECK | B9: Accounts Payable | C9: =INDEX('Forecast 1'!$B$9:$B$56,MATCH(Table2[[#This Row],[Category]],'Forecast 1'!$B$9:$B$56,0)) -> Accounts Payable | E9: IRS | F9: Tax Distributions | G9: =INDEX('Forecast 1'!$B$9:$B$56,MATCH(Table3[[#This Row],[Category]],'Forecast 1'!$B$9:$B$56,0)) -> Tax Distributions
A10: 151 CHECK | B10: Accounts Payable | C10: =INDEX('Forecast 1'!$B$9:$B$56,MATCH(Table2[[#This Row],[Category]],'Forecast 1'!$B$9:$B$56,0)) -> Accounts Payable | E10: KRYPTONIX | F10: Dues & Subscriptions | G10: =INDEX('Forecast 1'!$B$9:$B$56,MATCH(Table3[[#This Row],[Category]],'Forecast 1'!$B$9:$B$56,0)) -> Dues & Subscriptions
A11: 193 CHECK | B11: Accounts Payable | C11: =INDEX('Forecast 1'!$B$9:$B$56,MATCH(Table2[[#This Row],[Category]],'Forecast 1'!$B$9:$B$56,0)) -> Accounts Payable | E11: DISCOVER | F11: Credit Cards | G11: =INDEX('Forecast 1'!$B$9:$B$56,MATCH(Table3[[#This Row],[Category]],'Forecast 1'!$B$9:$B$56,0)) -> Credit Cards
A12: 198 CHECK | B12: Accounts Payable | C12: =INDEX('Forecast 1'!$B$9:$B$56,MATCH(Table2[[#This Row],[Category]],'Forecast 1'!$B$9:$B$56,0)) -> Accounts Payable | E12: FRACTALIX | F12: Lease Payments | G12: =INDEX('Forecast 1'!$B$9:$B$56,MATCH(Table3[[#This Row],[Category]],'Forecast 1'!$B$9:$B$56,0)) -> Lease Payments
A13: 199 CHECK | B13: Accounts Payable | C13: =INDEX('Forecast 1'!$B$9:$B$56,MATCH(Table2[[#This Row],[Category]],'Forecast 1'!$B$9:$B$56,0)) -> Accounts Payable | E13: GLOWTECH | F13: Technology | G13: =INDEX('Forecast 1'!$B$9:$B$56,MATCH(Table3[[#This Row],[Category]],'Forecast 1'!$B$9:$B$56,0)) -> Technology
... A22: 345 CHECK | B22: Accounts Payable | C22: =INDEX('Forecast 1'!$B$9:$B$56,MATCH(Table2[[#This Row],[Category]],'Forecast 1'!$B$9:$B$56,0)) -> Accounts Payable | E22: IRIDIUMIX | F22: Other Non-operating Outflows | G22: =INDEX('Forecast 1'!$B$9:$B$56,MATCH(Table3[[#This Row],[Category]],'Forecast 1'!$B$9:$B$56,0)) -> Other Non-operating Outflows
E23: JUNCTIX | F23: Other Non-operating Outflows | G23: =INDEX('Forecast 1'!$B$9:$B$56,MATCH(Table3[[#This Row],[Category]],'Forecast 1'!$B$9:$B$56,0)) -> Other Non-operating Outflows

Sheet Error Checking
B2: =SUM(B3:B7) -> 0 | D2: Master Error Check Cell
B4: =SUM('Forecast 1'!14:14) -> 0 | D4: Forecast does not match the data
B5: =SUM(Summary!14:14) -> 0 | D5: Summary sheet mismatch

Sheet Formula Sheet
A1: Sharpe and Sortino
A2: Formula | B2: Explanation | C2: Sheet
A4: =_xlfn.FORMULATEXT('Bank Statement Export'!A2) -> =F2+7-WEEKDAY(F2) | B4: In excel weekday function uses numbers for days. So 1 = Sunday and 7 = Saturday. Cell F2, in bankstatment tab has date of 16/10/2023 and we have added 7 days which makes it to 23/10/2023. We need to remove two days to get to 21/10/2023. Therefore, weekday(F2), which is 16th Oct 23 if you check the calendar it will be Monday and hence as per weekday function it takes 2, therefore, from 23/10/2023 removes 2 leaving it to be 21/10/2023. Since, we are doing weekly cashflow, therefore, we need week ending on Saturday. | C4: =RIGHT(CELL("filename",'Bank Statement Export'!A1),LEN(CELL("filename",'Bank Statement Export'!A1))-FIND("]",CELL("filename",'Bank Statement Export'!A1))) -> Bank Statement Export
A8: =_xlfn.FORMULATEXT('Bank Statement Export'!C2) -> {=IFERROR(INDEX(Mapping!$B$2:$B$22,MATCH('Bank Statement Export'!B2,Mapping!$A$2:$A$22,0)),INDEX(Table3[Category],MATCH(TRUE,ISNUMBER(SEARCH(Table3[Unique ID Contains],B2)),0)))}
B10: First, if you have a new version of excel, then you can use XLOOKUP. But if anyone is using an older
B11: version then the above formula will be required. The above formula is a combination of two formulas
B12: 1st - remember on mapping tab there are two tables, 1st is for all accounts payable and second is for everything else.
B13: So, the 1st formula is matching the unique ID match to accounts payable table and looking for category which is accounts payable.
B14: So, for all those which are not in the accounts payable section will show an error. Therefore, we need the second part of the forumal which takes incharge if there is an error.
B15: The 2nd part of the formual is for the second table which is all the other ID's which are not accounts payable.
B16: Now, in the bank statement tab the unique ID is given as transaction no and then the description. But on the 2nd table there is only description and no transaction no. Therefore, we
B17: need an approximate match - so the formula is as below
B18: Index = Data what to looked for?
B19: Match(true,isnumber(search(..
B20: in excel when we only use search this come to numeric value for e.g. see below D20 marked yellow. The search function to look for excel is showing as numeric value.
B21: Excel | C21: =SEARCH("Excel",B21) -> 1
B22: But what we are finding is text and hence we need to use isnumber, what isnumber does is
B23: if the search result is number then TRUE
B24: if the search result is not number then FALSE
B25: So isnumber positions the TRUE and match function is finding the 1st TRUE.
C26: =RIGHT(CELL("filename",'Bank Statement Export'!A1),LEN(CELL("filename",'Bank Statement Export'!A1))-FIND("]",CELL("filename",'Bank Statement Export'!A1))) -> Bank Statement Export
A30: =_xlfn.FORMULATEXT(Summary!V7) -> =MAX('Forecast 1'!7:7) | B30: In the summary tab we want to pull data from the forecast tab. As the new data keeps coming in we want the summary tab to pick the last data. Summary tab is to show the summary of the forecast and it should auto update from forecast tab. | C30: =RIGHT(CELL("filename",Summary!A1),LEN(CELL("filename",Summary!A1))-FIND("]",CELL("filename",Summary!A1))) -> Summary
